Workbook

Sheet 컬럼정하기_필수 속성값 정리
A1: 컬럼정하기
A2: 품명 | B2: Pneumatic Cylinder | C2: AC Geared Motor | D2: Protection Relay
A3: 속성1 | B3: Model-1 | C3: Model-1 | D3: Model-1
A4: 속성2 | B4: Maker Name-1 | C4: Maker Name-1 | D4: Maker Name-1
A5: 속성3 | B5: Bore Size | C5: Insulation Class | D5: Coil Voltage
A6: 속성4 | B6: Rod Diameter | C6: IP Class | D6: Setting Tap Range
A7: 속성5 | B7: Stroke Length | C7: Number of Poles | D7: Setting Time Range
A8: 속성6 | B8: Pressure Rating | C8: Capacity
A9: 속성7 | C9: Voltage
A10: 속성8 | C10: Frequency
A11: 속성9 | C11: Speed Rating
A12: 속성10 | C12: Speed Reduction Ratio

Sheet Q코드, pdf 파일명 50코드
A1: Q-Code | B1: 그룹사명 | C1: 품명 | D1: Model-1 첨부파일명
A2: Q4675156 | B2: 포스코 | C2: Pneumatic Cylinder | D2: _SMC_CDJ2F16-25Z-A93L-B_CATALOG_20250526104947035.pdf
A3: Q4675089 | B3: 포스코 | C3: Pneumatic Cylinder | D3: _SMC_CDM2B25-25Z-A93L_CATALOG_20250526104540071.pdf
A4: Q4675326 | B4: 포스코 | C4: Pneumatic Cylinder | D4: _SMC_CDQSD16-25DM-A93L_CATALOG_20250528132218077.pdf
A5: Q4675164 | B5: 포스코 | C5: Pneumatic Cylinder | D5: _SMC_CDUK25-30D-A93L_CATALOG_20250526111558421.pdf
A6: Q4683457 | B6: 포스코 | C6: Pneumatic Cylinder | D6: 250812_A2_제선설비부_물품등록자료_T1663035 2FINEX RTO Pneumatic Cylinder CA2B100-300Z Catalog_20250812185026609.pdf
A7: Q4501288 | B7: 포스코 | C7: Pneumatic Cylinder | D7: CS1CN160-100-CJAD0046(업그레이드 품)[1CGL 5.6.7 TB]_20220114112323273.pdf
A8: Q4550786 | B8: 포스코 | C8: Pneumatic Cylinder | D8: ACM_20220111135135572.pdf
A9: Q4549165 | B9: 포스코 | C9: Pneumatic Cylinder | D9: ACM카달로그_20220119165138547.pdf
A10: Q4655802 | B10: 포스코 | C10: Pneumatic Cylinder | D10: Pneumatic cylinder CDA2T80-KRT09KO-200Z-A54L3 SMC_20241112142525736.pdf
A11: Q4627759 | B11: 포스코 | C11: Pneumatic Cylinder | D11: CA2Y 카다로그_20240122135108312.pdf
A12: Q4669390 | B12: 포스코 | C12: Pneumatic Cylinder | D12: CDS1CN125-KRD0368-350-A54L 도면_20250325141804318.pdf
... A73: Q3507398 | B73: 포스코퓨처엠 | C73: Protection Relay | D73: A시리즈 개별 카다로그 (1)_20250210132526349.pdf

Sheet 시스템 읽어올 값.
A1: Q-Code | B1: 그룹사명 | C1: 품명 | D1: Model-1 | E1: Maker Name-1 | F1: Bore Size | G1: Rod Diameter | H1: Stroke Length | I1: Pressure Rating | J1: 정답여부 | K1: Model-1 첨부URL1
A2: Q4675156 | B2: 포스코 | C2: Pneumatic Cylinder | D2: =VLOOKUP(A2,'실린더 상세사양값. 80'!$A$1:$AP$81,40,0) -> CDJ2F16-25Z-A93L-B | E2: =VLOOKUP(A2,'실린더 상세사양값. 80'!$A$1:$BT$81,42,0) -> SMC | F2: =VLOOKUP(A2,'실린더 상세사양값. 80'!$A$1:$CG$81,32,0) -> 16 | G2: =VLOOKUP(A2,'실린더 상세사양값. 80'!$A$1:$CG$81,34,0) -> 16 | H2: =VLOOKUP(A2,'실린더 상세사양값. 80'!$A$1:$CG$81,36,0) -> 25 | I2: =VLOOKUP(A2,'실린더 상세사양값. 80'!$A$1:$CG$81,38,0) -> 7 | J2: 정답 | K2: https://www.smckorea.co.kr/
A3: Q4675089 | B3: 포스코 | C3: Pneumatic Cylinder | D3: =VLOOKUP(A3,'실린더 상세사양값. 80'!$A$1:$AP$81,40,0) -> CDM2B25-25Z-A93L | E3: =VLOOKUP(A3,'실린더 상세사양값. 80'!$A$1:$BT$81,42,0) -> SMC | F3: =VLOOKUP(A3,'실린더 상세사양값. 80'!$A$1:$CG$81,32,0) -> 25 | G3: =VLOOKUP(A3,'실린더 상세사양값. 80'!$A$1:$CG$81,36,0) -> 25 | H3: =VLOOKUP(A3,'실린더 상세사양값. 80'!$A$1:$CG$81,36,0) -> 25 | I3: =VLOOKUP(A3,'실린더 상세사양값. 80'!$A$1:$CG$81,38,0) -> 10 | J3: 정답 | K3: https://www.smckorea.co.kr/
A4: Q4675326 | B4: 포스코 | C4: Pneumatic Cylinder | D4: =VLOOKUP(A4,'실린더 상세사양값. 80'!$A$1:$AP$81,40,0) -> CDQSD16-25DM-A93L | E4: =VLOOKUP(A4,'실린더 상세사양값. 80'!$A$1:$BT$81,42,0) -> SMC | F4: =VLOOKUP(A4,'실린더 상세사양값. 80'!$A$1:$CG$81,32,0) -> 16 | G4: =VLOOKUP(A4,'실린더 상세사양값. 80'!$A$1:$CG$81,36,0) -> 25 | H4: =VLOOKUP(A4,'실린더 상세사양값. 80'!$A$1:$CG$81,36,0) -> 25 | I4: =VLOOKUP(A4,'실린더 상세사양값. 80'!$A$1:$CG$81,38,0) -> 10 | J4: 정답 | K4: https://www.smckorea.co.kr/
A5: Q4675164 | B5: 포스코 | C5: Pneumatic Cylinder | D5: =VLOOKUP(A5,'실린더 상세사양값. 80'!$A$1:$AP$81,40,0) -> CDUK25-30D-A93L | E5: =VLOOKUP(A5,'실린더 상세사양값. 80'!$A$1:$BT$81,42,0) -> SMC | F5: =VLOOKUP(A5,'실린더 상세사양값. 80'!$A$1:$CG$81,32,0) -> 25 | G5: =VLOOKUP(A5,'실린더 상세사양값. 80'!$A$1:$CG$81,36,0) -> 30 | H5: =VLOOKUP(A5,'실린더 상세사양값. 80'!$A$1:$CG$81,36,0) -> 30 | I5: =VLOOKUP(A5,'실린더 상세사양값. 80'!$A$1:$CG$81,38,0) -> 7 | J5: 정답 | K5: https://www.smckorea.co.kr/
A6: Q4683457 | B6: 포스코 | C6: Pneumatic Cylinder | D6: =VLOOKUP(A6,'실린더 상세사양값. 80'!$A$1:$AP$81,40,0) -> CA2B100-300Z | E6: =VLOOKUP(A6,'실린더 상세사양값. 80'!$A$1:$BT$81,42,0) -> SMC | F6: =VLOOKUP(A6,'실린더 상세사양값. 80'!$A$1:$CG$81,32,0) -> 100 | G6: =VLOOKUP(A6,'실린더 상세사양값. 80'!$A$1:$CG$81,36,0) -> 300 | H6: =VLOOKUP(A6,'실린더 상세사양값. 80'!$A$1:$CG$81,36,0) -> 300 | I6: =VLOOKUP(A6,'실린더 상세사양값. 80'!$A$1:$CG$81,38,0) -> 10 | J6: 정답 | K6: https://www.smcpneumatics.com/CA2B100-300Z.html
A7: Q4501288 | B7: 포스코 | C7: Pneumatic Cylinder | D7: =VLOOKUP(A7,'실린더 상세사양값. 80'!$A$1:$AP$81,40,0) -> CS1CN160-100-CJAD0046 | E7: =VLOOKUP(A7,'실린더 상세사양값. 80'!$A$1:$BT$81,42,0) -> SMC | F7: =VLOOKUP(A7,'실린더 상세사양값. 80'!$A$1:$CG$81,32,0) -> 160 | G7: =VLOOKUP(A7,'실린더 상세사양값. 80'!$A$1:$CG$81,36,0) -> 100 | H7: =VLOOKUP(A7,'실린더 상세사양값. 80'!$A$1:$CG$81,36,0) -> 100 | I7: =VLOOKUP(A7,'실린더 상세사양값. 80'!$A$1:$CG$81,38,0) -> 0 | J7: 정답 | K7: http://www.smcpneumatics.com/pdfs/smc/70ACS1.pdf
A8: Q4550786 | B8: 포스코 | C8: Pneumatic Cylinder | D8: =VLOOKUP(A8,'실린더 상세사양값. 80'!$A$1:$AP$81,40,0) -> ACM-N-FA50-S425 | E8: =VLOOKUP(A8,'실린더 상세사양값. 80'!$A$1:$BT$81,42,0) -> KCC | F8: =VLOOKUP(A8,'실린더 상세사양값. 80'!$A$1:$CG$81,32,0) -> 50 | G8: =VLOOKUP(A8,'실린더 상세사양값. 80'!$A$1:$CG$81,36,0) -> 425 | H8: =VLOOKUP(A8,'실린더 상세사양값. 80'!$A$1:$CG$81,36,0) -> 425 | I8: =VLOOKUP(A8,'실린더 상세사양값. 80'!$A$1:$CG$81,38,0) -> 10 | J8: 정답 | K8: https://www.kccpr.com/bbs/search.php?url=https%3A%2F%2Fwww.kccpr.com%2Fbbs%2Fsearch.php&stx=ACM
A9: Q4549165 | B9: 포스코 | C9: Pneumatic Cylinder | D9: =VLOOKUP(A9,'실린더 상세사양값. 80'!$A$1:$AP$81,40,0) -> ACM-N-TC80-S125-J | E9: =VLOOKUP(A9,'실린더 상세사양값. 80'!$A$1:$BT$81,42,0) -> KCC | F9: =VLOOKUP(A9,'실린더 상세사양값. 80'!$A$1:$CG$81,32,0) -> 80 | G9: =VLOOKUP(A9,'실린더 상세사양값. 80'!$A$1:$CG$81,36,0) -> 125 | H9: =VLOOKUP(A9,'실린더 상세사양값. 80'!$A$1:$CG$81,36,0) -> 125 | I9: =VLOOKUP(A9,'실린더 상세사양값. 80'!$A$1:$CG$81,38,0) -> 10 | J9: 정답 | K9: https://www.kccpr.com/bbs/search.php?url=https%3A%2F%2Fwww.kccpr.com%2Fbbs%2Fsearch.php&stx=ACM
A10: Q4655802 | B10: 포스코 | C10: Pneumatic Cylinder | D10: =VLOOKUP(A10,'실린더 상세사양값. 80'!$A$1:$AP$81,40,0) -> CDA2T80-KRT09KO-200Z-A54L3 | E10: =VLOOKUP(A10,'실린더 상세사양값. 80'!$A$1:$BT$81,42,0) -> SMC | F10: =VLOOKUP(A10,'실린더 상세사양값. 80'!$A$1:$CG$81,32,0) -> 80 | G10: =VLOOKUP(A10,'실린더 상세사양값. 80'!$A$1:$CG$81,36,0) -> 200 | H10: =VLOOKUP(A10,'실린더 상세사양값. 80'!$A$1:$CG$81,36,0) -> 200 | I10: =VLOOKUP(A10,'실린더 상세사양값. 80'!$A$1:$CG$81,38,0) -> 10 | J10: 정답 | K10: https://www.smckorea.co.kr/ppis/data/catalog/CA2-Z.pdf
A11: Q4627759 | B11: 포스코 | C11: Pneumatic Cylinder | D11: =VLOOKUP(A11,'실린더 상세사양값. 80'!$A$1:$AP$81,40,0) -> CA2YT80-150Z-W | E11: =VLOOKUP(A11,'실린더 상세사양값. 80'!$A$1:$BT$81,42,0) -> SMC | F11: =VLOOKUP(A11,'실린더 상세사양값. 80'!$A$1:$CG$81,32,0) -> 80 | G11: =VLOOKUP(A11,'실린더 상세사양값. 80'!$A$1:$CG$81,36,0) -> 150 | H11: =VLOOKUP(A11,'실린더 상세사양값. 80'!$A$1:$CG$81,36,0) -> 150 | I11: =VLOOKUP(A11,'실린더 상세사양값. 80'!$A$1:$CG$81,38,0) -> 0 | J11: 정답
A12: Q4669390 | B12: 포스코 | C12: Pneumatic Cylinder | D12: =VLOOKUP(A12,'실린더 상세사양값. 80'!$A$1:$AP$81,40,0) -> CDS1CN125-KRD0368-350-A54L | E12: =VLOOKUP(A12,'실린더 상세사양값. 80'!$A$1:$BT$81,42,0) -> SMC | F12: =VLOOKUP(A12,'실린더 상세사양값. 80'!$A$1:$CG$81,32,0) -> 125 | G12: =VLOOKUP(A12,'실린더 상세사양값. 80'!$A$1:$CG$81,36,0) -> 350 | H12: =VLOOKUP(A12,'실린더 상세사양값. 80'!$A$1:$CG$81,36,0) -> 350 | I12: =VLOOKUP(A12,'실린더 상세사양값. 80'!$A$1:$CG$81,38,0) -> 15 | J12: 정답 | K12: https://www.smckorea.co.kr/ppis/data/catalog/CS1.pdf
A13: Q4629827 | B13: 포스코 | C13: Pneumatic Cylinder | D13: =VLOOKUP(A13,'실린더 상세사양값. 80'!$A$1:$AP$81,40,0) -> CDS1TN125-KRD0368-500-Z73L | E13: =VLOOKUP(A13,'실린더 상세사양값. 80'!$A$1:$BT$81,42,0) -> SMC | F13: =VLOOKUP(A13,'실린더 상세사양값. 80'!$A$1:$CG$81,32,0) -> 125 | G13: =VLOOKUP(A13,'실린더 상세사양값. 80'!$A$1:$CG$81,36,0) -> 500 | H13: =VLOOKUP(A13,'실린더 상세사양값. 80'!$A$1:$CG$81,36,0) -> 500 | I13: =VLOOKUP(A13,'실린더 상세사양값. 80'!$A$1:$CG$81,38,0) -> 9.7 | J13: 정답
A14: Q4627207 | B14: 포스코 | C14: Pneumatic Cylinder | D14: =VLOOKUP(A14,'실린더 상세사양값. 80'!$A$1:$AP$81,40,0) -> CDS2T200-200-CJCD0039 | E14: =VLOOKUP(A14,'실린더 상세사양값. 80'!$A$1:$BT$81,42,0) -> SMC | F14: =VLOOKUP(A14,'실린더 상세사양값. 80'!$A$1:$CG$81,32,0) -> 200 | G14: =VLOOKUP(A14,'실린더 상세사양값. 80'!$A$1:$CG$81,36,0) -> 220 | H14: =VLOOKUP(A14,'실린더 상세사양값. 80'!$A$1:$CG$81,36,0) -> 220 | I14: =VLOOKUP(A14,'실린더 상세사양값. 80'!$A$1:$CG$81,38,0) -> 16 | J14: 정답
A15: Q4636670 | B15: 포스코 | C15: Pneumatic Cylinder | D15: =VLOOKUP(A15,'실린더 상세사양값. 80'!$A$1:$AP$81,40,0) -> CDS2T320-250-CJCD0239 | E15: =VLOOKUP(A15,'실린더 상세사양값. 80'!$A$1:$BT$81,42,0) -> SMC | F15: =VLOOKUP(A15,'실린더 상세사양값. 80'!$A$1:$CG$81,32,0) -> 320 | G15: =VLOOKUP(A15,'실린더 상세사양값. 80'!$A$1:$CG$81,36,0) -> 250 | H15: =VLOOKUP(A15,'실린더 상세사양값. 80'!$A$1:$CG$81,36,0) -> 250 | I15: =VLOOKUP(A15,'실린더 상세사양값. 80'!$A$1:$CG$81,38,0) -> 0 | J15: 정답
A16: Q4680486 | B16: 포스코 | C16: Pneumatic Cylinder | D16: =VLOOKUP(A16,'실린더 상세사양값. 80'!$A$1:$AP$81,40,0) -> CG1DN63-64-CJD00567 | E16: =VLOOKUP(A16,'실린더 상세사양값. 80'!$A$1:$BT$81,42,0) -> SMC | F16: =VLOOKUP(A16,'실린더 상세사양값. 80'!$A$1:$CG$81,32,0) -> 63 | G16: =VLOOKUP(A16,'실린더 상세사양값. 80'!$A$1:$CG$81,36,0) -> 64 | H16: =VLOOKUP(A16,'실린더 상세사양값. 80'!$A$1:$CG$81,36,0) -> 64 | I16: =VLOOKUP(A16,'실린더 상세사양값. 80'!$A$1:$CG$81,38,0) -> 10 | J16: 정답 | K16: https://www.smckorea.co.kr/ppis/data/domyun/CJD00567-AP..pdf
A17: Q4697437 | B17: 포스코 | C17: Pneumatic Cylinder | D17: =VLOOKUP(A17,'실린더 상세사양값. 80'!$A$1:$AP$81,40,0) -> CDS1TN200-246K-A54 | E17: =VLOOKUP(A17,'실린더 상세사양값. 80'!$A$1:$BT$81,42,0) -> SMC | F17: =VLOOKUP(A17,'실린더 상세사양값. 80'!$A$1:$CG$81,32,0) -> 200 | G17: =VLOOKUP(A17,'실린더 상세사양값. 80'!$A$1:$CG$81,36,0) -> 246 | H17: =VLOOKUP(A17,'실린더 상세사양값. 80'!$A$1:$CG$81,36,0) -> 246 | I17: =VLOOKUP(A17,'실린더 상세사양값. 80'!$A$1:$CG$81,38,0) -> 9999 | J17: 정답
A18: Q4371330 | B18: 포스코 | C18: Pneumatic Cylinder | D18: =VLOOKUP(A18,'실린더 상세사양값. 80'!$A$1:$AP$81,40,0) -> CDQ2B50-55Z-DCN446GN | E18: =VLOOKUP(A18,'실린더 상세사양값. 80'!$A$1:$BT$81,42,0) -> SMC | F18: =VLOOKUP(A18,'실린더 상세사양값. 80'!$A$1:$CG$81,32,0) -> 50 | G18: =VLOOKUP(A18,'실린더 상세사양값. 80'!$A$1:$CG$81,36,0) -> 9999 | H18: =VLOOKUP(A18,'실린더 상세사양값. 80'!$A$1:$CG$81,36,0) -> 9999 | I18: =VLOOKUP(A18,'실린더 상세사양값. 80'!$A$1:$CG$81,38,0) -> 10 | J18: 정답 | K18: http://www.smckorea.co.kr/esales/data/sangpum/catalog/CQ2-Z.pdf
A19: Q4037566 | B19: 포스코 | C19: Pneumatic Cylinder | D19: =VLOOKUP(A19,'실린더 상세사양값. 80'!$A$1:$AP$81,40,0) -> CDS1TN140-KRT04KO-710-XC14 +D-A54Z(2EA)+BT-12(2EA) | E19: =VLOOKUP(A19,'실린더 상세사양값. 80'!$A$1:$BT$81,42,0) -> SMC | F19: =VLOOKUP(A19,'실린더 상세사양값. 80'!$A$1:$CG$81,32,0) -> 140 | G19: =VLOOKUP(A19,'실린더 상세사양값. 80'!$A$1:$CG$81,36,0) -> 710 | H19: =VLOOKUP(A19,'실린더 상세사양값. 80'!$A$1:$CG$81,36,0) -> 710 | I19: =VLOOKUP(A19,'실린더 상세사양값. 80'!$A$1:$CG$81,38,0) -> 10 | J19: 정답 | K19: http://www.smckorea.co.kr/homepage/ver3.5/product/catalogue_sub_detail.asp?no=914#
A20: Q4521203 | B20: 포스코 | C20: Pneumatic Cylinder | D20: =VLOOKUP(A20,'실린더 상세사양값. 80'!$A$1:$AP$81,40,0) -> C96SD100-320C | E20: =VLOOKUP(A20,'실린더 상세사양값. 80'!$A$1:$BT$81,42,0) -> SMC | F20: =VLOOKUP(A20,'실린더 상세사양값. 80'!$A$1:$CG$81,32,0) -> 100 | G20: =VLOOKUP(A20,'실린더 상세사양값. 80'!$A$1:$CG$81,36,0) -> 320 | H20: =VLOOKUP(A20,'실린더 상세사양값. 80'!$A$1:$CG$81,36,0) -> 320 | I20: =VLOOKUP(A20,'실린더 상세사양값. 80'!$A$1:$CG$81,38,0) -> 10 | J20: 정답 | K20: http://www.smckorea.co.kr/ppis/data/catalog/C96.pdf
A21: Q4511190 | B21: 포스코 | C21: Pneumatic Cylinder | D21: =VLOOKUP(A21,'실린더 상세사양값. 80'!$A$1:$AP$81,40,0) -> CDA2T100-KRT09KO-125Z-W-A96L | E21: =VLOOKUP(A21,'실린더 상세사양값. 80'!$A$1:$BT$81,42,0) -> SMC | F21: =VLOOKUP(A21,'실린더 상세사양값. 80'!$A$1:$CG$81,32,0) -> 100 | G21: =VLOOKUP(A21,'실린더 상세사양값. 80'!$A$1:$CG$81,36,0) -> 125 | H21: =VLOOKUP(A21,'실린더 상세사양값. 80'!$A$1:$CG$81,36,0) -> 125 | I21: =VLOOKUP(A21,'실린더 상세사양값. 80'!$A$1:$CG$81,38,0) -> 0 | J21: 정답 | K21: http://www.smckorea.co.kr/ppis/data/catalog/CA2-Z.pdf
A22: Q4520279 | B22: 포스코 | C22: Pneumatic Cylinder | D22: =VLOOKUP(A22,'실린더 상세사양값. 80'!$A$1:$AP$81,40,0) -> CDG1UN50TF-170-CJZH0846 | E22: =VLOOKUP(A22,'실린더 상세사양값. 80'!$A$1:$BT$81,42,0) -> SMC | F22: =VLOOKUP(A22,'실린더 상세사양값. 80'!$A$1:$CG$81,32,0) -> 50 | G22: =VLOOKUP(A22,'실린더 상세사양값. 80'!$A$1:$CG$81,36,0) -> 170 | H22: =VLOOKUP(A22,'실린더 상세사양값. 80'!$A$1:$CG$81,36,0) -> 170 | I22: =VLOOKUP(A22,'실린더 상세사양값. 80'!$A$1:$CG$81,38,0) -> 10 | J22: 정답 | K22: http://www.smckorea.co.kr/ppis/data/catalog/CG1-Z.pdf
A23: Q4508586 | B23: 포스코 | C23: Pneumatic Cylinder | D23: =VLOOKUP(A23,'실린더 상세사양값. 80'!$A$1:$AP$81,40,0) -> CDM2E32-200Z-NW-A93L | E23: =VLOOKUP(A23,'실린더 상세사양값. 80'!$A$1:$BT$81,42,0) -> SMC | F23: =VLOOKUP(A23,'실린더 상세사양값. 80'!$A$1:$CG$81,32,0) -> 9999 | G23: =VLOOKUP(A23,'실린더 상세사양값. 80'!$A$1:$CG$81,36,0) -> 9999 | H23: =VLOOKUP(A23,'실린더 상세사양값. 80'!$A$1:$CG$81,36,0) -> 9999 | I23: =VLOOKUP(A23,'실린더 상세사양값. 80'!$A$1:$CG$81,38,0) -> 0 | J23: 정답 | K23: http://www.smckorea.co.kr/ppis/data/catalog/CM2-Z.pdf
A24: Q4520278 | B24: 포스코 | C24: Pneumatic Cylinder | D24: =VLOOKUP(A24,'실린더 상세사양값. 80'!$A$1:$AP$81,40,0) -> CDM2E40TF-160Z-XC6 | E24: =VLOOKUP(A24,'실린더 상세사양값. 80'!$A$1:$BT$81,42,0) -> SMC | F24: =VLOOKUP(A24,'실린더 상세사양값. 80'!$A$1:$CG$81,32,0) -> 40 | G24: =VLOOKUP(A24,'실린더 상세사양값. 80'!$A$1:$CG$81,36,0) -> 160 | H24: =VLOOKUP(A24,'실린더 상세사양값. 80'!$A$1:$CG$81,36,0) -> 160 | I24: =VLOOKUP(A24,'실린더 상세사양값. 80'!$A$1:$CG$81,38,0) -> 10 | J24: 정답 | K24: http://www.smckorea.co.kr/ppis/data/catalog/CM2-Z.pdf
A25: Q4507377 | B25: 포스코 | C25: Pneumatic Cylinder | D25: =VLOOKUP(A25,'실린더 상세사양값. 80'!$A$1:$AP$81,40,0) -> CDQMB50-10-A72 | E25: =VLOOKUP(A25,'실린더 상세사양값. 80'!$A$1:$BT$81,42,0) -> SMC | F25: =VLOOKUP(A25,'실린더 상세사양값. 80'!$A$1:$CG$81,32,0) -> 50 | G25: =VLOOKUP(A25,'실린더 상세사양값. 80'!$A$1:$CG$81,36,0) -> 10 | H25: =VLOOKUP(A25,'실린더 상세사양값. 80'!$A$1:$CG$81,36,0) -> 10 | I25: =VLOOKUP(A25,'실린더 상세사양값. 80'!$A$1:$CG$81,38,0) -> 10 | J25: 정답 | K25: http://www.smckorea.co.kr/ppis/data/catalog/CQM.pdf
A26: Q3507377 | B26: 포스코 | C26: Pneumatic Cylinder | D26: CDS2T3200-250-CJCD0239 | E26: SMC | F26: 50 | G26: 10 | H26: 10 | I26: 10 | J26: 오류치 | K26: https://www.smckorea.co.kr/ppis/data/catalog/CA2-Z.pdf
A27: Q3507378 | B27: 포스코 | C27: Pneumatic Cylinder | D27: CPS2T3200-250-CJCD0235 | E27: SMC | F27: 51 | G27: 11 | H27: 12 | I27: 19 | J27: 오류치 | K27: https://www.smckorea.co.kr/ppis/data/catalog/CA2-Z.pdf
A28: Q3507379 | B28: 포스코 | C28: Pneumatic Cylinder | D28: CDS2T3200-250-CJCD0240 | E28: SMC | F28: 50 | G28: 32 | H28: 10 | I28: 11 | J28: 오류치 | K28: https://www.smckorea.co.kr/ppis/data/catalog/CA2-Z.pdf
A29: Q3507380 | B29: 포스코 | C29: Pneumatic Cylinder | D29: CPS2T3200-250-CJCD0236 | E29: SMC | F29: 51 | G29: 35 | H29: 7 | I29: 12 | J29: 오류치 | K29: https://www.smckorea.co.kr/ppis/data/catalog/CA2-Z.pdf
A30: Q3507381 | B30: 포스코 | C30: Pneumatic Cylinder | D30: CDS2T3200-250-CJCD0241 | E30: SMC | F30: 50 | G30: 10 | H30: 10 | I30: 14 | J30: 오류치 | K30: https://www.smckorea.co.kr/ppis/data/catalog/CA2-Z.pdf
A31: Q3507382 | B31: 포스코 | C31: Pneumatic Cylinder | D31: CPS2T3200-250-CJCD0237 | E31: SMC | F31: 51 | G31: 11 | H31: 42 | I31: 15 | J31: 오류치 | K31: https://www.smckorea.co.kr/ppis/data/catalog/CA2-Z.pdf
A32: Q3507383 | B32: 포스코 | C32: Pneumatic Cylinder | D32: CDS2T3200-250-CJCD0242 | E32: SMC | F32: 50 | G32: 11 | H32: 10 | I32: 123 | J32: 오류치 | K32: https://www.smckorea.co.kr/ppis/data/catalog/CA2-Z.pdf
A35: Q-Code | B35: 그룹사명 | C35: 품명 | D35: Model-1 | E35: Maker Name-1 | F35: Insulation Class | G35: IP Class | H35: Number of Poles | I35: Capacity | J35: Voltage | K35: Frequency | L35: Speed Rating | M35: Speed Reduction Ratio | N35: 정답여부
A36: Q4632857 | B36: 포스코 | C36: AC Geared Motor | D36: =VLOOKUP(A36,'모터 상세사양값'!$A$1:$CG$27,28,0) -> DHHM8-9175-43 | E36: =VLOOKUP(A36,'모터 상세사양값'!$A$1:$CG$27,30,0) -> HANA MECHANICAL&ELECTRICAL | F36: =VLOOKUP(A36,'모터 상세사양값'!$A$1:$CG$27,52,0) -> F | G36: =VLOOKUP(A36,'모터 상세사양값'!$A$1:$CG$27,54,0) -> 0 | H36: =VLOOKUP(A36,'모터 상세사양값'!$A$1:$CG$27,56,0) -> 4 | I36: =VLOOKUP(A36,'모터 상세사양값'!$A$1:$CG$27,58,0) -> 5.5 | J36: =VLOOKUP(A36,'모터 상세사양값'!$A$1:$CG$27,60,0) -> 440 | K36: =VLOOKUP(A36,'모터 상세사양값'!$A$1:$CG$27,62,0) -> 60 | L36: =VLOOKUP(A36,'모터 상세사양값'!$A$1:$CG$27,64,0) -> 1780 | M36: =VLOOKUP(A36,'모터 상세사양값'!$A$1:$CG$27,66,0) -> 1/43 | N36: 정답
A37: Q4636710 | B37: 포스코 | C37: AC Geared Motor | D37: =VLOOKUP(A37,'모터 상세사양값'!$A$1:$CG$27,28,0) -> R47 DRN100L4 | E37: =VLOOKUP(A37,'모터 상세사양값'!$A$1:$CG$27,30,0) -> SEW | F37: =VLOOKUP(A37,'모터 상세사양값'!$A$1:$CG$27,52,0) -> 155F | G37: =VLOOKUP(A37,'모터 상세사양값'!$A$1:$CG$27,54,0) -> IP54 | H37: =VLOOKUP(A37,'모터 상세사양값'!$A$1:$CG$27,56,0) -> 4 | I37: =VLOOKUP(A37,'모터 상세사양값'!$A$1:$CG$27,58,0) -> 2.2 | J37: =VLOOKUP(A37,'모터 상세사양값'!$A$1:$CG$27,60,0) -> 254/440 | K37: =VLOOKUP(A37,'모터 상세사양값'!$A$1:$CG$27,62,0) -> 60 | L37: =VLOOKUP(A37,'모터 상세사양값'!$A$1:$CG$27,64,0) -> 1765/174 | M37: =VLOOKUP(A37,'모터 상세사양값'!$A$1:$CG$27,66,0) -> 1/10.15 | N37: 정답
A38: Q4688576 | B38: 포스코 | C38: AC Geared Motor | D38: =VLOOKUP(A38,'모터 상세사양값'!$A$1:$CG$27,28,0) -> RPH | E38: =VLOOKUP(A38,'모터 상세사양값'!$A$1:$CG$27,30,0) -> HYOSUNG | F38: =VLOOKUP(A38,'모터 상세사양값'!$A$1:$CG$27,52,0) -> F | G38: =VLOOKUP(A38,'모터 상세사양값'!$A$1:$CG$27,54,0) -> IP55 | H38: =VLOOKUP(A38,'모터 상세사양값'!$A$1:$CG$27,56,0) -> 4 | I38: =VLOOKUP(A38,'모터 상세사양값'!$A$1:$CG$27,58,0) -> 0.75 | J38: =VLOOKUP(A38,'모터 상세사양값'!$A$1:$CG$27,60,0) -> 440 | K38: =VLOOKUP(A38,'모터 상세사양값'!$A$1:$CG$27,62,0) -> 60 | L38: =VLOOKUP(A38,'모터 상세사양값'!$A$1:$CG$27,64,0) -> 1735/35 | M38: =VLOOKUP(A38,'모터 상세사양값'!$A$1:$CG$27,66,0) -> 1/50 | N38: 정답
A39: Q4688760 | B39: 포스코 | C39: AC Geared Motor | D39: =VLOOKUP(A39,'모터 상세사양값'!$A$1:$CG$27,28,0) -> RPH | E39: =VLOOKUP(A39,'모터 상세사양값'!$A$1:$CG$27,30,0) -> HYOSUNG | F39: =VLOOKUP(A39,'모터 상세사양값'!$A$1:$CG$27,52,0) -> F | G39: =VLOOKUP(A39,'모터 상세사양값'!$A$1:$CG$27,54,0) -> IP55 | H39: =VLOOKUP(A39,'모터 상세사양값'!$A$1:$CG$27,56,0) -> 4 | I39: =VLOOKUP(A39,'모터 상세사양값'!$A$1:$CG$27,58,0) -> 1.5 | J39: =VLOOKUP(A39,'모터 상세사양값'!$A$1:$CG$27,60,0) -> 440 | K39: =VLOOKUP(A39,'모터 상세사양값'!$A$1:$CG$27,62,0) -> 60 | L39: =VLOOKUP(A39,'모터 상세사양값'!$A$1:$CG$27,64,0) -> 1750/29.2 | M39: =VLOOKUP(A39,'모터 상세사양값'!$A$1:$CG$27,66,0) -> 60 | N39: 정답
A40: Q4622968 | B40: 포스코 | C40: AC Geared Motor | D40: =VLOOKUP(A40,'모터 상세사양값'!$A$1:$CG$27,28,0) -> HLA020101057587 | E40: =VLOOKUP(A40,'모터 상세사양값'!$A$1:$CG$27,30,0) -> HYOSUNG | F40: =VLOOKUP(A40,'모터 상세사양값'!$A$1:$CG$27,52,0) -> F | G40: =VLOOKUP(A40,'모터 상세사양값'!$A$1:$CG$27,54,0) -> TE | H40: =VLOOKUP(A40,'모터 상세사양값'!$A$1:$CG$27,56,0) -> 4 | I40: =VLOOKUP(A40,'모터 상세사양값'!$A$1:$CG$27,58,0) -> 1.5 | J40: =VLOOKUP(A40,'모터 상세사양값'!$A$1:$CG$27,60,0) -> 440 | K40: =VLOOKUP(A40,'모터 상세사양값'!$A$1:$CG$27,62,0) -> 60 | L40: =VLOOKUP(A40,'모터 상세사양값'!$A$1:$CG$27,64,0) -> 1750 | M40: =VLOOKUP(A40,'모터 상세사양값'!$A$1:$CG$27,66,0) -> 1/15 | N40: 정답
A41: Q4621316 | B41: 포스코 | C41: AC Geared Motor | D41: =VLOOKUP(A41,'모터 상세사양값'!$A$1:$CG$27,28,0) -> HMA01080000560 | E41: =VLOOKUP(A41,'모터 상세사양값'!$A$1:$CG$27,30,0) -> HYOSUNG | F41: =VLOOKUP(A41,'모터 상세사양값'!$A$1:$CG$27,52,0) -> F | G41: =VLOOKUP(A41,'모터 상세사양값'!$A$1:$CG$27,54,0) -> TE | H41: =VLOOKUP(A41,'모터 상세사양값'!$A$1:$CG$27,56,0) -> 4 | I41: =VLOOKUP(A41,'모터 상세사양값'!$A$1:$CG$27,58,0) -> 3.7 | J41: =VLOOKUP(A41,'모터 상세사양값'!$A$1:$CG$27,60,0) -> 440 | K41: =VLOOKUP(A41,'모터 상세사양값'!$A$1:$CG$27,62,0) -> 60 | L41: =VLOOKUP(A41,'모터 상세사양값'!$A$1:$CG$27,64,0) -> 1755 | M41: =VLOOKUP(A41,'모터 상세사양값'!$A$1:$CG$27,66,0) -> 1/120 | N41: 정답
A42: Q4621046 | B42: 포스코 | C42: AC Geared Motor | D42: =VLOOKUP(A42,'모터 상세사양값'!$A$1:$CG$27,28,0) -> HLA020101057590 | E42: =VLOOKUP(A42,'모터 상세사양값'!$A$1:$CG$27,30,0) -> HYOSUNG | F42: =VLOOKUP(A42,'모터 상세사양값'!$A$1:$CG$27,52,0) -> F | G42: =VLOOKUP(A42,'모터 상세사양값'!$A$1:$CG$27,54,0) -> TE | H42: =VLOOKUP(A42,'모터 상세사양값'!$A$1:$CG$27,56,0) -> 4 | I42: =VLOOKUP(A42,'모터 상세사양값'!$A$1:$CG$27,58,0) -> 5.5 | J42: =VLOOKUP(A42,'모터 상세사양값'!$A$1:$CG$27,60,0) -> 440 | K42: =VLOOKUP(A42,'모터 상세사양값'!$A$1:$CG$27,62,0) -> 60 | L42: =VLOOKUP(A42,'모터 상세사양값'!$A$1:$CG$27,64,0) -> 1775 | M42: =VLOOKUP(A42,'모터 상세사양값'!$A$1:$CG$27,66,0) -> 1/100 | N42: 정답
A43: Q4620473 | B43: 포스코 | C43: AC Geared Motor | D43: =VLOOKUP(A43,'모터 상세사양값'!$A$1:$CG$27,28,0) -> HLA020101057591 | E43: =VLOOKUP(A43,'모터 상세사양값'!$A$1:$CG$27,30,0) -> HYOSUNG | F43: =VLOOKUP(A43,'모터 상세사양값'!$A$1:$CG$27,52,0) -> F | G43: =VLOOKUP(A43,'모터 상세사양값'!$A$1:$CG$27,54,0) -> TE | H43: =VLOOKUP(A43,'모터 상세사양값'!$A$1:$CG$27,56,0) -> 4 | I43: =VLOOKUP(A43,'모터 상세사양값'!$A$1:$CG$27,58,0) -> 7.5 | J43: =VLOOKUP(A43,'모터 상세사양값'!$A$1:$CG$27,60,0) -> 440 | K43: =VLOOKUP(A43,'모터 상세사양값'!$A$1:$CG$27,62,0) -> 60 | L43: =VLOOKUP(A43,'모터 상세사양값'!$A$1:$CG$27,64,0) -> 1770 | M43: =VLOOKUP(A43,'모터 상세사양값'!$A$1:$CG$27,66,0) -> 1/60 | N43: 정답
A44: Q4620571 | B44: 포스코 | C44: AC Geared Motor | D44: =VLOOKUP(A44,'모터 상세사양값'!$A$1:$CG$27,28,0) -> HLA020101057588 | E44: =VLOOKUP(A44,'모터 상세사양값'!$A$1:$CG$27,30,0) -> HYOSUNG | F44: =VLOOKUP(A44,'모터 상세사양값'!$A$1:$CG$27,52,0) -> F | G44: =VLOOKUP(A44,'모터 상세사양값'!$A$1:$CG$27,54,0) -> TE | H44: =VLOOKUP(A44,'모터 상세사양값'!$A$1:$CG$27,56,0) -> 4 | I44: =VLOOKUP(A44,'모터 상세사양값'!$A$1:$CG$27,58,0) -> 2.2 | J44: =VLOOKUP(A44,'모터 상세사양값'!$A$1:$CG$27,60,0) -> 440 | K44: =VLOOKUP(A44,'모터 상세사양값'!$A$1:$CG$27,62,0) -> 60 | L44: =VLOOKUP(A44,'모터 상세사양값'!$A$1:$CG$27,64,0) -> 1765 | M44: =VLOOKUP(A44,'모터 상세사양값'!$A$1:$CG$27,66,0) -> 1/30 | N44: 정답
A45: Q4621315 | B45: 포스코 | C45: AC Geared Motor | D45: =VLOOKUP(A45,'모터 상세사양값'!$A$1:$CG$27,28,0) -> HMA01080000560 | E45: =VLOOKUP(A45,'모터 상세사양값'!$A$1:$CG$27,30,0) -> HYOSUNG | F45: =VLOOKUP(A45,'모터 상세사양값'!$A$1:$CG$27,52,0) -> F | G45: =VLOOKUP(A45,'모터 상세사양값'!$A$1:$CG$27,54,0) -> IP55 | H45: =VLOOKUP(A45,'모터 상세사양값'!$A$1:$CG$27,56,0) -> 4 | I45: =VLOOKUP(A45,'모터 상세사양값'!$A$1:$CG$27,58,0) -> 3.7 | J45: =VLOOKUP(A45,'모터 상세사양값'!$A$1:$CG$27,60,0) -> 440 | K45: =VLOOKUP(A45,'모터 상세사양값'!$A$1:$CG$27,62,0) -> 60 | L45: =VLOOKUP(A45,'모터 상세사양값'!$A$1:$CG$27,64,0) -> 1755 | M45: =VLOOKUP(A45,'모터 상세사양값'!$A$1:$CG$27,66,0) -> 1/90 | N45: 정답
A46: Q4660900 | B46: 포스코 | C46: AC Geared Motor | D46: =VLOOKUP(A46,'모터 상세사양값'!$A$1:$CG$27,28,0) -> JK-BT2200 | E46: =VLOOKUP(A46,'모터 상세사양값'!$A$1:$CG$27,30,0) -> JEIL REDUCER | F46: =VLOOKUP(A46,'모터 상세사양값'!$A$1:$CG$27,52,0) -> F | G46: =VLOOKUP(A46,'모터 상세사양값'!$A$1:$CG$27,54,0) -> IP55 | H46: =VLOOKUP(A46,'모터 상세사양값'!$A$1:$CG$27,56,0) -> 6 | I46: =VLOOKUP(A46,'모터 상세사양값'!$A$1:$CG$27,58,0) -> 30 | J46: =VLOOKUP(A46,'모터 상세사양값'!$A$1:$CG$27,60,0) -> 440 | K46: =VLOOKUP(A46,'모터 상세사양값'!$A$1:$CG$27,62,0) -> 60 | L46: =VLOOKUP(A46,'모터 상세사양값'!$A$1:$CG$27,64,0) -> 1200 | M46: =VLOOKUP(A46,'모터 상세사양값'!$A$1:$CG$27,66,0) -> 1/15 | N46: 정답
A47: Q3507384 | B47: 포스코 | C47: AC Geared Motor | D47: HLA020101057587 | E47: JEIL REDUCER | F47: F | G47: IP55 | H47: 8 | I47: 20 | J47: 440 | K47: 60 | L47: 1750 | M47: 1/15 | N47: 오류치
A48: Q3507385 | B48: 포스코 | C48: AC Geared Motor | D48: HMA01080000561 | E48: JEIL REDUCER | F48: F | G48: IP55 | H48: 8 | I48: 30 | J48: 440 | K48: 60 | L48: 1750 | M48: 1/15 | N48: 오류치
A49: Q3507386 | B49: 포스코 | C49: AC Geared Motor | D49: HLA020101057587 | E49: JEIL REDUCER | F49: F | G49: IP55 | H49: 8 | I49: 40 | J49: 440 | K49: 60 | L49: 1750 | M49: 1/15 | N49: 오류치
A50: Q3507387 | B50: 포스코 | C50: AC Geared Motor | D50: HMA01080000562 | E50: JEIL REDUCER | F50: F | G50: IP55 | H50: 8 | I50: 50 | J50: 440 | K50: 60 | L50: 1750 | M50: 1/15 | N50: 오류치
A51: Q3507388 | B51: 포스코 | C51: AC Geared Motor | D51: HLA020101057587 | E51: JEIL REDUCER | F51: F | G51: IP55 | H51: 8 | I51: 60 | J51: 440 | K51: 60 | L51: 1750 | M51: 1/15 | N51: 오류치
A52: Q3507389 | B52: 포스코 | C52: AC Geared Motor | D52: HMA01080000563 | E52: JEIL REDUCER | F52: F | G52: IP55 | H52: 8 | I52: 70 | J52: 440 | K52: 60 | L52: 1750 | M52: 1/15 | N52: 오류치
A54: Q-Code | B54: 그룹사명 | C54: 품명 | D54: Model-1 | E54: Maker Name-1 | F54: Coil Voltage | G54: Setting Tap Range | H54: Setting Time Range | I54: Option & Others | J54: 정답여부
A55: Q4631078 | B55: 포스코퓨처엠 | C55: Protection Relay | D55: =VLOOKUP(A55,'protection Relay 상세사양'!$A$1:$CG$47,32,0) -> DMP06I-T | E55: =VLOOKUP(A55,'protection Relay 상세사양'!$A$1:$CG$47,34,0) -> LS | F55: =VLOOKUP(A55,'protection Relay 상세사양'!$A$1:$CG$47,50,0) -> 100-260VAC | G55: =VLOOKUP(A55,'protection Relay 상세사양'!$A$1:$CG$47,52,0) -> 0 | H55: =VLOOKUP(A55,'protection Relay 상세사양'!$A$1:$CG$47,54,0) -> 0 | I55: =VLOOKUP(A55,'protection Relay 상세사양'!$A$1:$CG$47,58,0) -> 0 | J55: 정답
A56: Q4657312 | B56: 포스코 | C56: Protection Relay | D56: =VLOOKUP(A56,'protection Relay 상세사양'!$A$1:$CG$47,32,0) -> DMP65I-TZ | E56: =VLOOKUP(A56,'protection Relay 상세사양'!$A$1:$CG$47,34,0) -> LS | F56: =VLOOKUP(A56,'protection Relay 상세사양'!$A$1:$CG$47,50,0) -> 80~250VAC/DC | G56: =VLOOKUP(A56,'protection Relay 상세사양'!$A$1:$CG$47,52,0) -> 0 | H56: =VLOOKUP(A56,'protection Relay 상세사양'!$A$1:$CG$47,54,0) -> 0 | I56: =VLOOKUP(A56,'protection Relay 상세사양'!$A$1:$CG$47,58,0) -> 0 | J56: 정답
A57: Q4677466 | B57: 포스코퓨처엠 | C57: Protection Relay | D57: =VLOOKUP(A57,'protection Relay 상세사양'!$A$1:$CG$47,32,0) -> DMP65I-T | E57: =VLOOKUP(A57,'protection Relay 상세사양'!$A$1:$CG$47,34,0) -> LS | F57: =VLOOKUP(A57,'protection Relay 상세사양'!$A$1:$CG$47,50,0) -> 100-260VAC | G57: =VLOOKUP(A57,'protection Relay 상세사양'!$A$1:$CG$47,52,0) -> 0 | H57: =VLOOKUP(A57,'protection Relay 상세사양'!$A$1:$CG$47,54,0) -> 0 | I57: =VLOOKUP(A57,'protection Relay 상세사양'!$A$1:$CG$47,58,0) -> 0 | J57: 정답
A58: Q4684055 | B58: 포스코퓨처엠 | C58: Protection Relay | D58: =VLOOKUP(A58,'protection Relay 상세사양'!$A$1:$CG$47,32,0) -> WYGF-D12NC | E58: =VLOOKUP(A58,'protection Relay 상세사양'!$A$1:$CG$47,34,0) -> WOONYOUNG | F58: =VLOOKUP(A58,'protection Relay 상세사양'!$A$1:$CG$47,50,0) -> OTHERS | G58: =VLOOKUP(A58,'protection Relay 상세사양'!$A$1:$CG$47,52,0) -> 0 | H58: =VLOOKUP(A58,'protection Relay 상세사양'!$A$1:$CG$47,54,0) -> 0.1 ~ 10S | I58: =VLOOKUP(A58,'protection Relay 상세사양'!$A$1:$CG$47,58,0) -> AC/DC110~220V | J58: 정답
A59: Q4573379 | B59: POSCO MEXICO | C59: Protection Relay | D59: =VLOOKUP(A59,'protection Relay 상세사양'!$A$1:$CG$47,32,0) -> 3RU2146-4KB0 | E59: =VLOOKUP(A59,'protection Relay 상세사양'!$A$1:$CG$47,34,0) -> SIEMENS | F59: =VLOOKUP(A59,'protection Relay 상세사양'!$A$1:$CG$47,50,0) -> AC 440V | G59: =VLOOKUP(A59,'protection Relay 상세사양'!$A$1:$CG$47,52,0) -> 57~75A | H59: =VLOOKUP(A59,'protection Relay 상세사양'!$A$1:$CG$47,54,0) -> 0 | I59: =VLOOKUP(A59,'protection Relay 상세사양'!$A$1:$CG$47,58,0) -> 0 | J59: 정답
A60: Q4571139 | B60: POSCO MEXICO | C60: Protection Relay | D60: =VLOOKUP(A60,'protection Relay 상세사양'!$A$1:$CG$47,32,0) -> 3RU5146-4KB0 | E60: =VLOOKUP(A60,'protection Relay 상세사양'!$A$1:$CG$47,34,0) -> SIEMENS | F60: =VLOOKUP(A60,'protection Relay 상세사양'!$A$1:$CG$47,50,0) -> AC 440V | G60: =VLOOKUP(A60,'protection Relay 상세사양'!$A$1:$CG$47,52,0) -> 57~75A | H60: =VLOOKUP(A60,'protection Relay 상세사양'!$A$1:$CG$47,54,0) -> 0 | I60: =VLOOKUP(A60,'protection Relay 상세사양'!$A$1:$CG$47,58,0) -> 0 | J60: 정답
A61: Q4666232 | B61: 포스코 | C61: Protection Relay | D61: =VLOOKUP(A61,'protection Relay 상세사양'!$A$1:$CG$47,32,0) -> DSP-AOM-02Z7-ZCT-F | E61: =VLOOKUP(A61,'protection Relay 상세사양'!$A$1:$CG$47,34,0) -> SAMWHADSP | F61: =VLOOKUP(A61,'protection Relay 상세사양'!$A$1:$CG$47,50,0) -> 100-240VAC | G61: =VLOOKUP(A61,'protection Relay 상세사양'!$A$1:$CG$47,52,0) -> 0 | H61: =VLOOKUP(A61,'protection Relay 상세사양'!$A$1:$CG$47,54,0) -> 0 | I61: =VLOOKUP(A61,'protection Relay 상세사양'!$A$1:$CG$47,58,0) -> 0 | J61: 정답
A62: Q4666236 | B62: 포스코 | C62: Protection Relay | D62: =VLOOKUP(A62,'protection Relay 상세사양'!$A$1:$CG$47,32,0) -> DSP-AOM-10Z7-ZCT-F | E62: =VLOOKUP(A62,'protection Relay 상세사양'!$A$1:$CG$47,34,0) -> SAMWHADSP | F62: =VLOOKUP(A62,'protection Relay 상세사양'!$A$1:$CG$47,50,0) -> 100-240VAC | G62: =VLOOKUP(A62,'protection Relay 상세사양'!$A$1:$CG$47,52,0) -> 0 | H62: =VLOOKUP(A62,'protection Relay 상세사양'!$A$1:$CG$47,54,0) -> 0 | I62: =VLOOKUP(A62,'protection Relay 상세사양'!$A$1:$CG$47,58,0) -> 0 | J62: 정답
A63: Q4666301 | B63: 포스코 | C63: Protection Relay | D63: =VLOOKUP(A63,'protection Relay 상세사양'!$A$1:$CG$47,32,0) -> DSP-AOM-70Z7-ZCT-F | E63: =VLOOKUP(A63,'protection Relay 상세사양'!$A$1:$CG$47,34,0) -> SAMWHADSP | F63: =VLOOKUP(A63,'protection Relay 상세사양'!$A$1:$CG$47,50,0) -> 100-240VAC | G63: =VLOOKUP(A63,'protection Relay 상세사양'!$A$1:$CG$47,52,0) -> 0 | H63: =VLOOKUP(A63,'protection Relay 상세사양'!$A$1:$CG$47,54,0) -> 0 | I63: =VLOOKUP(A63,'protection Relay 상세사양'!$A$1:$CG$47,58,0) -> 0 | J63: 정답
A64: Q4677461 | B64: 포스코퓨처엠 | C64: Protection Relay | D64: =VLOOKUP(A64,'protection Relay 상세사양'!$A$1:$CG$47,32,0) -> DSP-AOL-02Z7-F | E64: =VLOOKUP(A64,'protection Relay 상세사양'!$A$1:$CG$47,34,0) -> SAMWHADSP | F64: =VLOOKUP(A64,'protection Relay 상세사양'!$A$1:$CG$47,50,0) -> 100-240VAC | G64: =VLOOKUP(A64,'protection Relay 상세사양'!$A$1:$CG$47,52,0) -> 0 | H64: =VLOOKUP(A64,'protection Relay 상세사양'!$A$1:$CG$47,54,0) -> 0 | I64: =VLOOKUP(A64,'protection Relay 상세사양'!$A$1:$CG$47,58,0) -> 0 | J64: 정답
A65: Q4677978 | B65: 포스코 | C65: Protection Relay | D65: =VLOOKUP(A65,'protection Relay 상세사양'!$A$1:$CG$47,32,0) -> DSP-IR-Z7-C-F | E65: =VLOOKUP(A65,'protection Relay 상세사양'!$A$1:$CG$47,34,0) -> SAM WHA DSP | F65: =VLOOKUP(A65,'protection Relay 상세사양'!$A$1:$CG$47,50,0) -> DC 24V | G65: =VLOOKUP(A65,'protection Relay 상세사양'!$A$1:$CG$47,52,0) -> 0 | H65: =VLOOKUP(A65,'protection Relay 상세사양'!$A$1:$CG$47,54,0) -> 0 | I65: =VLOOKUP(A65,'protection Relay 상세사양'!$A$1:$CG$47,58,0) -> 0 | J65: 정답
A66: Q4677979 | B66: 포스코 | C66: Protection Relay | D66: =VLOOKUP(A66,'protection Relay 상세사양'!$A$1:$CG$47,32,0) -> DSP-IRM-Z7-C-F | E66: =VLOOKUP(A66,'protection Relay 상세사양'!$A$1:$CG$47,34,0) -> SAM WHA DSP | F66: =VLOOKUP(A66,'protection Relay 상세사양'!$A$1:$CG$47,50,0) -> DC 24V | G66: =VLOOKUP(A66,'protection Relay 상세사양'!$A$1:$CG$47,52,0) -> 0 | H66: =VLOOKUP(A66,'protection Relay 상세사양'!$A$1:$CG$47,54,0) -> 0 | I66: =VLOOKUP(A66,'protection Relay 상세사양'!$A$1:$CG$47,58,0) -> 0 | J66: 정답
... A69: Q4641086 | B69: 포스코퓨처엠 | C69: Protection Relay | D69: =VLOOKUP(A69,'protection Relay 상세사양'!$A$1:$CG$47,32,0) -> GD12-L05A | E69: =VLOOKUP(A69,'protection Relay 상세사양'!$A$1:$CG$47,34,0) -> KYONGBO | F69: =VLOOKUP(A69,'protection Relay 상세사양'!$A$1:$CG$47,50,0) -> AC110-220V | G69: =VLOOKUP(A69,'protection Relay 상세사양'!$A$1:$CG$47,52,0) -> 0 | H69: =VLOOKUP(A69,'protection Relay 상세사양'!$A$1:$CG$47,54,0) -> 0 | I69: =VLOOKUP(A69,'protection Relay 상세사양'!$A$1:$CG$47,58,0) -> 60HZ | J69: 오류치
A70: Q3507390 | B70: 포스코퓨처엠 | C70: Protection Relay | D70: DSP-AOM-69Z7-ZCT-F | E70: WOONYOUNG | F70: DC 24V | G70: 0 | H70: 0 | I70: 60HZ | J70: 오류치
A71: Q3507391 | B71: 포스코퓨처엠 | C71: Protection Relay | D71: DSP-AOM-65Z7-ZCT-F | E71: WOONYOUNG | F71: DC 24V | G71: 0 | H71: 0 | I71: 60HZ | J71: 오류치
A72: Q3507392 | B72: 포스코퓨처엠 | C72: Protection Relay | D72: DSP-AOM-69Z8-ZCT-F | E72: WOONYOUNG | F72: DC 24V | G72: 0 | H72: 0 | I72: 60HZ | J72: 오류치
A73: Q3507393 | B73: 포스코퓨처엠 | C73: Protection Relay | D73: DSP-AOM-65Z8-ZCT-F | E73: WOONYOUNG | F73: DC 24V | G73: 0 | H73: 0 | I73: 60HZ | J73: 오류치
A74: Q3507394 | B74: 포스코퓨처엠 | C74: Protection Relay | D74: DSP-AOM-69Z9-ZCT-F | E74: WOONYOUNG | F74: DC 24V | G74: 0 | H74: 0 | I74: 60HZ | J74: 오류치
A75: Q3507395 | B75: 포스코퓨처엠 | C75: Protection Relay | D75: DSP-AOM-65Z9-ZCT-F | E75: WOONYOUNG | F75: DC 24V | G75: 0 | H75: 0 | I75: 60HZ | J75: 오류치
A76: Q3507396 | B76: 포스코퓨처엠 | C76: Protection Relay | D76: DSP-AOM-69Z10-ZCT-F | E76: WOONYOUNG | F76: DC 24V | G76: 0 | H76: 0 | I76: 60HZ | J76: 오류치
A77: Q3507397 | B77: 포스코퓨처엠 | C77: Protection Relay | D77: DSP-AOM-65Z10-ZCT-F | E77: WOONYOUNG | F77: DC 24V | G77: 0 | H77: 0 | I77: 60HZ | J77: 오류치
A78: Q3507398 | B78: 포스코퓨처엠 | C78: Protection Relay | D78: DSP-AOM-69Z11-ZCT-F | E78: WOONYOUNG | F78: DC 24V | G78: 0 | H78: 0 | I78: 60HZ | J78: 오류치

Sheet 공압실린더 56개 
A1: Q-Code | B1: =COUNTA(B2:B1048576) -> 77 | C1: 그룹사명 | D1: 품명 | E1: Purchase Category | F1: 표준화섹션담당자 | G1: 자재특성구분 | H1: 처리상태 | I1: 조달 | J1: 통화 | K1: 사양 및 규격 | L1: 단위 | M1: 계약형태 | N1: Model-1 | O1: Maker-1 | P1: Option-1 | Q1: Model-2 | R1: Maker-2 | S1: Option-2 | T1: Model-3 | U1: Maker-3 | V1: Option-3 | W1: Option & Others | X1: Application | Y1: 도면번호1 | Z1: 첨부도면파일명 | AA1: 첨부자재규격서명 | AB1: Model-1 첨부파일명 | AC1: Model-2 첨부파일명 | AD1: Model-3 첨부파일명 | AE1: Model-1 첨부URL1 | AF1: Model-1 첨부URL2 | AG1: Model-2 첨부URL1 | AH1: 첨부Image파일명1 | AI1: 첨부Image파일명2 | AJ1: 신청자명 | AK1: 신청자 소속 | AL1: 신청자 E-mail | AM1: 요청자명 | AN1: 요청자 소속 | AO1: 요청자 E-mail | AP1: 최종검토일 | AQ1: 년도 | AR1: 단수승인사유 | AS1: 검토자 메모 | AT1: 월별Inactive대상
A2: Q4675156 | B2: 0 | C2: 포스코 | D2: Pneumatic Cylinder | E2: Pneumatic Cylinder | F2: 전아람 | G2: 특정사양품(단수) | H2: ACTIVE | I2: L | J2: KRW | K2: CWC(DA),16Dx16Dx25ST,7kgf/cm2,[CDJ2F16-25Z-A93L-B/SMC],FOR CHARPY IMPACT TESTER(SETTER),OR EQUIVALENT | L2: EA | M2: STANDARD | N2: CDJ2F16-25Z-A93L-B | O2: SMC | R2: NONE | X2: FOR CHARPY IMPACT TESTER(SETTER) | AB2: _SMC_CDJ2F16-25Z-A93L-B_CATALOG_20250526104947035.pdf | AE2: https://www.smckorea.co.kr/ | AH2: SMC_CDJ2F16-25Z-A93L-B_20250526105245175.jpg | AJ2: 권우석 | AK2: (포항)품질기술부 재질시험섹션 | AL2: kws80395@posco.co.kr | AM2: 박민우 | AN2: (포항)품질기술부 재질시험섹션 | AO2: cinnamon@posco.co.kr | AP2: 2025-05-28 11:05:31 | AQ2: 2025 | AR2: 차후 재점검 | AS2: 기 설치된 물품의 호환성을 위해 특정 사양으로 등록건 확인,_x000D_ Q4644072등 유사item 검색하였으나, 유사/동일품 없음 확인후 승인합니다._x000D_ (특정 사양품감축 관련) 차후 입고시 스케치, 현물 확인을 통한 도면화, 일반 사양화, 복수화 전환 검토 요청 필히 부탁드립니다. 감사합니다._x000D_ | AT2: N
A3: Q4675089 | B3: 0 | C3: 포스코 | D3: Pneumatic Cylinder | E3: Pneumatic Cylinder | F3: 전아람 | G3: 특정사양품(단수) | H3: ACTIVE | I3: L | J3: KRW | K3: CWC(DA),25Dx25Dx25ST,10kgf/cm2,[CDM2B25-25Z-A93L/SMC],FOR CHARPY IMPACT TESTER(STOPPER),OR EQUIVALENT | L3: EA | M3: STANDARD | N3: CDM2B25-25Z-A93L | O3: SMC | R3: NONE | X3: FOR CHARPY IMPACT TESTER(STOPPER) | AB3: _SMC_CDM2B25-25Z-A93L_CATALOG_20250526104540071.pdf | AE3: https://www.smckorea.co.kr/ | AH3: SMC_CDM2B25-25Z-A93L_20250526104504139.jpg | AJ3: 권우석 | AK3: (포항)품질기술부 재질시험섹션 | AL3: kws80395@posco.co.kr | AM3: 박민우 | AN3: (포항)품질기술부 재질시험섹션 | AO3: cinnamon@posco.co.kr | AP3: 2025-05-27 17:05:32 | AQ3: 2025 | AR3: 차후 재점검 | AS3: 기 설치된 물품의 호환성을 위해 특정 사양으로 등록건 확인,_x000D_ Q4290511등 유사item 검색하였으나, 유사/동일품 없음 확인후 승인합니다._x000D_ (특정 사양품감축 관련) 차후 입고시 스케치, 현물 확인을 통한 도면화, 일반 사양화, 복수화 전환 검토 요청 필히 부탁드립니다. 감사합니다._x000D_ | AT3: N
A4: Q4675326 | B4: 0 | C4: 포스코 | D4: Pneumatic Cylinder | E4: Pneumatic Cylinder | F4: 전아람 | G4: 특정사양품(단수) | H4: ACTIVE | I4: L | J4: KRW | K4: CWC(DA),16Dx16Dx25ST,10kgf/cm2,[CDQSD16-25DM-A93L/SMC],FOR CHARPY IMPACT TESTER(HOLDER),OR EQUIVALENT | L4: EA | M4: STANDARD | N4: CDQSD16-25DM-A93L | O4: SMC | R4: NONE | X4: FOR CHARPY IMPACT TESTER(HOLDER) | AB4: _SMC_CDQSD16-25DM-A93L_CATALOG_20250528132218077.pdf | AE4: https://www.smckorea.co.kr/ | AH4: SMC_CDQSD16-25DM-A93L_20250528132218190.jpg | AJ4: 권우석 | AK4: (포항)품질기술부 재질시험섹션 | AL4: kws80395@posco.co.kr | AM4: 박민우 | AN4: (포항)품질기술부 재질시험섹션 | AO4: cinnamon@posco.co.kr | AP4: 2025-05-29 13:05:54 | AQ4: 2025 | AR4: 차후 재점검 | AS4: 기 설치된 물품의 호환성을 위해 특정 사양으로 등록건 확인,_x000D_ Q4644099등 유사item 검색하였으나, 유사/동일품 없음 확인후 승인합니다._x000D_ (특정 사양품감축 관련) 차후 입고시 스케치, 현물 확인을 통한 도면화, 일반 사양화, 복수화 전환 검토 요청 필히 부탁드립니다. 감사합니다._x000D_ _x000D_ | AT4: N
A5: Q4675164 | B5: 0 | C5: 포스코 | D5: Pneumatic Cylinder | E5: Pneumatic Cylinder | F5: 전아람 | G5: 특정사양품(단수) | H5: ACTIVE | I5: L | J5: KRW | K5: CWC(DA),25Dx25Dx30ST,7kgf/cm2,[CDUK25-30D-A93L/SMC],FOR CHARPY IMPACT TESTER(BURR REMOVER),OR EQUIVALENT | L5: EA | M5: STANDARD | N5: CDUK25-30D-A93L | O5: SMC | R5: NONE | X5: FOR CHARPY IMPACT TESTER(BURR REMOVER) | AB5: _SMC_CDUK25-30D-A93L_CATALOG_20250526111558421.pdf | AE5: https://www.smckorea.co.kr/ | AH5: SMC_CDUK25-30D-A93L_20250526111854632.jpg | AJ5: 권우석 | AK5: (포항)품질기술부 재질시험섹션 | AL5: kws80395@posco.co.kr | AM5: 박민우 | AN5: (포항)품질기술부 재질시험섹션 | AO5: cinnamon@posco.co.kr | AP5: 2025-05-28 13:05:15 | AQ5: 2025 | AR5: 차후 재점검 | AS5: 기 설치된 물품의 호환성을 위해 특정 사양으로 등록건 확인,_x000D_ Q4594812등 유사item 검색하였으나, 유사/동일품 없음 확인후 승인합니다._x000D_ (특정 사양품감축 관련) 차후 입고시 스케치, 현물 확인을 통한 도면화, 일반 사양화, 복수화 전환 검토 요청 필히 부탁드립니다. 감사합니다._x000D_ | AT5: N
A6: Q4688206 | B6: 0 | C6: 포스코 | D6: Pneumatic Cylinder | E6: Pneumatic Cylinder | F6: 전아람 | G6: 특정사양품(단수) | H6: ACTIVE | I6: L | J6: KRW | K6: CWC(DA),SD,50Dx20Dx100ST,10.2kgf/cm2,[CDQ2A50-100DCZ-M9BWL/SMC],OR EQUIVALENT | L6: EA | M6: STANDARD | N6: CDQ2A50-100DCZ-M9BWL | O6: SMC | R6: NONE | AB6: 16. 특정사양품(신규등록) 품의서(CDQ2A50-100DCZ-M9BWL)_20250924145804115.docx | AE6: https://www.smckorea.co.kr/ | AH6: 16. Pneumatic Valve (공압 밸브)_20250924145312817.jpg | AJ6: 정석운 | AK6: 설비자재구매실 자재구매그룹 광양자재지원섹션 | AL6: sambar@posco.co.kr | AM6: 김선재 | AN6: 설비자재구매실 자재구매그룹 광양자재지원섹션 | AO6: jae7668@posco.co.kr | AP6: 2025-09-24 17:09:00 | AQ6: 2025 | AR6: 차후 재점검 | AS6: 기 설치된 물품의 호환성을 위해 특정 사양으로 등록건 확인, _x000D_ 유사 item 검색하였으나, 유사/동일품 없음 확인후 승인합니다._x000D_ (특정 사양품감축 관련) 차후 입고시 스케치, 현물 확인을 통한 도면화, 일반 사양화, 복수화 전환 검토 요청 부탁드립니다. 감사합니다._x000D_ | AT6: N
A7: Q4683457 | B7: 0 | C7: 포스코 | D7: Pneumatic Cylinder | E7: Pneumatic Cylinder | F7: 전아람 | G7: 특정사양품(단수) | H7: ACTIVE | I7: L | J7: KRW | K7: CA,100Dx30Dx300ST,10kgf/cm2,[CA2B100-300Z/SMC],2FINEX RTO,OR EQUIVALENT | L7: SET | M7: STANDARD | N7: CA2B100-300Z | O7: SMC | R7: NONE | X7: 2FINEX RTO | AB7: 250812_A2_제선설비부_물품등록자료_T1663035 2FINEX RTO Pneumatic Cylinder CA2B100-300Z Catalog_20250812185026609.pdf | AE7: https://www.smcpneumatics.com/CA2B100-300Z.html | AH7: 250812_A2_제선설비부_물품등록자료_T1663035 2FINEX RTO Pneumatic Cylinder CA2B100-300Z image_20250812185329161.jpg | AJ7: 문승준 | AK7: (포항)제선설비부 2FINEX정비섹션 | AL7: m130508@posco.co.kr | AM7: 김황식 | AN7: (포항)제선설비부 2FINEX정비섹션 | AO7: afang@posco.co.kr | AP7: 2025-08-13 07:08:01 | AQ7: 2025 | AR7: 차후 재점검 | AT7: N
A8: Q4501288 | B8: 0 | C8: 포스코 | D8: Pneumatic Cylinder | E8: Hydraulic & Pneumatics | F8: 전아람 | G8: 특정사양품(단수) | H8: ACTIVE | I8: L | J8: KRW | K8: CWC(DA),160Dx100ST,[CS1CN160-100-CJAD0046/SMC],FOR 1CGL #5,#6,#7 TENSION BRIDLE SNUBBER ROLL,OR EQUIVALENT | L8: EA | M8: STANDARD | N8: CS1CN160-100-CJAD0046 | O8: SMC | R8: NONE | X8: FOR 1CGL #5,#6,#7 TENSION BRIDLE SNUBBER ROLL | AB8: CS1CN160-100-CJAD0046(업그레이드 품)[1CGL 5.6.7 TB]_20220114112323273.pdf | AE8: http://www.smcpneumatics.com/pdfs/smc/70ACS1.pdf | AH8: 54TB_Roll_Snubber_R_sk2580_20201022_214208_20220114110512061.jpg | AJ8: 양병춘 | AK8: (광양)압연설비부 도금정비1섹션 | AM8: 김현호 | AN8: (광양)압연설비부 도금정비1섹션 | AO8: khh8352@posco.co.kr | AP8: 2022-01-17 08:01:57 | AQ8: 2022 | AR8: 차후 재점검 | AS8: 기 설치품의 사양 정보로 E-Catalog에 등록 하였으나 복수 참여 업체가 없어 자재 수급에 긴급성을 고려하여 기 설치품으로 물품 등록 하게 되었음. _x000D_ | AT8: N
A9: Q4661796 | B9: 0 | C9: 포스코 | D9: Pneumatic Cylinder | E9: Pneumatic Cylinder | F9: 전아람 | G9: 특정사양품(단수) | H9: ACTIVE | I9: L | J9: KRW | K9: CWC(DA),CA,250Dx150ST,[CS1CN250-KRD0368-150/SMC],FOR K1APL NO.6 TBR SNUBBER ROLL UP/DOWN,OR EQUIVALENT | L9: SET | M9: STANDARD | N9: CS1CN250-KRD0368-150 | O9: SMC | R9: NONE | X9: FOR K1APL NO.6 TBR SNUBBER ROLL UP/DOWN | AB9: 6TBR SR SMC Pneumatic Cylinder 카탈로그_20250113100103768.png | AE9: https://www.smckorea.co.kr/ | AH9: SMC Pneumatic Cylinder 실물 사진_20250113100103847.png | AJ9: 박원준 | AK9: (광양)압연설비2부 전기강판정비섹션 | AL9: wjpark@posco.co.kr | AM9: 최인오 | AN9: (광양)압연설비2부 전기강판정비섹션 | AO9: choi6959@posco.co.kr | AP9: 2025-01-15 11:01:16 | AQ9: 2025 | AR9: 차후 재점검 | AS9: MRO e-Caltalog시스템 경유건으로 대체 Maker 미 발굴건, 기 설치된 Cylinder의 호환성을 위해 특정 사양으로 등록건 확인, _x000D_ Q4077013 등 유사 item 검색하였으나, 유사/동일품 없음 확인후 승인합니다. _x000D_ (특정 사양품감축 관련) 차후 입고시 스케치, 현물 확인을 통한 도면화,일반 사양화, 복수화 전환 검토 요청 필히 부탁드립니다. 감사합니다._x000D_ | AT9: N
A10: Q4550786 | B10: 0 | C10: 포스코 | D10: Pneumatic Cylinder | E10: Hydraulic & Pneumatics | F10: 전아람 | G10: 특정사양품(단수) | H10: ACTIVE | I10: L | J10: KRW | K10: FA,50Dx20Dx425ST,10kgf/cm2,[ACM-N-FA50-S425/KCC],OR EQUIVALENT | L10: SET | M10: STANDARD | N10: ACM-N-FA50-S425 | O10: KCC | R10: NONE | AB10: ACM_20220111135135572.pdf | AE10: https://www.kccpr.com/bbs/search.php?url=https%3A%2F%2Fwww.kccpr.com%2Fbbs%2Fsearch.php&stx=ACM | AH10: ACM_20220111135109104.jpg | AI10: Roll_Changing_Car_Air Cylinder_20220113105455723.jpg | AJ10: 이규연 | AK10: (포항)압연설비부 전기강판정비섹션 | AL10: lkydh@posco.co.kr | AM10: 이정욱 | AN10: (포항)압연설비부 전기강판정비섹션 | AO10: jw4102@posco.co.kr | AP10: 2022-02-09 08:02:06 | AQ10: 2022 | AR10: 불가피 품목 | AT10: N
A11: Q4549165 | B11: 0 | C11: 포스코 | D11: Pneumatic Cylinder | E11: Hydraulic & Pneumatics | F11: 전아람 | G11: 특정사양품(단수) | H11: ACTIVE | I11: L | J11: KRW | K11: CWC(DA),TC,80Dx25Dx125ST,10kgf/cm2,[ACM-N-TC80-S125-J/KCC],FOR CGL SHOT BLAST DUST COLLECTOR DOUBLE DAMPER PNEUMATIC CYLINDER,OR EQUIVALENT | L11: EA | M11: STANDARD | N11: ACM-N-TC80-S125-J | O11: KCC | R11: NONE | X11: FOR CGL SHOT BLAST DUST COLLECTOR DOUBLE DAMPER PNEUMATIC CYLINDER | AB11: ACM카달로그_20220119165138547.pdf | AE11: https://www.kccpr.com/bbs/search.php?url=https%3A%2F%2Fwww.kccpr.com%2Fbbs%2Fsearch.php&stx=ACM | AH11: ACM_20220119165114295.jpg | AJ11: 권인순 | AK11: (포항)압연설비부 냉연정비2섹션 | AM11: 신석현 | AN11: (포항)압연설비부 냉연정비2섹션 | AO11: sh01293@posco.co.kr | AP11: 2022-01-21 13:01:32 | AQ11: 2022 | AR11: 불가피 품목 | AT11: N
A12: Q4610700 | B12: 0 | C12: 포스코 | D12: Pneumatic Cylinder | E12: Pneumatic Cylinder | F12: 전아람 | G12: 특정사양품(단수) | H12: ACTIVE | I12: L | J12: KRW | K12: CWC(DA),TC,63Dx20Dx50ST,10kgf/cm2,[C96ST63-50-CJBG0810/SMC],OR EQUIVALENT | L12: SET | M12: STANDARD | N12: C96ST63-50-CJBG0810 | O12: SMC | R12: NONE | AB12: C96ST63-50-CJBG0810 도면_20230823093047288.jpg | AH12: C96_20230823092933535.jpg | AJ12: 이규연 | AK12: (포항)압연설비2부 전기강판정비섹션 | AL12: lkydh@posco.co.kr | AM12: 홍준모 | AN12: (포항)압연설비2부 전기강판정비섹션 | AO12: junmo01@posco.co.kr | AP12: 2023-08-28 09:08:40 | AQ12: 2023 | AR12: 차후 재점검 | AS12: MRO e-Caltalog시스템 경유건으로 대체 Maker 미 발굴건,3APL Side Trimmer Edge Support Roll의 핵심 부품으로 기 설치된 Pneumatic Cylinder의 호환성을 위해 특정 사양으로 등록건 확인 후 승인,(특정 사양품감축 관련) 차후 입고시 스케치, 현물 확인을 통한 도면화,일반 사양화,복수화 전환 검토 요청 필히 부탁드립니다. 감사합니다. | AT12: N
A13: Q4655802 | B13: 0 | C13: 포스코 | D13: Pneumatic Cylinder | E13: Pneumatic Cylinder | F13: 전아람 | G13: 특정사양품(단수) | H13: ACTIVE | I13: L | J13: KRW | K13: CWC(DA),TA,80Dx50Dx200ST,10kgf/cm2,[CDA2T80-KRT09KO-200Z-A54L3/SMC],FOR K1SMP 1RH SAMPLING PROBE LOADING CLAMP ROTATE,OR EQUIVALENT | L13: EA | M13: STANDARD | N13: CDA2T80-KRT09KO-200Z-A54L3 | O13: SMC | R13: NONE | X13: FOR K1SMP 1RH SAMPLING PROBE LOADING CLAMP ROTATE | AB13: Pneumatic cylinder CDA2T80-KRT09KO-200Z-A54L3 SMC_20241112142525736.pdf | AE13: https://www.smckorea.co.kr/ppis/data/catalog/CA2-Z.pdf | AH13: CDA2T80-KRT09KO-200Z-A54L3 대표사진_20241105115621263.PNG | AJ13: 남태현 | AK13: (광양)제강설비부 제강정비섹션 | AM13: 구건웅 | AN13: (광양)제강설비부 제강정비섹션 | AO13: kkkunwoong@posco.co.kr | AP13: 2024-11-13 15:11:56 | AQ13: 2024 | AR13: 차후 재점검 | AT13: N
A14: Q4609636 | B14: 0 | C14: 포스코 | D14: Pneumatic Cylinder | E14: Pneumatic Cylinder | F14: 전아람 | G14: 특정사양품(단수) | H14: ACTIVE | I14: L | J14: KRW | K14: CWC(DA),FA,100Dx30Dx115ST,10kgf/cm2,[CA2F100-KRT10KO-115Z-W-XC5/SMC],FOR K1APL FURNACE ENTRY SEAL ROLL UP & DOWN PNEUMATIC CYLINDER,OR EQUIVALENT | L14: SET | M14: STANDARD | N14: CA2F100-KRT10KO-115Z-W-XC5 | O14: SMC | R14: NONE | X14: FOR K1APL FURNACE ENTRY SEAL ROLL UP & DOWN PNEUMATIC CYLINDER | AB14: CA2-KRT 품명자료_20230816110159236.jpg, CA2F100-KRT10KO-115Z-W-XC5_20230816110208727.jpg | AE14: https://www.smckorea.co.kr/ | AH14: CA2_20230816110138500.jpg | AJ14: 정정현 | AK14: (광양)압연설비2부 전기강판정비섹션 | AL14: wjd1670@posco.co.kr | AM14: 박원준 | AN14: (광양)압연설비2부 전기강판정비섹션 | AO14: wjpark@posco.co.kr | AP14: 2023-08-18 10:08:16 | AQ14: 2023 | AR14: 차후 재점검 | AS14: MRO e-Caltalog시스템 경유건으로 대체 Maker 미 발굴건,K1APL FURNACE ENTRY SEAL ROLL UP & DOWN PNEUMATIC CYLINDER로 기 설치된 Pneumatic Cylinder의 호환성을 위해 특정 사양으로 등록건 확인 후 승인,(특정 사양품감축 관련) 차후 입고시 스케치, 현물 확인을 통한 도면화,일반 사양화,복수화 전환 검토 요청 필히 부탁드립니다. 감사합니다._x000D_ | AT14: N
A15: Q4592849 | B15: 0 | C15: 포스코 | D15: Pneumatic Cylinder | E15: Pneumatic Cylinder | F15: 전아람 | G15: 특정사양품(단수) | H15: ACTIVE | I15: L | J15: KRW | K15: CWC(DA),TC,63Dx20Dx1100ST,[CA2T63-1100Z-XC14/SMC],FOR 1CGL BANDING MACHINE LOWER CHUTE CYLINDER,OR EQUIVALENT | L15: EA | M15: STANDARD | N15: CA2T63-1100Z-XC14 | O15: SMC | R15: NONE | X15: FOR 1CGL BANDING MACHINE LOWER CHUTE CYLINDER | AB15: CA2T63-1100Z-XC14 도면_20230309101205940.jpg | AE15: https://www.smckorea.co.kr | AH15: CA2T63-1100Z-XC14 도면_20230308172157076.jpg | AJ15: 김응백 | AK15: (포항)압연설비2부 냉연정비2섹션 | AL15: kebe12@posco.co.kr | AM15: 박동방석 | AN15: (포항)압연설비2부 냉연정비2섹션 | AP15: 2023-03-13 09:03:48 | AQ15: 2023 | AR15: 차후 재점검 | AS15: MRO e-Caltalog시스템 공급사 소개건으로 대체 Maker 미 발굴건, 기 설치된 Pneumatic Cylinder의 호환성을 위해 특정 사양으로 등록건 확인 후 승인,_x000D_ (특정 사양품감축 관련) 차후 입고시 스케치, 현물 확인을 통한 도면화,일반 사양화,복수화 전환 검토 요청 필히 부탁드립니다. 감사합니다. | AT15: N
A16: Q4627759 | B16: 0 | C16: 포스코 | D16: Pneumatic Cylinder | E16: Pneumatic Cylinder | F16: 전아람 | G16: 특정사양품(단수) | H16: ACTIVE | I16: L | J16: KRW | K16: CWC(DA),TC,80Dx80Dx150ST,[CA2YT80-150Z-W/SMC],FOR K4H DC0~2 PINCH ROLL POLISHER AIR CYLINDER,OR EQUIVALENT | L16: EA | M16: STANDARD | N16: CA2YT80-150Z-W | O16: SMC | R16: NONE | X16: FOR K4H DC0~2 PINCH ROLL POLISHER AIR CYLINDER | AB16: CA2Y 카다로그_20240122135108312.pdf | AH16: CA2YT 시리즈 사진_20240122135032098.PNG | AJ16: 김성겸 | AK16: (광양)압연설비1부 열연정비2섹션 | AL16: sk_kim@posco.co.kr | AM16: 유두현 | AN16: (광양)압연설비1부 열연정비2섹션 | AO16: r2dhlove@posco.co.kr | AP16: 2024-01-30 16:01:55 | AQ16: 2024 | AR16: 차후 재점검 | AS16: MRO e-Caltalog시스템 경유건으로 대체 Maker 미 발굴건, 기 설치된 Cylinder의 호환성을 위해 특정 사양으로 등록건 확인_x000D_ Q4458267등 유사사양 확인 후 stroke 길이 상이 등으로 승인. | AT16: N
A17: Q4602359 | B17: 0 | C17: 포스코 | D17: Pneumatic Cylinder | E17: Pneumatic Cylinder | F17: 전아람 | G17: 특정사양품(단수) | H17: ACTIVE | I17: L | J17: KRW | K17: CWC(DA),CA,63Dx20Dx300ST,[CDA2C63-KRT09JO-300Z-W-A54/SMC],FOR CGL OVEN FUME EXHAUST FAN DAMPER CYLINDER,OR EQUIVALENT | L17: EA | M17: STANDARD | N17: CDA2C63-KRT09JO-300Z-W-A54 | O17: SMC | R17: NONE | X17: FOR CGL OVEN FUME EXHAUST FAN DAMPER CYLINDER | AB17: CDA2C63-KRT09JO-300Z-W-A54 도면_20230322090536209.jpg | AE17: https://www.smckorea.co.kr/ | AH17: CDA2C63-KRT09JO-300Z-W-A54 도면_20230322090505368.jpg | AJ17: 김응백 | AK17: (포항)압연설비2부 냉연정비2섹션 | AL17: kebe12@posco.co.kr | AM17: 김동환 | AN17: (포항)압연설비2부 냉연정비2섹션 | AO17: nakdhs@posco.co.kr | AP17: 2023-06-09 10:06:57 | AQ17: 2023 | AR17: 차후 재점검 | AS17: MRO e-Caltalog시스템 공급사 소개건으로 대체 Maker 미 발굴건,기 설치된 Pneumatic Cylinder의 호환성을 위해 특정 사양으로 등록건 확인 후 승인,_x000D_ (특정 사양품감축 관련) 차후 입고시 스케치, 현물 확인을 통한 도면화,일반 사양화,복수화 전환 검토 요청 필히 부탁드립니다. 감사합니다. | AT17: N
A18: Q4580829 | B18: 0 | C18: 포스코 | D18: Pneumatic Cylinder | E18: Pneumatic Cylinder | F18: 전아람 | G18: 특정사양품(단수) | H18: ACTIVE | I18: L | J18: KRW | K18: 40Dx16Dx450ST,[CDA2F40-450Z-Z73/SMC],FOR P1H HSL LABEL MACHINE FEEDER PNEUMATIC CYLINDER,OR EQUIVALENT | L18: EA | M18: STANDARD | N18: CDA2F40-450Z-Z73 | O18: SMC | R18: NONE | X18: FOR P1H HSL LABEL MACHINE FEEDER PNEUMATIC CYLINDER | AB18: cda2f40-450z-z73_20221123105810184.jpg | AE18: https://www.smckorea.co.kr/ppis/data/catalog/CA2-Z.pdf | AH18: CDA2_20221123105527252.jpg | AJ18: 조규호 | AK18: (포항)압연설비부 열연정비섹션 | AL18: kyuho85@posco.co.kr | AM18: 이일하 | AN18: (포항)압연설비부 열연정비섹션 | AP18: 2022-11-25 08:11:02 | AQ18: 2022 | AR18: 불가피 품목 | AT18: N
A19: Q4611126 | B19: 0 | C19: 포스코 | D19: Pneumatic Cylinder | E19: Hydraulic & Pneumatics | F19: 전아람 | G19: 특정사양품(단수) | H19: ACTIVE | I19: L | J19: KRW | K19: CWD,TC,100Dx30Dx420ST,[CDA2T100-420Z-A93L-XC14/SMC],OR EQUIVALENT | L19: SET | M19: STANDARD | N19: CDA2T100-420Z-A93L-XC14 | O19: SMC | R19: NONE | AB19: CDA2T100-420Z-A93L-XC14도면_20230822112542085.jpg | AE19: https://www.smckorea.co.kr/esales/data/sangpum/kisul_qa/2023KS008009/CDA2T100-420Z-A93L-XC14.pdf | AH19: CA2_20230822112503791.jpg | AJ19: 김영민 | AK19: (포항)압연설비1부 선재정비섹션 | AL19: dudals9563@posco.co.kr | AM19: 김강민 | AN19: (포항)압연설비1부 선재정비섹션 | AO19: inhachris768@posco.co.kr | AP19: 2023-08-30 13:08:39 | AQ19: 2023 | AR19: 차후 재점검 | AS19: MRO e-Caltalog시스템 경유건으로 대체 Maker 미 발굴건,기 설치된 Pneumatic Cylinder의 호환성을 위해 특정 사양으로 등록건 확인 후 승인,_x000D_ (특정 사양품감축 관련) 차후 입고시 스케치, 현물 확인을 통한 도면화,일반 사양화,복수화 전환 검토 요청 필히 부탁드립니다. 감사합니다._x000D_ | AT19: N
A20: Q4504927 | B20: 0 | C20: 포스코퓨처엠 | D20: Pneumatic Cylinder | E20: Pneumatic Cylinder | F20: 전아람 | G20: 특정사양품(단수) | H20: ACTIVE | I20: L | J20: KRW | K20: CWC(DA),TC,40Dx16Dx125ST,10kgf/cm2,[CDA2T40-125Z-NW-M9BW/SMC] | L20: SET | M20: STANDARD | N20: CDA2T40-125Z-NW-M9BW | O20: SMC | R20: NONE | AB20: CDA2T40-T125Z_20200402103822497.png | AE20: https://www.smckorea.co.kr/ | AH20: 1_20241014165711546.JPG | AJ20: 황 성욱 | AK20: 음극소재사업소 | AL20: hwangsw@poscofuturem.com | AM20: 이 승권 | AN20: 음극재정비섹션 | AO20: tmdrnjs0809@poscofuturem.com | AP20: 2024-10-16 10:10:40 | AQ20: 2024 | AR20: 차후 재점검 | AT20: N
A21: Q4669390 | B21: 0 | C21: 포스코 | D21: Pneumatic Cylinder | E21: Pneumatic Cylinder | F21: 전아람 | G21: 특정사양품(단수) | H21: ACTIVE | I21: L | J21: KRW | K21: CWC(DA),CA,125Dx90Dx350ST,15kgf/cm2,[CDS1CN125-KRD0368-350-A54L/SMC],MAKER DWG NO:CDS1CN125-KRD0368-350-A54L,OR EQUIVALENT | L21: EA | M21: STANDARD | N21: CDS1CN125-KRD0368-350-A54L | O21: SMC | R21: NONE | W21: MAKER DWG NO:CDS1CN125-KRD0368-350-A54L | AB21: CDS1CN125-KRD0368-350-A54L 도면_20250325141804318.pdf | AE21: https://www.smckorea.co.kr/ppis/data/catalog/CS1.pdf | AH21: CDS1CN125-KRD0368-350-A54L 대표사진_20250325141743709.png | AJ21: 김형종 | AK21: (광양)압연설비2부 도금정비2섹션 | AL21: naju68@posco.co.kr | AM21: 이태호 | AN21: (광양)압연설비2부 도금정비2섹션 | AO21: leetaeho0411@posco.co.kr | AP21: 2025-04-02 10:04:28 | AQ21: 2025 | AR21: 차후 재점검 | AS21: MRO e-Caltalog시스템 경유건으로 대체 Maker 미 발굴건, 기 설치된 CYLINDER의 호환성을 위해 특정 사양으로 등록건 확인,_x000D_ Q4096129등 유사item 검색하였으나, 유사/동일품 없음 확인후 승인합니다._x000D_ (특정 사양품감축 관련) 차후 입고시 스케치, 현물 확인을 통한 도면화, 일반 사양화, 복수화 전환 검토 요청 필히 부탁드립니다. 감사합니다._x000D_ | AT21: N
A22: Q4629827 | B22: 0 | C22: 포스코 | D22: Pneumatic Cylinder | E22: Pneumatic Cylinder | F22: 전아람 | G22: 특정사양품(단수) | H22: ACTIVE | I22: L | J22: KRW | K22: 125Dx727Dx500ST,9.7kgf/cm2,[CDS1TN125-KRD0368-500-Z73L/SMC],MAKER DWG NO:CDS1TN125-KRD0368-500-Z73L,OR EQUIVALENT | L22: SET | M22: STANDARD | N22: CDS1TN125-KRD0368-500-Z73L | O22: SMC | R22: NONE | W22: MAKER DWG NO:CDS1TN125-KRD0368-500-Z73L | AB22: CDS1TN125-KRD0368-500-Z73L_20240109111550766.pdf | AH22: cds1_20240109111427520.png | AJ22: 민병찬 | AK22: (포항)제강설비부 제강정비섹션 | AL22: clazziquai@posco.co.kr | AM22: 김대철 | AN22: (포항)제강설비부 제강정비섹션 | AO22: kim.7@posco.co.kr | AP22: 2024-02-20 14:02:50 | AQ22: 2024 | AR22: 차후 재점검 | AT22: N
A23: Q4627207 | B23: 0 | C23: 포스코 | D23: Pneumatic Cylinder | E23: Pneumatic Cylinder | F23: 전아람 | G23: 특정사양품(단수) | H23: ACTIVE | I23: L | J23: KRW | K23: CWC(DA),CA,200Dx200Dx220ST,16kgf/cm2,[CDS2T200-200-CJCD0039/SMC],OR EQUIVALENT | L23: EA | M23: STANDARD | N23: CDS2T200-200-CJCD0039 | O23: SMC | R23: NONE | AB23: CDS2T200-200-CJCD0039_20240117110145614.pdf | AH23: cs2 실린더_20240117105756959.PNG | AJ23: 홍성현 | AK23: 광양생산부 정비섹션 | AM23: 이현우 | AN23: 광양생산부 정비섹션 | AO23: 2hyunwoo@posco.co.kr | AP23: 2024-01-25 11:01:22 | AQ23: 2024 | AR23: 차후 재점검 | AS23: MRO e-Caltalog시스템 경유건으로 대체 Maker 미 발굴건, 기 설치된 Cylinder의 호환성을 위해 특정 사양으로 등록건 확인 후 승인,_x000D_ 유사사양 확인함._x000D_ | AT23: N
A24: Q4636670 | B24: 0 | C24: 포스코 | D24: Pneumatic Cylinder | E24: Pneumatic Cylinder | F24: 전아람 | G24: 특정사양품(단수) | H24: ACTIVE | I24: L | J24: KRW | K24: CWC(DA),CA,320Dx320Dx250ST,[CDS2T320-250-CJCD0239/SMC],MAKER DWG NO:CDS2T320-250-CJCD0239,OR EQUIVALENT | L24: EA | M24: STANDARD | N24: CDS2T320-250-CJCD0239 | O24: SMC | R24: NONE | W24: MAKER DWG NO:CDS2T320-250-CJCD0239 | AB24: CDS2T320-250-CJCD0239_20240424160715569.pdf | AH24: cs2 실린더_20240424160715682.PNG | AJ24: 홍성현 | AK24: 광양생산부 정비섹션 | AM24: 이현우 | AN24: 광양생산부 정비섹션 | AO24: 2hyunwoo@posco.co.kr | AP24: 2024-04-25 08:04:39 | AQ24: 2024 | AR24: 차후 재점검 | AS24: Q4627207등 유사item 검색하였으나, Boa Size상이로 확인하고 승인합니다. | AT24: N
A25: Q4680486 | B25: 0 | C25: 포스코 | D25: Pneumatic Cylinder | E25: Pneumatic Cylinder | F25: 전아람 | G25: 특정사양품(단수) | H25: ACTIVE | I25: L | J25: KRW | K25: CWC(DA),CA,63Dx20Dx64ST,10kgf/cm2,[CG1DN63-64-CJD00567/SMC],MAKER DWG NO:CG1DN63-64-CJD00567,FOR K1C 3RCL OILER DRIP PAN SWING CYLINDER,OR EQUIVALENT | L25: EA | M25: STANDARD | N25: CG1DN63-64-CJD00567 | O25: SMC | R25: NONE | W25: MAKER DWG NO:CG1DN63-64-CJD00567 | X25: FOR K1C 3RCL OILER DRIP PAN SWING CYLINDER | AB25: CG1DN63-64-CJD00567_20250717071148728.pdf | AE25: https://www.smckorea.co.kr/ppis/data/domyun/CJD00567-AP..pdf | AH25: CG1_20250717071148769.jpg | AJ25: 이현식 | AK25: (광양)압연설비2부 냉연정비2섹션 | AL25: lee388@posco.co.kr | AM25: 최용석 | AN25: (광양)압연설비2부 냉연정비2섹션 | AO25: choiyongsuk@posco.co.kr | AP25: 2025-07-17 09:07:26 | AQ25: 2025 | AR25: 차후 재점검 | AS25: 기 설치된 물품의 호환성을 위해 특정 사양으로 등록건 확인,_x000D_ Q2230732등 유사item 검색하였으나, 유사/동일품 없음 확인후 승인합니다._x000D_ (특정 사양품감축 관련) 차후 입고시 스케치, 현물 확인을 통한 도면화, 일반 사양화, 복수화 전환 검토 요청 부탁드립니다. 감사합니다._x000D_ _x000D_ | AT25: N
A26: Q4609635 | B26: 0 | C26: 포스코 | D26: Pneumatic Cylinder | E26: Pneumatic Cylinder | F26: 전아람 | G26: 특정사양품(단수) | H26: ACTIVE | I26: L | J26: KRW | K26: CWC(DA),CF,40Dx14Dx40ST,10kgf/cm2,[CM2B40-40Z/SMC],FOR K1APL EXIT SEAL ROLL UPPER/LOWER SEAL PACKING OPEN/CLOSE,OR EQUIVALENT | L26: SET | M26: STANDARD | N26: CM2B40-40Z | O26: SMC | R26: NONE | X26: FOR K1APL EXIT SEAL ROLL UPPER/LOWER SEAL PACKING OPEN/CLOSE | AB26: CM2_20230816105642860.jpg | AE26: https://www.smckorea.co.kr/ppis/data/catalog/CM2-Z.pdf | AH26: CM2_20230816105623524.jpg | AJ26: 정정현 | AK26: (광양)압연설비2부 전기강판정비섹션 | AL26: wjd1670@posco.co.kr | AM26: 박원준 | AN26: (광양)압연설비2부 전기강판정비섹션 | AO26: wjpark@posco.co.kr | AP26: 2023-08-18 10:08:01 | AQ26: 2023 | AR26: 차후 재점검 | AS26: MRO e-Caltalog시스템 경유건으로 대체 Maker 미 발굴건,K1APL EXIT SEAL ROLL UPPER/LOWER SEAL PACKING OPEN/CLOSE로 기 설치된 Pneumatic Cylinder의 호환성을 위해 특정 사양으로 등록건 확인 후 승인,(특정 사양품감축 관련) 차후 입고시 스케치, 현물 확인을 통한 도면화,일반 사양화,복수화 전환 검토 요청 필히 부탁드립니다. 감사합니다. | AT26: N
A27: Q4649046 | B27: 0 | C27: 포스코 | D27: Pneumatic Cylinder | E27: Pneumatic Cylinder | F27: 전아람 | G27: 특정사양품(단수) | H27: ACTIVE | I27: L | J27: KRW | K27: CWC(DA),CC,40Dx14Dx350ST,10kgf/cm2,[CDBM2B40-350-HN-A93/SMC],FOR 3CAL SAMPLE MACHINE "Y" HEAD,OR EQUIVALENT | L27: EA | M27: STANDARD | N27: CDBM2B40-350-HN-A93 | O27: SMC | R27: NONE | X27: FOR 3CAL SAMPLE MACHINE "Y" HEAD | AB27: CM2엔드락_20240808163226993.jpg | AE27: https://www.smckorea.co.kr/ppis/data/catalog/CM2-Z.pdf | AH27: CM2엔드락_20240808163208789.jpg | AJ27: 김응백 | AK27: (포항)압연설비2부 냉연정비2섹션 | AL27: kebe12@posco.co.kr | AM27: 왕우현 | AN27: (포항)압연설비2부 냉연정비2섹션 | AO27: dngus0503@posco.co.kr | AP27: 2024-09-02 11:09:47 | AQ27: 2024 | AR27: 차후 재점검 | AT27: N
A28: Q4697437 | B28: 0 | C28: 포스코 | D28: Pneumatic Cylinder | E28: Pneumatic Cylinder | F28: 전아람 | G28: 특정사양품(단수) | H28: ACTIVE | I28: L | J28: KRW | K28: CWC(DA),TC,200Dx246ST,[CDS1TN200-246K-A54/SMC],OR EQUIVALENT | L28: SET | M28: STANDARD | N28: CDS1TN200-246K-A54 | O28: SMC | Q28: UNKNOWN | R28: NONE | T28: UNKNOWN | U28: NONE | AB28: CS1_20260106170106839.pdf | AH28: CS1LN125-KRT04KO-600_20260106171938339.png | AJ28: 구건웅 | AK28: (광양)제강설비부 제강정비섹션 | AL28: kkkunwoong@posco.co.kr | AM28: 구건웅 | AN28: (광양)제강설비부 제강정비섹션 | AO28: kkkunwoong@posco.co.kr | AP28: 2026-01-07 08:01:32 | AQ28: 2026 | AR28: 차후 재점검 | AS28: 기 설치된 물품의 호환성을 위해 특정 사양으로 등록건 확인, 유사 item 검색하였으나, 유사/동일품 없음 확인후 승인합니다. (특정 사양품감축 관련) 차후 입고시 스케치, 현물 확인을 통한 도면화, 일반 사양화, 복수화 전환 검토 요청 부탁드립니다. 감사합니다. | AT28: N
A29: Q4609854 | C29: 포스코 | D29: Pneumatic Cylinder | E29: Pneumatic Cylinder | F29: 전아람 | G29: 특정사양품(단수) | H29: ACTIVE | I29: L | J29: KRW | K29: CWC(DA),TD,300Dx70Dx550ST,10kgf/cm2,[CS1C0-VOA003-550/SMC],FOR K1APL COOLING DEVICE UPPER CASING UP/DOWN PNEUMATIC CYLINDER,OR EQUIVALENT | L29: SET | M29: STANDARD | N29: CS1C0-VOA003-550 | O29: SMC | R29: NONE | X29: FOR K1APL COOLING DEVICE UPPER CASING UP/DOWN PNEUMATIC CYLINDER | AB29: CS1C0-VOA003-550 사양서_20230816104357707.jpg | AH29: CS1_20230816104334033.jpg | AJ29: 정정현 | AK29: (광양)압연설비2부 전기강판정비섹션 | AL29: wjd1670@posco.co.kr | AM29: 박원준 | AN29: (광양)압연설비2부 전기강판정비섹션 | AO29: wjpark@posco.co.kr | AP29: 2023-08-21 09:08:14 | AQ29: 2023 | AR29: 차후 재점검 | AS29: MRO e-Caltalog시스템 경유건으로 대체 Maker 미 발굴건,K1APL STRIP COOLING DEVICE 의 핵심 부품으로 기 설치된 Pneumatic Cylinder의 호환성을 위해 특정 사양으로 등록건 확인 후 승인,(특정 사양품감축 관련) 차후 입고시 스케치, 현물 확인을 통한 도면화,일반 사양화,복수화 전환 검토 요청 필히 부탁드립니다. 감사합니다. | AT29: N
A30: Q4609677 | C30: 포스코 | D30: Pneumatic Cylinder | E30: Hydraulic & Pneumatics | F30: 전아람 | G30: 특정사양품(단수) | H30: ACTIVE | I30: L | J30: KRW | K30: CWC(DA),CD,140Dx36Dx135ST,10kgf/cm2,[CS1CN140-KRT04KO-135-XC5/SMC],FOR K1APL STRIP GRIPPER UP/DOWN PNEUMATIC CYLINDER,OR EQUIVALENT | L30: SET | M30: STANDARD | N30: CS1CN140-KRT04KO-135-XC5 | O30: SMC | R30: NONE | X30: FOR K1APL STRIP GRIPPER UP/DOWN PNEUMATIC CYLINDER | AB30: CS1CN140-KRT04KO-135-XC5_20230818130538338.jpg | AH30: CS1_20230816104955978.jpg | AJ30: 정정현 | AK30: (광양)압연설비2부 전기강판정비섹션 | AL30: wjd1670@posco.co.kr | AM30: 박원준 | AN30: (광양)압연설비2부 전기강판정비섹션 | AO30: wjpark@posco.co.kr | AP30: 2023-08-18 13:08:25 | AQ30: 2023 | AR30: 차후 재점검 | AS30: MRO e-Caltalog시스템 경유건으로 대체 Maker 미 발굴건,K1APL STRIP GRIPPER UP/DOWN PNEUMATIC CYLINDER로 기 설치된 Pneumatic Cylinder의 호환성을 위해 특정 사양으로 등록건 확인 후 승인,(특정 사양품감축 관련) 차후 입고시 스케치, 현물 확인을 통한 도면화,일반 사양화,복수화 전환 검토 요청 필히 부탁드립니다. 감사합니다.(현장 Name Plate사진으로 사양 확인건) | AT30: N
A31: Q4608549 | C31: 포스코 | D31: Pneumatic Cylinder | E31: Pneumatic Cylinder | F31: 전아람 | G31: 특정사양품(단수) | H31: ACTIVE | I31: L | J31: KRW | K31: CWC(DA),CB,200Dx50Dx150ST,10kgf/cm2,[CS1CN200-KRD0368-150/SMC],FOR K1APL NO.3 TENSION BRIDLE ROLL SNUBBER ROLL UP & DOWN PNEUMATIC CYLINDER,OR EQUIVALENT | L31: SET | M31: STANDARD | N31: CS1CN200-KRD0368-150 | O31: SMC | R31: NONE | X31: FOR K1APL NO.3 TENSION BRIDLE ROLL SNUBBER ROLL UP & DOWN PNEUMATIC CYLINDER | AB31: CS1CN200-KRD0368-150_20230807164932049.jpg | AE31: https://www.smckorea.co.kr/ppis/data/catalog/CS1.pdf | AH31: Cylinder_20230807165018060.jpg | AJ31: 정정현 | AK31: (광양)압연설비2부 전기강판정비섹션 | AL31: wjd1670@posco.co.kr | AM31: 박원준 | AN31: (광양)압연설비2부 전기강판정비섹션 | AO31: wjpark@posco.co.kr | AP31: 2023-08-08 11:08:11 | AQ31: 2023 | AR31: 차후 재점검 | AS31: MRO e-Caltalog시스템 경유건으로 대체 Maker 미 발굴건,K1APL NO.3 TENSION BRIDLE ROLL SNUBBER ROLL UP & DOWN PNEUMATIC CYLINDER로 기 설치된 Pneumatic Cylinder의 호환성을 위해 특정 사양으로 등록건 확인 후 승인,(특정 사양품감축 관련) 차후 입고시 스케치, 현물 확인을 통한 도면화,일반 사양화,복수화 전환 검토 요청 필히 부탁드립니다. 감사합니다. | AT31: N
A32: Q4660031 | C32: 포스코 | D32: Pneumatic Cylinder | E32: Pneumatic Cylinder | F32: 전아람 | G32: 특정사양품(단수) | H32: ACTIVE | I32: L | J32: KRW | K32: 250Dx60Dx830ST,[CS1D250-KRD0368-830/SMC],FOR K3H SCRAP CHUTE LIFT,OR EQUIVALENT | L32: EA | M32: STANDARD | N32: CS1D250-KRD0368-830 | O32: SMC | R32: NONE | X32: FOR K3H SCRAP CHUTE LIFT | AB32: cs1d250_20241218132730514.png | AE32: https://www.smckorea.co.kr/homepage/ver3.5/product/catalogue_sub_detail.asp?cata_no=914 | AH32: 캡처1_20250226141148414.png | AJ32: 김성겸 | AK32: (광양)압연설비1부 열연정비2섹션 | AL32: sk_kim@posco.co.kr | AM32: 양승국 | AN32: (광양)압연설비1부 열연정비2섹션 | AO32: skystc1997@posco.co.kr | AP32: 2025-02-27 13:02:36 | AQ32: 2025 | AR32: 차후 재점검 | AS32: Q4020093등 유사item 검색하였으나, stroke등 상이함 확인후 승인합니다. | AT32: N
A33: Q4608555 | C33: 포스코 | D33: Pneumatic Cylinder | E33: Pneumatic Cylinder | F33: 전아람 | G33: 특정사양품(단수) | H33: ACTIVE | I33: L | J33: KRW | K33: CWC(DA),CB,250Dx60Dx400ST,10kgf/cm2,[CS1CN250-KRD0368-400/SMC],FOR K1APL NO.10 STEERING ROLL UP & DOWN PNEUMATIC CYLINDER,OR EQUIVALENT | L33: SET | M33: STANDARD | N33: CS1CN250-KRD0368-400 | O33: SMC | R33: NONE | X33: FOR K1APL NO.10 STEERING ROLL UP & DOWN PNEUMATIC CYLINDER | AB33: CS1DN250-KRD0368-400 라벨_20230803111519273.jpg | AE33: https://www.smckorea.co.kr/ppis/data/catalog/CS1.pdf | AH33: Cylinder_20230807165711445.jpg | AJ33: 정정현 | AK33: (광양)압연설비2부 전기강판정비섹션 | AL33: wjd1670@posco.co.kr | AM33: 박원준 | AN33: (광양)압연설비2부 전기강판정비섹션 | AO33: wjpark@posco.co.kr | AP33: 2023-08-08 11:08:33 | AQ33: 2023 | AR33: 차후 재점검 | AS33: MRO e-Caltalog시스템 경유건으로 대체 Maker 미 발굴건,K1APL NO.10 STEERING ROLL UP & DOWN PNEUMATIC CYLINDER로 기 설치된 Pump의 호환성을 위해 특정 사양으로 등록건 확인 후 승인,(특정 사양품감축 관련) 차후 입고시 스케치, 현물 확인을 통한 도면화,일반 사양화,복수화 전환 검토 요청 필히 부탁드립니다. 감사합니다. | AT33: N
A34: Q4662387 | C34: 포스코 | D34: Pneumatic Cylinder | E34: Pneumatic Cylinder | F34: 전아람 | G34: 특정사양품(단수) | H34: ACTIVE | I34: L | J34: KRW | K34: CWC(DA),FA,180Dx45Dx80ST,9.9kgf/cm2,[CS1F180-80-KRHD0444/SMC],FOR 1CGL EXIT WRINGER ROLL OPEN&CLOSE CYLINDER,OR EQUIVALENT | L34: EA | M34: STANDARD | N34: CS1F180-80-KRHD0444 | O34: SMC | R34: NONE | X34: FOR 1CGL EXIT WRINGER ROLL OPEN&CLOSE CYLINDER | AB34: CS1F180-80-KRHD0444 도면_20250102163354322.pdf | AE34: https://www.smckorea.co.kr/esales/data/sangpum/kisul_qa/2024KS012656/KRHD0444-AP.pdf | AH34: CS1_20250102163143465.jpg | AI34: CS1F180-80-KRHD0444_SMC_20250116152515461.jpg | AJ34: 박광웅 | AK34: (광양)압연설비2부 도금정비1섹션 | AM34: 김대한 | AN34: (광양)압연설비2부 도금정비1섹션 | AP34: 2025-01-20 15:01:54 | AQ34: 2025 | AR34: 차후 재점검 | AS34: MRO e-Caltalog시스템 경유건으로 대체 Maker 미 발굴건, 기 설치된 Cylinder의 호환성을 위해 특정 사양으로 등록건 확인,_x000D_ Q4111676 등 유사item 검색하였으나, 유사/동일품 없음 확인후 승인합니다._x000D_ (특정 사양품감축 관련) 차후 입고시 스케치, 현물 확인을 통한 도면화,일반 사양화, 복수화 전환 검토 요청 필히 부탁드립니다. 감사합니다._x000D_ | AT34: N
A35: Q4636081 | C35: 포스코 | D35: Pneumatic Cylinder | E35: Pneumatic Cylinder | F35: 전아람 | G35: 특정사양품(단수) | H35: ACTIVE | I35: L | J35: KRW | K35: CWC(DA),FA,180Dx45Dx100ST,9.89kgf/cm2,[CS1FN180-KRT04JO-100/SMC],MAKER DWG NO:CS1FN180-KRT04JO-100,FOR 1EGL ACS & ARS WRINGER ROLL TOP PNEUMATIC CYLINDER,OR EQUIVALENT | L35: EA | M35: STANDARD | N35: CS1FN180-KRT04JO-100 | O35: SMC | R35: NONE | W35: MAKER DWG NO:CS1FN180-KRT04JO-100 | X35: FOR 1EGL ACS & ARS WRINGER ROLL TOP PNEUMATIC CYLINDER | AB35: CS1FN180-KRT04JO-100 도면_20240417162506734.pdf | AE35: https://www.smckorea.co.kr/ppis/data/catalog/CS1.pdf | AH35: CS1FN180-KRT04JO-100 대표_20240417162429494.PNG | AJ35: 박광웅 | AK35: (광양)압연설비2부 도금정비1섹션 | AM35: 박정규 | AN35: (광양)압연설비2부 도금정비1섹션 | AO35: pjk2540@posco.co.kr | AP35: 2024-04-19 09:04:43 | AQ35: 2024 | AR35: 차후 재점검 | AS35: Q4111676등 유사 item 검색하였으나, stroke등 상이하여 확인하고 승인합니다. | AT35: N
A36: Q4608565 | C36: 포스코 | D36: Pneumatic Cylinder | E36: Pneumatic Cylinder | F36: 전아람 | G36: 특정사양품(단수) | H36: ACTIVE | I36: L | J36: KRW | K36: CWC(DA),FE,200Dx50Dx150ST,10kgf/cm2,[CS1DN250-KRD0368-400/SMC],FOR K1APL FURNACE WCS DAM ROLL UP & DOWN PNEUMATIC CYLINDER,OR EQUIVALENT | L36: SET | M36: STANDARD | N36: CS1DN250-KRD0368-400 | O36: SMC | R36: NONE | X36: FOR K1APL FURNACE WCS DAM ROLL UP & DOWN PNEUMATIC CYLINDER | AB36: CS1FN200-KRT04KO-150-XC5 라벨_20230803111800907.jpg | AE36: https://www.smckorea.co.kr/ppis/data/catalog/CS1.pdf | AH36: Cylinder_20240116160853051.jpg | AJ36: 정정현 | AK36: (광양)압연설비2부 전기강판정비섹션 | AL36: wjd1670@posco.co.kr | AM36: 박원준 | AN36: (광양)압연설비2부 전기강판정비섹션 | AO36: wjpark@posco.co.kr | AP36: 2024-01-18 10:01:51 | AQ36: 2024 | AR36: 차후 재점검 | AS36: MRO e-Caltalog시스템 경유건으로 대체 Maker 미 발굴건,K1APL FURNACE WCS DAM ROLL UP & DOWN PNEUMATIC CYLINDER로 기 설치된 Pneumatic Cylinder의 호환성을 위해 특정 사양으로 등록건 확인 후 승인,(특정 사양품감축 관련) 차후 입고시 스케치, 현물 확인을 통한 도면화,일반 사양화,복수화 전환 검토 요청 필히 부탁드립니다. 감사합니다. | AT36: N
A37: Q4685560 | C37: 포스코 | D37: Pneumatic Cylinder | E37: Pneumatic Cylinder | F37: 전아람 | G37: 특정사양품(단수) | H37: ACTIVE | I37: L | J37: KRW | K37: 200Dx50Dx80ST,9.89kgf/cm2,[CS1FN200-KRT04KO-80/SMC],2APL PICKLE SQUEEZE ROLL UP/DOWN,OR EQUIVALENT | L37: SET | M37: STANDARD | N37: CS1FN200-KRT04KO-80 | O37: SMC | R37: NONE | X37: 2APL PICKLE SQUEEZE ROLL UP/DOWN | AB37: CS1FN200-KRT04KO-80_20250901145913989.pdf | AE37: https://www.smckorea.co.kr/homepage/ver3.5/product/catalogue_sub_detail.asp?no=914 | AH37: CS1_20250827152926703.jpg | AJ37: 김원길 | AK37: (포항)압연설비2부 STS압연정비섹션 | AL37: 855956@posco.co.kr | AM37: 정세훈 | AN37: (포항)압연설비2부 STS압연정비섹션 | AO37: sehun0129@posco.co.kr | AP37: 2025-09-02 16:09:21 | AQ37: 2025 | AR37: 차후 재점검 | AS37: 기 설치된 물품의 호환성을 위해 특정 사양으로 등록건 확인,_x000D_ 유사item 검색하였으나, 유사/동일품 없음 확인후 승인합니다._x000D_ (특정 사양품감축 관련) 차후 입고시 스케치, 현물 확인을 통한 도면화, 일반 사양화, 복수화 전환 검토 요청 부탁드립니다. 감사합니다._x000D_ | AT37: N
A38: Q4606860 | C38: 포스코 | D38: Pneumatic Cylinder | E38: Pneumatic Cylinder | F38: 전아람 | G38: 특정사양품(단수) | H38: ACTIVE | I38: L | J38: KRW | K38: CWC(DA),TD,160Dx40Dx140ST,9.7kgf/cm2,[CS1TN160-KRD0368-140-XC14A/SMC],FOR 1EGL WELDER DOWN PASS PINCH ROLL UP/DOWN CYLINDER,OR EQUIVALENT | L38: SET | M38: STANDARD | N38: CS1TN160-KRD0368-140-XC14A | O38: SMC | R38: NONE | X38: FOR 1EGL WELDER DOWN PASS PINCH ROLL UP/DOWN CYLINDER | AB38: CS1TN160-KRD0368-140-XC14A 도면_20230718114028531.jpg | AE38: https://www.smckorea.co.kr/ | AH38: CS1_20230718113831032.jpg | AJ38: 김응백 | AK38: (포항)압연설비2부 냉연정비2섹션 | AL38: kebe12@posco.co.kr | AM38: 백종수 | AN38: (포항)압연설비2부 냉연정비2섹션 | AO38: jongsu97@posco.co.kr | AP38: 2023-07-21 08:07:08 | AQ38: 2023 | AR38: 차후 재점검 | AS38: MRO e-Caltalog시스템 경유건으로 대체 Maker 미 발굴건,1EGL WELDER DOWN PASS PINCH ROLL UP/DOWN CYLINDER로 기 설치된 Pneumatic Cylinder의 호환성을 위해 특정 사양으로 등록건 확인 후 승인,(특정 사양품감축 관련) 차후 입고시 스케치, 현물 확인을 통한 도면화,일반 사양화,복수화 전환 검토 요청 필히 부탁드립니다. 감사합니다. | AT38: N
A39: Q4592954 | C39: 포스코 | D39: Pneumatic Cylinder | E39: Pneumatic Cylinder | F39: 전아람 | G39: 특정사양품(단수) | H39: ACTIVE | I39: L | J39: KRW | K39: CWC(DA),TC,180Dx45Dx200ST,[CS1TN180-200-CJBD0280/SMC],FOR 1CGL BANDING MACHINE CARRIDGE SHIFTING CYLINDER,OR EQUIVALENT | L39: EA | M39: STANDARD | N39: CS1TN180-200-CJBD0280 | O39: SMC | R39: NONE | X39: FOR 1CGL BANDING MACHINE CARRIDGE SHIFTING CYLINDER | AB39: CS1TN180-200-CJBD0280 도면_20230309101508507.jpg | AE39: https://www.smckorea.co.kr/ | AH39: CS1TN180-200-CJBD0280 도면_20230308172721343.jpg | AJ39: 김응백 | AK39: (포항)압연설비2부 냉연정비2섹션 | AL39: kebe12@posco.co.kr | AM39: 박동방석 | AN39: (포항)압연설비2부 냉연정비2섹션 | AP39: 2023-03-14 09:03:51 | AQ39: 2023 | AR39: 불가피 품목 | AS39: MRO e-Caltalog시스템 경유건으로 대체 Maker 미 발굴건,도금 1CGL Banding Machine Carridge Shifting Cylinder의 핵심 부품으로 기 설치된 Pneumatic Cylinder의 호환성을 위해 특정 사양으로 등록건 확인 후 승인,(특정 사양품감축 관련) 차후 입고시 스케치, 현물 확인을 통한 도면화,일반 사양화,복수화 전환 검토 요청 필히 부탁드립니다. (주)TPC메카트로닉스 기술영업팀 노민영책임(010-9323-4684)과 복수화 재 검토 요청 부탁드립니다.감사합니다. | AT39: N
A40: Q4592850 | C40: 포스코 | D40: Pneumatic Cylinder | E40: Pneumatic Cylinder | F40: 전아람 | G40: 특정사양품(단수) | H40: ACTIVE | I40: L | J40: KRW | K40: CWC(DA),TC,250Dx60Dx1750ST,[CS1TN250-1750-CJBD0272/SMC],FOR 1CGL BANDING FRAME HEAD LIFTING CYLINDER | L40: EA | M40: STANDARD | N40: CS1TN250-1750-CJBD0272 | O40: SMC | R40: NONE | X40: FOR 1CGL BANDING FRAME HEAD LIFTING CYLINDER | AB40: CS1TN250-1750-CJBD0272 도면_20230309101322838.jpg | AE40: https://www.smckorea.co.kr | AH40: CS1TN250-1750-CJBD0272 도면_20230308172501550.jpg | AJ40: 김응백 | AK40: (포항)압연설비2부 냉연정비2섹션 | AL40: kebe12@posco.co.kr | AM40: 박동방석 | AN40: (포항)압연설비2부 냉연정비2섹션 | AP40: 2023-03-13 09:03:11 | AQ40: 2023 | AR40: 차후 재점검 | AS40: MRO e-Caltalog시스템 공급사 소개건으로 대체 Maker 미 발굴건, 기 설치된 Pneumatic Cylinder의 호환성을 위해 특정 사양으로 등록건 확인 후 승인,_x000D_ (특정 사양품감축 관련) 차후 입고시 스케치, 현물 확인을 통한 도면화,일반 사양화,복수화 전환 검토 요청 필히 부탁드립니다. 감사합니다._x000D_ | AT40: N
A41: Q4609634 | C41: 포스코 | D41: Pneumatic Cylinder | E41: Pneumatic Cylinder | F41: 전아람 | G41: 특정사양품(단수) | H41: ACTIVE | I41: L | J41: KRW | K41: CWC(DA),CD,125Dx32Dx120ST,10kgf/cm2,[CDS2D125-120/SMC],FOR K1APL EXIT SHEAR PINCH ROLL UP & DOWN,OR EQUIVALENT | L41: SET | M41: STANDARD | N41: CDS2D125-120 | O41: SMC | R41: NONE | X41: FOR K1APL EXIT SHEAR PINCH ROLL UP & DOWN | AB41: CS2_20230816105444058.jpg | AE41: https://www.smckorea.co.kr/ppis/data/catalog/CS2.pdf | AH41: CS2_20230816105427834.jpg | AJ41: 정정현 | AK41: (광양)압연설비2부 전기강판정비섹션 | AL41: wjd1670@posco.co.kr | AM41: 박원준 | AN41: (광양)압연설비2부 전기강판정비섹션 | AO41: wjpark@posco.co.kr | AP41: 2023-08-18 10:08:16 | AQ41: 2023 | AR41: 차후 재점검 | AS41: MRO e-Caltalog시스템 경유건으로 대체 Maker 미 발굴건,K1APL EXIT SHEAR PINCH ROLL UP & DOWN로 기 설치된 Pneumatic Cylinder의 호환성을 위해 특정 사양으로 등록건 확인 후 승인,(특정 사양품감축 관련) 차후 입고시 스케치, 현물 확인을 통한 도면화,일반 사양화,복수화 전환 검토 요청 필히 부탁드립니다. 감사합니다. | AT41: N
A42: Q4595473 | C42: 포스코 | D42: Pneumatic Cylinder | E42: Pneumatic Cylinder | F42: 전아람 | G42: 특정사양품(단수) | H42: ACTIVE | I42: L | J42: KRW | K42: CSA,CA,32Dx33.6Dx300ST,10kgf/cm2,[CDY1S32-300BZ-A93/SMC],WITH SWITCH RAIL, AUTO SWITCH SWITCH, SHOCK ABSORBER,FOR PUNCH PRESS,OR EQUIVALENT | L42: SET | M42: STANDARD | N42: CDY1S32-300BZ-A93 | O42: SMC | R42: NONE | W42: WITH SWITCH RAIL, AUTO SWITCH SWITCH, SHOCK ABSORBER | X42: FOR PUNCH PRESS | AB42: CY1S_20230323152908225.jpg | AE42: https://www.google.com/url?sa=t&rct=j&q=&esrc=s&source=web&cd=&ved=2ahUKEwieronB65P-AhVFON4KHWhlBNwQFnoECAUQAQ&url=https%3A%2F%2Fcontent2.smcetech.com%2Fpdf%2FCY.pdf&usg=AOvVaw1cP-gIP8cALTUtmVwRhrNI | AH42: CY1S_20230331074033096.jpg | AJ42: 이일환 | AK42: (포항)EIC기술부 자동화설비정비섹션 | AM42: 이규문 | AN42: (포항)EIC기술부 자동화설비정비섹션 | AO42: kmlee0907@posco.co.kr | AP42: 2023-04-13 15:04:58 | AQ42: 2023 | AR42: 차후 재점검 | AS42: MRO e-Caltalog시스템 경유건으로 대체 Maker 미 발굴건,재질시험실 전기강판 펀치프레스 시편이송용 실린더의 핵심 부품으로 기 설치된 Pneumatic Cylinder의 호환성을 위해 특정 사양으로 등록건 확인 후 승인,(특정 사양품감축 관련) 차후 입고시 스케치, 현물 확인을 통한 도면화,일반 사양화,복수화 전환 검토 요청 필히 부탁드립니다. (주)TPC메카트로닉스 기술영업팀 노민영책임(010-9323-4684)과 복수화 재 검토 요청 부탁드립니다.감사합니다._x000D_ | AT42: N
A43: Q4661659 | B43: 0 | C43: 포스코 | D43: Pneumatic Cylinder | E43: Pneumatic Cylinder | F43: 전아람 | G43: 특정사양품(단수) | H43: ACTIVE | I43: L | J43: KRW | K43: CWC(DA),FA,30Dx100Dx220ST,[ACM-N FA 100-S220/KCC],FOR K1APL EXIT SIDE GUIDE OPEN CLOSE,OR EQUIVALENT | L43: SET | M43: STANDARD | N43: ACM-N FA 100-S220 | O43: KCC | R43: NONE | X43: FOR K1APL EXIT SIDE GUIDE OPEN CLOSE | AB43: K1APL Exit Side Guide OpenClose KCC Pneumatic Cylinder 카탈로그_20250110074338417.png | AE43: https://www.kccpr.com/bbs/board.php?bo_table=Pneumatic_cylinder&wr_id=2&sca=%ED%91%9C%EC%A4%80+%EC%8B%A4%EB%A6%B0%EB%8D%94 | AH43: K1APL Exit Side Guide OpenClose KCC Pneumatic Cylinder 카탈로그 실물 사진_20250110074338483.png | AJ43: 박원준 | AK43: (광양)압연설비2부 전기강판정비섹션 | AL43: wjpark@posco.co.kr | AM43: 최인오 | AN43: (광양)압연설비2부 전기강판정비섹션 | AO43: choi6959@posco.co.kr | AP43: 2025-01-14 13:01:22 | AQ43: 2025 | AR43: 차후 재점검 | AS43: MRO e-Caltalog시스템 경유건으로 대체 Maker 미 발굴건, 기 설치된 Cylinder의 호환성을 위해 특정 사양으로 등록건 확인, _x000D_ Q4124778등 유사item 검색하였으나, 유사/동일품 없음 확인후 승인합니다. _x000D_ (특정 사양품감축 관련) 차후 입고시 스케치, 현물 확인을 통한 도면화,일반 사양화, 복수화 전환 검토 요청 필히 부탁드립니다. 감사합니다._x000D_ | AT43: N
A44: Q4607652 | B44: 0 | C44: 포스코 | D44: Pneumatic Cylinder | E44: Hydraulic & Pneumatics | F44: 전아람 | G44: 특정사양품(단수) | H44: ACTIVE | I44: L | J44: KRW | K44: CWC(DA),FA,200Dx50Dx2350ST,[ACL N H FA200 S2350 -Y D-J59K/KCC],1-1RCL BANDING MACHINE LIFTER | L44: SET | M44: STANDARD | N44: ACL N H FA200 S2350 -Y D-J59K | O44: KCC | R44: NONE | X44: 1-1RCL BANDING MACHINE LIFTER | AB44: KCC 사양표_20230729092321253.png | AE44: https://www.kccpr.com/bbs/search.php?url=https%3A%2F%2Fwww.kccpr.com%2Fbbs%2Fsearch.php&stx=ACL+N+H+FA200+ | AH44: Banding Machine Head Lift Cylinder_20230616082952201.png | AJ44: 곽진섭 | AK44: (광양)EIC기술부 자동화설비정비섹션 | AL44: ggwakjs@posco.co.kr | AM44: 곽진섭 | AN44: (광양)EIC기술부 자동화설비정비섹션 | AO44: ggwakjs@posco.co.kr | AP44: 2023-07-31 09:07:31 | AQ44: 2023 | AR44: 차후 재점검 | AS44: MRO e-Caltalog시스템 경유건으로 대체 Maker 미 발굴건,Banding Machine Header Lift의 핵심 부품으로 기 설치된 Pneumatic Cylinder의 호환성을 위해 특정 사양으로 등록건 확인 후 승인,(특정 사양품감축 관련) 차후 입고시 스케치, 현물 확인을 통한 도면화,일반 사양화,복수화 전환 검토 요청 필히 부탁드립니다. (11) 특허등록 번호 (특허품이 아닌 경우 해당없음으로 기입)부탁드립니다. 향후 미 기입시 Rework처리 될수 있습니다. Q4482287와 유사건으로 Stroke가 다름 확인건, 감사합니다._x000D_ | AT44: N
A45: Q4660885 | C45: 포스코 | D45: Pneumatic Cylinder | E45: Pneumatic Cylinder | F45: 전아람 | G45: 특정사양품(단수) | H45: ACTIVE | I45: L | J45: KRW | K45: 10Dx4Dx60ST,0.61kgf/cm2,[MXH10-60Z-M9NS/SMC],OR EQUIVALENT | L45: SET | M45: BLANKET | N45: MXH10-60Z-M9NS | O45: SMC | R45: NONE | AB45: MXH-Z_20250107115123648.pdf | AE45: https://www.smckorea.co.kr/ppis/data/catalog/MXH-Z.pdf?ver=7980.5295135706665 | AH45: MXH10-60Z-M9NS_20250107115123747.jpg | AJ45: 유상용 | AK45: (광양)EIC기술부 자동화설비정비섹션 | AL45: hammer@posco.co.kr | AM45: 성홍기 | AN45: (광양)EIC기술부 자동화설비정비섹션 | AO45: posshk@posco.co.kr | AP45: 2025-01-08 09:01:49 | AQ45: 2025 | AR45: 차후 재점검 | AS45: MRO e-Caltalog시스템 경유건으로 대체 Maker 미 발굴건, 기 설치된 Cylinder의 호환성을 위해 특정 사양으로 등록건 확인, _x000D_ Q4644095등 유사item 검색하였으나, 유사/동일품 없음 확인후 승인합니다. _x000D_ | AT45: N
A46: Q4685419 | C46: 포스코 | D46: Pneumatic Cylinder | E46: Pneumatic Cylinder | F46: 전아람 | G46: 특정사양품(단수) | H46: ACTIVE | I46: L | J46: KRW | K46: 25Dx700ST,8kgf/cm2,[MY1B25-700Z-M9BW/SMC],OR EQUIVALENT | L46: EA | M46: STANDARD | N46: MY1B25-700Z-M9BW | O46: SMC | R46: NONE | AB46: MY1B25-700Z-M9BW_20250827113240355.jpg | AE46: https://www.smckorea.co.kr/ppis/data/catalog/MY1.pdf | AH46: MY1B_20250827113210693.jpg | AJ46: 최봉근 | AK46: (광양)품질기술부 재질시험섹션 | AL46: bongkeun.choi@posco.co.kr | AM46: 김윤기 | AN46: (광양)품질기술부 재질시험섹션 | AO46: kok2213@posco.co.kr | AP46: 2025-09-01 17:09:10 | AQ46: 2025 | AR46: 차후 재점검 | AS46: 기 설치된 물품의 호환성을 위해 특정 사양으로 등록건 확인,_x000D_ 유사item 검색하였으나, 유사/동일품 없음 확인후 승인합니다._x000D_ (특정 사양품감축 관련) 차후 입고시 스케치, 현물 확인을 통한 도면화, 일반 사양화, 복수화 전환 검토 요청 부탁드립니다. 감사합니다._x000D_ | AT46: N
A47: Q4595474 | C47: 포스코 | D47: Pneumatic Cylinder | E47: Pneumatic Cylinder | F47: 전아람 | G47: 특정사양품(단수) | H47: ACTIVE | I47: L | J47: KRW | K47: CSA,CA,25Dx0Dx1600ST,10kgf/cm2,[MY1CWK25-1600-Z73/SMC],WITH AUTOSWITCH,FOR PUNCH PRESS,OR EQUIVALENT | L47: SET | M47: STANDARD | N47: MY1CWK25-1600-Z73 | O47: SMC | R47: NONE | W47: WITH AUTOSWITCH | X47: FOR PUNCH PRESS | AB47: MY1W_20230323153840916.jpg | AE47: https://www.smckorea.co.kr/ppis/data/catalog/MY1()W.pdf | AH47: MY1W_20230323153804659.jpg | AJ47: 이일환 | AK47: (포항)EIC기술부 자동화설비정비섹션 | AM47: 이규문 | AN47: (포항)EIC기술부 자동화설비정비섹션 | AO47: kmlee0907@posco.co.kr | AP47: 2023-03-30 15:03:36 | AQ47: 2023 | AR47: 차후 재점검 | AS47: MRO e-Caltalog시스템 경유건으로 대체 Maker 미 발굴건,재질시험실 전기강판 펀치프레스 시편이송용 실린더의 핵심 부품으로 기 설치된 Pneumatic Cylinder의 호환성을 위해 특정 사양으로 등록건 확인 후 승인,(특정 사양품감축 관련) 차후 입고시 스케치, 현물 확인을 통한 도면화,일반 사양화,복수화 전환 검토 요청 필히 부탁드립니다. (주)TPC메카트로닉스 기술영업팀 노민영책임(010-9323-4684)과 복수화 재 검토 요청 부탁드립니다.감사합니다._x000D_ | AT47: N
A48: Q4317761 | C48: 포스코 | D48: Pneumatic Cylinder | E48: Pneumatic Cylinder | F48: 전아람 | G48: 특정사양품(단수) | H48: ACTIVE | I48: L | J48: KRW | K48: TA,125Dx0Dx180ST,1.57kgf/cm2,[CDS2T125-180-Y7BWSDPC/SMC] | L48: EA | M48: STANDARD | N48: CDS2T125-180-Y7BWSDPC | O48: SMC | R48: NONE | AB48: page2_20160829133828974.bmp | AH48: th_20230613130256648.jpg | AJ48: Umesh Warekar | AK48: Mech. Maint. Team | AM48: Umesh Warekar | AN48: Mech. Maint. Team | AP48: 2023-06-26 16:06:24 | AQ48: 2023 | AT48: N
A49: Q4537900 | C49: 포스코 | D49: Pneumatic Cylinder | E49: Hydraulic & Pneumatics | F49: 전아람 | G49: 특정사양품(단수) | H49: ACTIVE | I49: L | J49: KRW | K49: CWC(DA),CB,125Dx36Dx100ST,10kgf/cm2,[ADQ2D125-100DCM-SCB2710/TPC]+WITH TY-12A KNUCKLE JOINT,1CC BILLET TCM CLAMPING | L49: SET | M49: STANDARD | N49: ADQ2D125-100DCM-SCB2710 | O49: TPC | P49: WITH TY-12A KNUCKLE JOINT | R49: NONE | W49: 1CC BILLET TCM CLAMPING | AB49: SCB2630 - 복사본_20211007093512136.pdf | AH49: 너클조인트-복사본_20210915165259406_20211116132317344.png | AJ49: 김재석 | AK49: (포항)제강설비부 연주정비섹션 | AM49: 김현우 | AN49: (포항)제강설비부 연주정비섹션 | AO49: bearer601n@posco.co.kr | AP49: 2021-11-22 13:11:27 | AQ49: 2021 | AR49: 차후 재점검 | AT49: N
A50: Q4695802 | C50: 포스코 | D50: Pneumatic Cylinder | E50: Pneumatic Cylinder | F50: 전아람 | G50: 특정사양품(단수) | H50: ACTIVE | I50: L | J50: KRW | K50: CWC(DA),TA,32Dx12Dx35ST,10kgf/cm2,[CM2U32-35/SMC],FOR K1ACL WELDER DRESSER PRESSING OPEN/CLOSE AIR CYLINDER,OR EQUIVALENT | L50: SET | M50: STANDARD | N50: CM2U32-35 | O50: SMC | Q50: UNKNOWN | R50: NONE | T50: UNKNOWN | U50: NONE | W50: FOR K1ACL WELDER DRESSER PRESSING OPEN/CLOSE AIR CYLINDER | AB50: SMC_CM2 시리즈_20251215112715432.pdf | AE50: https://www.smckorea.co.kr/ | AH50: Dresser pressing cylinder_20251215111118649.jpg | AJ50: 박형준 | AK50: (광양)압연설비2부 전기강판정비섹션 | AL50: phj4892@posco.co.kr | AM50: 홍성준 | AN50: (광양)압연설비2부 전기강판정비섹션 | AO50: ghdtjdwns181@posco.co.kr | AP50: 2025-12-16 17:12:41 | AQ50: 2025 | AR50: 차후 재점검 | AS50: 기 설치된 물품의 호환성을 위해 특정 사양으로 등록건 확인, 유사 item 검색하였으나, 유사/동일품 없음 확인후 승인합니다. (특정 사양품감축 관련) 차후 입고시 스케치, 현물 확인을 통한 도면화, 일반 사양화, 복수화 전환 검토 요청 부탁드립니다. 감사합니다. | AT50: N
A51: Q4691661 | C51: 포스코 | D51: Pneumatic Cylinder | E51: Pneumatic Cylinder | F51: 전아람 | G51: 특정사양품(단수) | H51: ACTIVE | I51: L | J51: KRW | K51: CWC(DA),CD,140Dx36Dx200ST,10kgf/cm2,[CDS1DN140-KRT04KO-200-M9NL/SMC],FOR CGL PREMELT POT INGOT FEEDER,OR EQUIVALENT | L51: SET | M51: STANDARD | N51: CDS1DN140-KRT04KO-200-M9NL | O51: SMC | R51: NONE | X51: FOR CGL PREMELT POT INGOT FEEDER | AB51: SMC_file_20251103093934935.pdf | AE51: https://www.smckorea.co.kr/ | AH51: CDS1DN_20251111073833443.png | AJ51: 박무균 | AK51: (포항)압연설비2부 냉연정비2섹션 | AL51: any0406@posco.co.kr | AM51: 김범준 | AN51: (포항)압연설비2부 냉연정비2섹션 | AO51: kimbjj@posco.co.kr | AP51: 2025-11-11 17:11:54 | AQ51: 2025 | AR51: 차후 재점검 | AS51: 기 설치된 물품의 호환성을 위해 특정 사양으로 등록건 확인,_x000D_ 유사 item 검색하였으나, 유사/동일품 없음 확인후 승인합니다._x000D_ (특정 사양품감축 관련) 차후 입고시 스케치, 현물 확인을 통한 도면화, 일반 사양화, 복수화 전환 검토 요청 부탁드립니다. 감사합니다._x000D_ | AT51: N
A52: Q4672372 | C52: POSCO MOBILITY | D52: Pneumatic Cylinder | E52: Pneumatic Cylinder | F52: 전아람 | G52: 특정사양품(단수) | H52: ACTIVE | I52: L | J52: KRW | K52: CWC(DA),FB,160Dx40Dx50ST,10kgf/cm2,[TCS1GN160-50J/TPC] | L52: EA | M52: STANDARD | N52: TCS1GN160-50J | O52: TPC | R52: NONE | AB52: TCS1_20250424094050986.jpg | AE52: https://tpcpage.co.kr/goods/detail.asp?gno=1538&cate=714 | AH52: TCS_20250424094214231.jpg | AJ52: 전주문 | AK52: 설비기술섹션 | AL52: arbr5@poscomobility.com | AM52: 배문식 | AN52: 설비기술섹션 | AO52: bmsik@poscomobility.com | AP52: 2025-04-29 15:04:47 | AQ52: 2025 | AR52: 차후 재점검 | AS52: 기 설치된 물품의 호환성을 위해 특정 사양으로 등록건 확인,_x000D_ Q4591763등 유사item 검색하였으나, 유사/동일품 없음 확인후 승인합니다._x000D_ (특정 사양품감축 관련) 차후 입고시 스케치, 현물 확인을 통한 도면화, 일반 사양화, 복수화 전환 검토 요청 필히 부탁드립니다. 감사합니다._x000D_ | AT52: N
A53: Q4357705 | C53: 포스코 | D53: Pneumatic Cylinder | E53: Pneumatic Cylinder | F53: 전아람 | G53: 특정사양품(단수) | H53: ACTIVE | I53: L | J53: KRW | K53: CWC(DA),FG,125Dx20ST,10kgf/cm2,[CDQ2B125-20DCZ-M9BALS/SMC],FOR 2PL PICO3 QUICK MASK AIR CYLIDER | L53: EA | M53: STANDARD | N53: CDQ2B125-20DCZ-M9BALS | O53: SMC | R53: NONE | X53: For 2PL PICO3 Quick Mask Air Cylider | AB53: 물품등록의뢰서 - PICO3 Quick Mask Air Cylider_20170504114136357.xlsx | AH53: 캡처PN111121_20210721154347942.jpg | AJ53: 김형진 | AK53: (포항)후판부 후판정비섹션 | AM53: 신용규 | AN53: (포항)후판부 후판정비섹션 | AO53: linkman7@posco.co.kr | AP53: 2021-07-22 14:07:16 | AQ53: 2021 | AS53: 향후 신청 시에는 특정 사 URL를 연결하시길 바랍니다. 감사합니다.(2017.5.12) | AT53: N
A54: Q4657313 | C54: 포스코 | D54: Pneumatic Cylinder | E54: Pneumatic Cylinder | F54: 전아람 | G54: 특정사양품(단수) | H54: ACTIVE | I54: L | J54: KRW | K54: CWC(DA),CB,80Dx25Dx200ST,10kgf/cm2,[CDA2D80-KRT09KO-200Z-W-A54Z/SMC],FOR K2SMP BUBBLING SAMPLING LANCE,OR EQUIVALENT | L54: EA | M54: STANDARD | N54: CDA2D80-KRT09KO-200Z-W-A54Z | O54: SMC | R54: NONE | X54: FOR K2SMP BUBBLING SAMPLING LANCE | AB54: 벨로우즈 표준화_20241127165904391.pdf | AE54: https://www.smckorea.co.kr/ppis/data/catalog/CA2-Z.pdf | AH54: CA2 취부옵션_20241127165605635.jpg | AJ54: 남태현 | AK54: (광양)제강설비부 제강정비섹션 | AM54: 김규태 | AN54: (광양)제강설비부 제강정비섹션 | AO54: kjh3643@posco.co.kr | AP54: 2024-11-29 07:11:40 | AQ54: 2024 | AR54: 차후 재점검 | AS54: Q4591758등 유사item 검색하였으나, 동일 maker의 다른 형범임 확인하고 승인합니다. | AT54: N
A55: Q4625604 | C55: 포스코 | D55: Pneumatic Cylinder | E55: Pneumatic Cylinder | F55: 전아람 | G55: 특정사양품(단수) | H55: ACTIVE | I55: L | J55: KRW | K55: CWC(DA),FC,63Dx20Dx400ST,1.0kgf/cm2,[CDNA2F63-KRT22KO-400-D-A93/SMC],OR EQUIVALENT | L55: SET | M55: STANDARD | N55: CDNA2F63-KRT22KO-400-D-A93 | O55: SMC | R55: NONE | AB55: 상면타각기 Pneumatic Cylinder 카탈로그_0900bf4ba4e0498b_613771_20240110080020121.pdf | AE55: https://www.smckorea.co.kr/ | AH55: 타각기 CYLINDER_20240219094415448.jpg | AJ55: 황해 | AK55: (광양)압연설비1부 후판정비섹션 | AL55: yellowsea@posco.co.kr | AM55: 정재승 | AN55: (광양)압연설비1부 후판정비섹션 | AO55: shk5912@posco.co.kr | AP55: 2024-02-21 09:02:52 | AQ55: 2024 | AR55: 차후 재점검 | AS55: MRO e-Caltalog시스템 경유건으로 대체 Maker 미 발굴건, 기 설치된 cylinder의 호환성을 위해 특정 사양으로 등록건 확인 후 승인, _x000D_ | AT55: N
A56: Q4694472 | C56: 포스코 | D56: Pneumatic Cylinder | E56: Pneumatic Cylinder | F56: 전아람 | G56: 특정사양품(단수) | H56: ACTIVE | I56: L | J56: KRW | K56: CWC(DA),TC,140Dx36Dx150ST,10kgf/cm2,[CDS1TN140-KRT04KO-150/SMC],FOR CGL PREMELT LAUNDER COVER,OR EQUIVALENT | L56: EA | M56: STANDARD | N56: CDS1TN140-KRT04KO-150 | O56: SMC | Q56: UNKNOWN | R56: NONE | T56: UNKNOWN | U56: NONE | X56: FOR CGL PREMELT LAUNDER COVER | AB56: 상품정보_CS1 벨로우즈 부착 실린더_20251202145700110.pdf | AE56: https://www.smckorea.co.kr/ | AH56: CDS1TN140-KRT04KO-150_20251201134541695.png | AJ56: 박무균 | AK56: (포항)압연설비2부 냉연정비2섹션 | AL56: any0406@posco.co.kr | AM56: 김범준 | AN56: (포항)압연설비2부 냉연정비2섹션 | AO56: kimbjj@posco.co.kr | AP56: 2025-12-02 15:12:56 | AQ56: 2025 | AR56: 차후 재점검 | AS56: 기 설치된 물품의 호환성을 위해 특정 사양으로 등록건 확인, 유사 item 검색하였으나, 유사/동일품 없음 확인후 승인합니다. (특정 사양품감축 관련) 차후 입고시 스케치, 현물 확인을 통한 도면화, 일반 사양화, 복수화 전환 검토 요청 부탁드립니다. 감사합니다 | AT56: N
A57: Q4626076 | C57: 포스코 | D57: Pneumatic Cylinder | E57: Pneumatic Cylinder | F57: 전아람 | G57: 특정사양품(단수) | H57: ACTIVE | I57: L | J57: KRW | K57: CWD,LAx20Dx250ST,9.6kgf/cm2,[CY1S20-250BZ-A93L/SMC],FOR 2WRM LAZER MARKING M/C POSITION CYLINDER,OR EQUIVALENT | L57: EA | M57: STANDARD | N57: CY1S20-250BZ-A93L | O57: SMC | R57: NONE | X57: FOR 2WRM LAZER MARKING M/C POSITION CYLINDER | AB57: 실린더 1_20240116080358551.jpg | AE57: https://kr.misumi-ec.com/vona2/detail/221006480227/?HissuCode=CY1SG20-250BZ-A93L | AH57: 실린더12_20240116101018874.jpg | AJ57: 김영민 | AK57: (포항)압연설비1부 선재정비섹션 | AL57: dudals9563@posco.co.kr | AM57: 주성룡 | AN57: (포항)압연설비1부 선재정비섹션 | AO57: jsb4562@posco.co.kr | AP57: 2024-01-16 14:01:48 | AQ57: 2024 | AR57: 차후 재점검 | AT57: N
A58: Q4607653 | C58: 포스코 | D58: Pneumatic Cylinder | E58: Pneumatic Cylinder | F58: 전아람 | G58: 특정사양품(단수) | H58: ACTIVE | I58: L | J58: KRW | K58: CWC(DA),FA,200Dx50Dx2300ST,10kgf/cm2,[CDS1FN200-2300-A93L/SMC],FOR 3-2RCL BANDING MACHINE LIFTER,OR EQUIVALENT | L58: SET | M58: STANDARD | N58: CDS1FN200-2300-A93L | O58: SMC | R58: NONE | X58: FOR 3-2RCL BANDING MACHINE LIFTER | AB58: 실린더 물품등록_20230729091830920.png | AE58: https://www.smckorea.co.kr/ppis/data/catalog/CS1.pdf?ver=7825.631353098796 | AH58: 실린더 사진_20230729092009962.png | AJ58: 곽진섭 | AK58: (광양)EIC기술부 자동화설비정비섹션 | AL58: ggwakjs@posco.co.kr | AM58: 곽진섭 | AN58: (광양)EIC기술부 자동화설비정비섹션 | AO58: ggwakjs@posco.co.kr | AP58: 2023-07-31 09:07:41 | AQ58: 2023 | AR58: 차후 재점검 | AS58: MRO e-Caltalog시스템 경유건으로 대체 Maker 미 발굴건,Banding Machine Header Lift의 핵심 부품으로 기 설치된 Pneumatic Cylinder의 호환성을 위해 특정 사양으로 등록건 확인 후 승인,(특정 사양품감축 관련) 차후 입고시 스케치, 현물 확인을 통한 도면화,일반 사양화,복수화 전환 검토 요청 필히 부탁드립니다. (11) 특허등록 번호 (특허품이 아닌 경우 해당없음으로 기입)부탁드립니다. 향후 미 기입시 Rework처리 될수 있습니다. Q4423335,Q4520848와 유사건으로 Stroke 및 센서 Type이 다름 확인건, 감사합니다. | AT58: N
A59: Q4545469 | C59: 포스코 | D59: Pneumatic Cylinder | E59: Hydraulic & Pneumatics | F59: 전아람 | G59: 특정사양품(단수) | H59: ACTIVE | I59: L | J59: KRW | K59: CWC(DA),FB,32Dx12Dx700ST,[RHCL32-700/SMC],OR EQUIVALENT | L59: EA | M59: STANDARD | N59: RHCL32-700 | O59: SMC | R59: NONE | AB59: 에어실린더RHC카다로그_20211209112529053_20211214152000304.pdf | AE59: https://www.smckorea.co.kr/homepage/ver3.5/srch/search.asp | AH59: 두산선반에어실린더_20211209112236126_20211214152000276.jpg | AJ59: 박만주 | AK59: (포항)품질기술부 재질시험섹션 | AL59: delimj@posco.co.kr | AM59: 임정우 | AN59: (포항)품질기술부 재질시험섹션 | AO59: limjeongwoo@posco.co.kr | AP59: 2021-12-17 13:12:34 | AQ59: 2021 | AR59: 차후 재점검 | AT59: N
A60: Q4636671 | C60: 포스코 | D60: Pneumatic Cylinder | E60: Pneumatic Cylinder | F60: 전아람 | G60: 특정사양품(단수) | H60: ACTIVE | I60: L | J60: KRW | K60: CWC(DA),CA,250Dx250Dx250ST,[CDS2T250-250-CJCD0238/SMC],MAKER DWG NO:CDS2T250-250-CJCD0238,OR EQUIVALENT | L60: EA | M60: STANDARD | N60: CDS2T250-250-CJCD0238 | O60: SMC | R60: NONE | W60: MAKER DWG NO:CDS2T250-250-CJCD0238 | AB60: 자재_물품등록_특정사양품 검토의뢰서_15,16가이드밴 실린더_이현우_20240424_20240424160857118.pptx | AH60: cs2 실린더_20240424160857281.PNG | AJ60: 홍성현 | AK60: 광양생산부 정비섹션 | AM60: 이현우 | AN60: 광양생산부 정비섹션 | AO60: 2hyunwoo@posco.co.kr | AP60: 2024-04-25 08:04:23 | AQ60: 2024 | AR60: 차후 재점검 | AS60: Q4304959등 유사item 검색하였으나 Boa Size 등이 상이함 확인후 승인합니다. | AT60: N
A61: Q2213642 | C61: 포스코 | D61: Pneumatic Cylinder | E61: Pneumatic Cylinder | F61: 전아람 | G61: 특정사양품(단수) | H61: ACTIVE | I61: L | J61: KRW | K61: CWC(DA),40Dx16Dx200ST,10kgf/cm2,[CDA2T40-200-Y59BL/SMC],FOR 3CAL BAND CUTTER WINDER | L61: SET | M61: STANDARD | N61: CDA2T40-200-Y59BL | O61: SMC | R61: NONE | X61: FOR 3CAL BAND CUTTER WINDER | AB61: 포)압정 2냉연 3CAL기계 CDA2T40-200-Y59BL(1)_1239869833189.jpg | AH61: 20220419080745739.jpg | AJ61: 이갑출 | AK61: (포항)압연정비부 냉연정비2과 | AM61: 강신호 | AN61: (포항)압연정비부 냉연정비2과 | AP61: 2022-04-20 09:04:48 | AQ61: 2022 | AT61: N
A62: Q4524100 | B62: 0 | C62: 포스코 | D62: Pneumatic Cylinder | E62: Hydraulic & Pneumatics | F62: 전아람 | G62: 특정사양품(단수) | H62: ACTIVE | I62: L | J62: KRW | K62: 20Dx50ST,[JCMMZ20TR-50/SMC],FOR 1WRM BTJ A-LINE G/M #1,2,3 WHEEL MEASURING CYL',OR EQUIVALENT | L62: EA | M62: STANDARD | N62: JCMMZ20TR-50 | O62: SMC | R62: NONE | X62: FOR 1WRM BTJ A-LINE G/M #1,2,3 WHEEL MEASURING CYL' | AE62: http://ca01.smcworld.com/catalog/New-products/mpv/s20-237-jcm/index.html#target/page_no=4 | AH62: A동 AIR CYL_20210520075433292.jpg | AJ62: 김성엽 | AK62: (포항)압연설비부 선재정비섹션 | AM62: 신동환 | AN62: (포항)압연설비부 선재정비섹션 | AO62: mils0818@posco.co.kr | AP62: 2021-05-31 10:05:01 | AQ62: 2021 | AR62: 차후 재점검 | AT62: N
A63: Q4371330 | B63: 0 | C63: 포스코 | D63: Pneumatic Cylinder | E63: Pneumatic Cylinder | F63: 전아람 | G63: 특정사양품(단수) | H63: ACTIVE | I63: L | J63: KRW | K63: 50D,10kgf/cm2,[CDQ2B50-55Z-DCN446GN/SMC],AIR CYLINDER FOR BANDING MACHINE | L63: SET | M63: STANDARD | N63: CDQ2B50-55Z-DCN446GN | O63: SMC | R63: NONE | X63: AIR CYLINDER FOR BANDING MACHINE | AB63: Q4371330_CQ2-Z.pdf | AE63: http://www.smckorea.co.kr/esales/data/sangpum/catalog/CQ2-Z.pdf | AH63: 삼정페이스게이트 실린더_20231213114156010.png | AJ63: Shivraj Pandram | AK63: CGL Mech. Maint. | AL63: shivraj@posco.net | AM63: Shivraj Pandram | AN63: CGL Mech. Maint. | AO63: shivraj@posco.net | AP63: 2023-12-18 15:12:56 | AQ63: 2023 | AS63: When you apply for the future, please save the catalog (mark the corresponding specification) and connect to 'Model-1 Attachment'. Thank you._x000D_ 향후 신청 시에는 해당 카다로그를 저장(해당사양 마킹)하여 'Model-1 첨부파일 '에 연결하시길 바랍니다. 감사합니다.(2017.8.4)_x000D_ _x000D_ | AT63: N
A64: Q4037566 | B64: 0 | C64: 포스코 | D64: Pneumatic Cylinder | E64: Pneumatic Cylinder | F64: 전아람 | G64: 특정사양품(단수) | H64: ACTIVE | I64: L | J64: KRW | K64: CWC(DA),TD,140Dx35Dx710ST,10kgf/cm2,[CDS1TN140-KRT04KO-710-XC14 +D-A54Z(2EA)+BT-12(2EA)/SMC],FOR 3CC SAMPLING DEVICE TILTING AIR CYLINDER,OR EQUIVALENT | L64: SET | M64: STANDARD | N64: CDS1TN140-KRT04KO-710-XC14 +D-A54Z(2EA)+BT-12(2EA) | O64: SMC | R64: NONE | X64: FOR 3CC SAMPLING DEVICE TILTING AIR CYLINDER | AB64: Q4037566_CS1.pdf | AE64: http://www.smckorea.co.kr/homepage/ver3.5/product/catalogue_sub_detail.asp?no=914# | AH64: 20250413093657448.jpg | AJ64: 김성표 | AK64: (포항)제강부 연주정비과 | AM64: 안희동 | AN64: (포항)제강부 연주정비과 | AP64: 2025-04-17 08:04:00 | AQ64: 2025 | AT64: Y
A65: Q4521203 | B65: 0 | C65: 포스코 | D65: Pneumatic Cylinder | E65: Hydraulic & Pneumatics | F65: 전아람 | G65: 특정사양품(단수) | H65: ACTIVE | I65: L | J65: KRW | K65: CWC(DA),CB,100Dx25Dx320ST,10kgf/cm2,[C96SD100-320C/SMC],OR EQUIVALENT | L65: SET | M65: STANDARD | N65: C96SD100-320C | O65: SMC | R65: NONE | AB65: Q4280848_C95_large.pdf | AE65: http://www.smckorea.co.kr/ppis/data/catalog/C96.pdf | AH65: C96_20210413095450859.png | AJ65: 최춘식 | AK65: (포항)압연설비부 STS압연정비섹션 | AM65: 김경오 | AN65: (포항)압연설비부 STS압연정비섹션 | AO65: kko1990@posco.co.kr | AP65: 2021-04-30 08:04:16 | AQ65: 2021 | AR65: 차후 재점검 | AT65: N
A66: Q4511190 | B66: 0 | C66: 포스코 | D66: Pneumatic Cylinder | E66: Hydraulic & Pneumatics | F66: 전아람 | G66: 특정사양품(단수) | H66: ACTIVE | I66: L | J66: KRW | K66: CWC(DA),TC,100Dx30Dx125ST,[CDA2T100-KRT09KO-125Z-W-A96L/SMC],FOR 2PL MAIN MARKING LINK CYLINDER,OR EQUIVALENT | L66: EA | M66: STANDARD | N66: CDA2T100-KRT09KO-125Z-W-A96L | O66: SMC | R66: NONE | X66: FOR 2PL MAIN MARKING LINK CYLINDER | AB66: Q4511190_CA2-Z.pdf | AE66: http://www.smckorea.co.kr/ppis/data/catalog/CA2-Z.pdf | AH66: CDA2T100-125KZ-W-A96L_20210115124829439.png | AJ66: 김형진 | AK66: (포항)압연설비부 후판정비섹션 | AM66: 김현승 | AN66: (포항)압연설비부 후판정비섹션 | AO66: geegee2310@posco.co.kr | AP66: 2021-02-02 09:02:56 | AQ66: 2021 | AR66: 차후 재점검 | AT66: N
A67: Q4520279 | B67: 0 | C67: 포스코 | D67: Pneumatic Cylinder | E67: Hydraulic & Pneumatics | F67: 전아람 | G67: 특정사양품(단수) | H67: ACTIVE | I67: L | J67: KRW | K67: CWC(DA),TA,50Dx20Dx170ST,10kgf/cm2,[CDG1UN50TF-170-CJZH0846/SMC],FOR 2PL UST PROBE HEADER CYLINDER,OR EQUIVALENT | L67: EA | M67: STANDARD | N67: CDG1UN50TF-170-CJZH0846 | O67: SMC | R67: NONE | X67: FOR 2PL UST PROBE HEADER CYLINDER | AB67: Q4520279_CG1-Z.pdf | AE67: http://www.smckorea.co.kr/ppis/data/catalog/CG1-Z.pdf | AH67: CDG1UN50TF-170Z-XA18C6_20240201111653820.jpg | AJ67: 김형진 | AK67: (포항)압연설비부 후판정비섹션 | AM67: 정민성 | AN67: (포항)압연설비부 후판정비섹션 | AO67: vevess1023@posco.co.kr | AP67: 2024-02-23 10:02:24 | AQ67: 2024 | AR67: 차후 재점검 | AT67: N
A68: Q4508586 | B68: 0 | C68: 포스코 | D68: Pneumatic Cylinder | E68: Hydraulic & Pneumatics | F68: 전아람 | G68: 특정사양품(단수) | H68: ACTIVE | I68: L | J68: KRW | K68: CWC(DA),[CDM2E32-200Z-NW-A93L/SMC],4CC MARKING | L68: SET | M68: STANDARD | N68: CDM2E32-200Z-NW-A93L | O68: SMC | R68: NONE | X68: 4CC MARKING | AB68: Q4508586_CM2-Z.pdf | AE68: http://www.smckorea.co.kr/ppis/data/catalog/CM2-Z.pdf | AH68: Detector Cylinder_20210112131056311.jpg | AJ68: 김재석 | AK68: (포항)제강설비부 연주정비섹션 | AM68: 홍경진 | AN68: (포항)제강설비부 연주정비섹션 | AO68: iklim00@posco.co.kr | AP68: 2021-01-14 14:01:51 | AQ68: 2021 | AR68: 차후 재점검 | AT68: N
A69: Q4520278 | B69: 0 | C69: 포스코 | D69: Pneumatic Cylinder | E69: Hydraulic & Pneumatics | F69: 전아람 | G69: 특정사양품(단수) | H69: ACTIVE | I69: L | J69: KRW | K69: CWC(DA),CA,40Dx14Dx160ST,10kgf/cm2,[CDM2E40TF-160Z-XC6/SMC],FOR 2PL UST MEASURING WHEEL CYLINDER,OR EQUIVALENT | L69: EA | M69: STANDARD | N69: CDM2E40TF-160Z-XC6 | O69: SMC | R69: NONE | X69: FOR 2PL UST MEASURING WHEEL CYLINDER | AB69: Q4520278_CM2-Z.pdf | AE69: http://www.smckorea.co.kr/ppis/data/catalog/CM2-Z.pdf | AH69: CDM2E40TF-160Z-XC6-2_20210420111902351.png | AJ69: 김형진 | AK69: (포항)압연설비부 후판정비섹션 | AM69: 정민성 | AN69: (포항)압연설비부 후판정비섹션 | AO69: vevess1023@posco.co.kr | AP69: 2021-04-22 09:04:14 | AQ69: 2021 | AR69: 차후 재점검 | AT69: N
A70: Q4507377 | B70: 0 | C70: 포스코 | D70: Pneumatic Cylinder | E70: Hydraulic & Pneumatics | F70: 전아람 | G70: 특정사양품(단수) | H70: ACTIVE | I70: L | J70: KRW | K70: CWC(DA),FA,50Dx20Dx10ST,10kgf/cm2,[CDQMB50-10-A72/SMC],FOR 2ZRM ROLL CHANGE CAR LIFTER ROLL SHIFT CYLINDER,OR EQUIVALENT | L70: EA | M70: STANDARD | N70: CDQMB50-10-A72 | O70: SMC | R70: NONE | X70: FOR 2ZRM ROLL CHANGE CAR LIFTER ROLL SHIFT CYLINDER | AB70: Q4507377_CQM.pdf | AE70: http://www.smckorea.co.kr/ppis/data/catalog/CQM.pdf | AH70: CDQMB50-10-A72-1_20210104071834268.png | AJ70: 박용봉 | AK70: (포항)압연설비부 전기강판정비섹션 | AM70: 최육기 | AN70: (포항)압연설비부 전기강판정비섹션 | AO70: ykchoi@posco.co.kr | AP70: 2021-01-04 09:01:07 | AQ70: 2021 | AR70: 차후 재점검 | AT70: N
A71: Q4510521 | B71: 0 | C71: 포스코퓨처엠 | D71: Pneumatic Cylinder | E71: Pneumatic Cylinder | F71: 전아람 | G71: 특정사양품(단수) | H71: ACTIVE | I71: L | J71: KRW | K71: CWC(DA),CA,80Dx25Dx100ST,10kgf/cm2,[CDQ2B80-100DMZ-XA18/SMC] | L71: SET | M71: STANDARD | N71: CDQ2B80-100DMZ-XA18 | O71: SMC | R71: NONE | AE71: http://www.smckorea.co.kr/ppis/data/catalog/CQ-Z.pdf | AH71: CDQ2B63-100DMZ-XA18_20210125120819059.png | AJ71: 김 지환 | AK71: 내화물정비섹션 | AL71: mm13551@poscofuturem.com | AM71: 김지환 | AN71: 내화물정비섹션 | AO71: mm13551@poscofuturem.com | AP71: 2021-01-27 14:01:45 | AQ71: 2021 | AR71: 차후 재점검 | AT71: N
A72: Q4361361 | B72: 0 | C72: 포스코 | D72: Pneumatic Cylinder | E72: Hydraulic & Pneumatics | F72: 전아람 | G72: 특정사양품(단수) | H72: ACTIVE | I72: L | J72: KRW | K72: CWC(DA),TC,180Dx45Dx800ST,10kgf/cm2,[CS1T180-800-XC86B/SMC],FOR SOFT COKE HOPPER GATE CYLINDER,OR EQUIVALENT | L72: EA | M72: STANDARD | N72: CS1T180-800-XC86B | O72: SMC | R72: NONE | X72: FOR SOFT COKE HOPPER GATE CYLINDER | AE72: http://www.smckorea.co.kr/ppis/data/catalog/CS1.pdf | AH72: CS1 Series_20210126140007236.jpg | AJ72: 최창규 | AK72: (포항)화성부 화성정비섹션 | AM72: 신종인 | AN72: (포항)화성부 화성정비섹션 | AP72: 2021-02-03 13:02:56 | AQ72: 2021 | AS72: 향후 신청 시에는 해당 카다로그를 저장(해당사양 마킹)하여 'Model-1 첨부파일 '에 연결하시길 바랍니다. 감사합니다.(2017.6.1) | AT72: N
A73: Q4459460 | B73: 0 | C73: 포스코 | D73: Pneumatic Cylinder | E73: Pneumatic Cylinder | F73: 전아람 | G73: 특정사양품(단수) | H73: ACTIVE | I73: L | J73: KRW | K73: CWC(DA),FA,200Dx50Dx125ST,[CS1FN200-KRT04JO-125-XC6/SMC],FOR K1CGL WATER QUENCH,OR EQUIVALENT | L73: EA | M73: STANDARD | N73: CS1FN200-KRT04JO-125-XC6 | O73: SMC | R73: NONE | X73: FOR K1CGL WATER QUENCH | AE73: http://www.smckorea.co.kr/ppis/data/catalog/CS1.pdf | AH73: 1CGL WATER 퀜치 에어실린더 사진_20220107145920443.png | AI73: CS1-1_20220107145920457.jpg | AJ73: 박원준 | AK73: (광양)압연설비부 도금정비1섹션 | AL73: wjpark@posco.co.kr | AM73: 노석길 | AN73: (광양)압연설비부 도금정비1섹션 | AO73: sk2580@posco.co.kr | AP73: 2022-01-17 08:01:55 | AQ73: 2022 | AT73: N
A74: Q4532777 | B74: 0 | C74: 포스코 | D74: Pneumatic Cylinder | E74: Hydraulic & Pneumatics | F74: 전아람 | G74: 특정사양품(단수) | H74: ACTIVE | I74: L | J74: KRW | K74: CWC(DA),40Dx350ST,[CDA2G40-350Z-W-A93L/SMC],1CC BILLET MARKING MACHINE,OR EQUIVALENT | L74: SET | M74: STANDARD | N74: CDA2G40-350Z-W-A93L | O74: SMC | R74: NONE | X74: 1CC BILLET MARKING MACHINE | AE74: https://kr.c.misumi-ec.com/book/SMC1_37/digitalcatalog.html?page_num=A-470 | AH74: 제목 없음_20210812073033987.jpg | AJ74: 김재석 | AK74: (포항)제강설비부 연주정비섹션 | AM74: 김민태 | AN74: (포항)제강설비부 연주정비섹션 | AP74: 2021-08-19 08:08:17 | AQ74: 2021 | AR74: 차후 재점검 | AT74: N
A75: Q4683941 | B75: 0 | C75: 포스코 | D75: Pneumatic Cylinder | E75: Pneumatic Cylinder | F75: 전아람 | G75: 특정사양품(단수) | H75: ACTIVE | I75: L | J75: KRW | K75: CWC(DA),FA,63Dx20Dx600ST,10kgf/cm2,[MDBF63-600Z-W-M9BW/SMC],OR EQUIVALENT | L75: EA | M75: STANDARD | N75: MDBF63-600Z-W-M9BW | O75: SMC | R75: NONE | AE75: https://www.smckorea.co.kr/ > 제품 검색 > MDBF63-600Z-W-M9BW | AH75: MDBF63-600Z-W-M9BW_20250818083414243.jpg | AJ75: 김대환 | AK75: (포항)제강설비부 제강정비섹션 | AL75: police907@posco.co.kr | AM75: 김대철 | AN75: (포항)제강설비부 제강정비섹션 | AO75: kim.7@posco.co.kr | AP75: 2025-08-19 13:08:47 | AQ75: 2025 | AR75: 차후 재점검 | AT75: N
A76: Q4550788 | B76: 0 | C76: 포스코 | D76: Pneumatic Cylinder | E76: Pneumatic Cylinder | F76: 전아람 | G76: 특정사양품(단수) | H76: ACTIVE | I76: L | J76: KRW | K76: CWC(DA),TC,40Dx16Dx575ST,[CDA2T40-575Z/SMC],OR EQUIVALENT | L76: SET | M76: STANDARD | N76: CDA2T40-575Z | O76: SMC | R76: NONE | AE76: https://www.smckorea.co.kr/esales/data/sangpum/catalog/CA2.pdf | AH76: CDA2T40_20220110085838252.jpg | AJ76: 이규연 | AK76: (포항)압연설비부 전기강판정비섹션 | AL76: lkydh@posco.co.kr | AM76: 김태원 | AN76: (포항)압연설비부 전기강판정비섹션 | AP76: 2022-02-09 08:02:05 | AQ76: 2022 | AR76: 불가피 품목 | AT76: N
A77: Q4627795 | B77: 0 | C77: 포스코 | D77: Pneumatic Cylinder | E77: Pneumatic Cylinder | F77: 전아람 | G77: 특정사양품(단수) | H77: ACTIVE | I77: L | J77: KRW | K77: CSA,LB,40Dx16Dx750ST,10.1kgf/cm2,[MDBB40-750Z-M9N/SMC],WITH SENSOR,MATERIAL TEST SHOP DTTM,OR EQUIVALENT | L77: SET | M77: STANDARD | N77: MDBB40-750Z-M9N | O77: SMC | R77: NONE | W77: WITH SENSOR | X77: MATERIAL TEST SHOP DTTM | AE77: https://www.smckorea.co.kr/homepage/ver3.5/product/catalogue_sub_detail.asp?cata_no=911# | AH77: [이미지] MDBL(MDBB)_SMC_20240130074029706.jpg | AJ77: 장요한 | AK77: (포항)EIC기술부 자동화설비정비섹션 | AL77: dreamjyh1@posco.co.kr | AM77: 이규문 | AN77: (포항)EIC기술부 자동화설비정비섹션 | AO77: kmlee0907@posco.co.kr | AP77: 2024-01-31 08:01:50 | AQ77: 2024 | AR77: 차후 재점검 | AS77: MRO e-Caltalog시스템 경유건으로 대체 Maker 미 발굴건, 기 설치된 Cylinder의 호환성을 위해 특정 사양으로 등록건 확인, _x000D_ Q2211852 등 유사사양 확인 후 mounting type, stroke 상이로 승인_x000D_ | AT77: N
A78: Q4627796 | B78: 0 | C78: 포스코 | D78: Pneumatic Cylinder | E78: Pneumatic Cylinder | F78: 전아람 | G78: 특정사양품(단수) | H78: ACTIVE | I78: L | J78: KRW | K78: CSA,LB,40Dx16Dx690ST,10kgf/cm2,[MDBL40-690Z-W-M9N/SMC],WITH SENSOR,MATERIAL TEST SHOP DTTM,OR EQUIVALENT | L78: SET | M78: STANDARD | N78: MDBL40-690Z-W-M9N | O78: SMC | R78: NONE | W78: WITH SENSOR | X78: MATERIAL TEST SHOP DTTM | AE78: https://www.smckorea.co.kr/homepage/ver3.5/product/catalogue_sub_detail.asp?cata_no=911# | AH78: [이미지] MDBL(MDBB)_SMC_20240130080046150.jpg | AJ78: 장요한 | AK78: (포항)EIC기술부 자동화설비정비섹션 | AL78: dreamjyh1@posco.co.kr | AM78: 이규문 | AN78: (포항)EIC기술부 자동화설비정비섹션 | AO78: kmlee0907@posco.co.kr | AP78: 2024-01-31 08:01:14 | AQ78: 2024 | AR78: 차후 재점검 | AS78: MRO e-Caltalog시스템 경유건으로 대체 Maker 미 발굴건, 기 설치된 Cylinder의 호환성을 위해 특정 사양으로 등록건 확인, _x000D_ 유사사양 확인 후 승인_x000D_ | AT78: N
A79: Q4648582 | B79: 0 | C79: 포스코 | D79: Pneumatic Cylinder | E79: Pneumatic Cylinder | F79: 전아람 | G79: 특정사양품(단수) | H79: ACTIVE | I79: L | J79: KRW | K79: CWC(DA),TC,80Dx25Dx800ST,10kgf/cm2,[CA2T80-800KZ-NW-XB6/SMC],FOR 2SMP DE-P SUB LANCE SLIDE GATE,OR EQUIVALENT | L79: SET | M79: STANDARD | N79: CA2T80-800KZ-NW-XB6 | O79: SMC | R79: NONE | X79: FOR 2SMP DE-P SUB LANCE SLIDE GATE | AE79: https://www.smckorea.co.kr/homepage/ver3.5/product/catalogue_sub_detail.asp?cata_no=913 | AH79: 실린더_20130409102657047_20240826073238606.jpg | AJ79: 하성원 | AK79: (포항)제강설비부 제강정비섹션 | AL79: hagry2@posco.co.kr | AM79: 하성원 | AN79: (포항)제강설비부 제강정비섹션 | AO79: hagry2@posco.co.kr | AP79: 2024-08-27 08:08:20 | AQ79: 2024 | AR79: 차후 재점검 | AS79: ** 추후 결재문서 단수+특정사양으로 등록하는 사유를 좀 더 보완하여 작성 부탁드립니다. _x000D_ Q4037562등 유사item 검색하였으나, 회전 수 등 상이하여 확인후 승인합니다. | AT79: N
A80: Q2095909 | B80: 0 | C80: 포스코 | D80: Pneumatic Cylinder | E80: Hydraulic & Pneumatics | F80: 전아람 | G80: 특정사양품(단수) | H80: ACTIVE | I80: L | J80: KRW | K80: CTC,SD,32Dx16Dx70ST,7kgf/cm2,[MHL2-32D/SMC],DOUBLE PISTON(14,16),FOR 4RH SAMPLING DEVICE | L80: SET | M80: STANDARD | N80: MHL2-32D | O80: SMC | R80: NONE | W80: DOUBLE PISTON(14,16) | X80: FOR 4RH SAMPLING DEVICE | AE80: https://www.smckorea.co.kr/homepage/ver3.5/product/catalogue_sub_detail.asp?no=1051# | AH80: MHL2_20230712103351059.jpg | AJ80: 김제일 | AK80: (광양)기계설비부 제강기계정비과 | AL80: jeilgood@posco.co.kr | AP80: 2023-07-17 09:07:38 | AQ80: 2023 | AT80: N
A81: Q4668346 | B81: 0 | C81: 포스코 | D81: Pneumatic Cylinder | E81: Pneumatic Cylinder | F81: 전아람 | G81: 특정사양품(단수) | H81: ACTIVE | I81: L | J81: KRW | K81: 40Dx16Dx150ST,10.197162kgf/cm2,[MGPM40-150-HL-M9BZ/SMC],OR EQUIVALENT | L81: SET | M81: STANDARD | N81: MGPM40-150-HL-M9BZ | O81: SMC | R81: NONE | AE81: https://www.smckorea.co.kr/homepage/ver3.5/product/catalogue_sub_detail.asp?no=954 | AH81: 2RCL MGPM40-150-HL-M9BZ_20250321085338735.jpg | AJ81: 이규연 | AK81: (포항)압연설비2부 전기강판정비섹션 | AL81: lkydh@posco.co.kr | AM81: 이병훈 | AN81: (포항)압연설비2부 전기강판정비섹션 | AO81: bh712@posco.co.kr | AP81: 2025-03-21 11:03:39 | AQ81: 2025 | AR81: 차후 재점검 | AS81: MRO e-Caltalog시스템 경유건으로 대체 Maker 미 발굴건, 기 설치된 CYLINDER의 호환성을 위해 특정 사양으로 등록건 확인,_x000D_ 유사item 검색하였으나, 유사/동일품 없음 확인후 승인합니다._x000D_ (특정 사양품감축 관련) 차후 입고시 스케치, 현물 확인을 통한 도면화,일반 사양화, 복수화 전환 검토 요청 필히 부탁드립니다. 감사합니다._x000D_ | AT81: N
A82: Q4623087 | B82: 0 | C82: 포스코 | D82: Pneumatic Cylinder | E82: Hydraulic & Pneumatics | F82: 전아람 | G82: 특정사양품(단수) | H82: ACTIVE | I82: L | J82: KRW | K82: CWC(DA),FH,50Dx20Dx200ST,10.2kgf/cm2,[MLGPM50-200Z-F-A96L/SMC],OR EQUIVALENT | L82: SET | M82: STANDARD | N82: MLGPM50-200Z-F-A96L | O82: SMC | R82: NONE | AE82: https://www.smckorea.co.kr/homepage/ver3.5/srch/search.asp | AH82: MLGPM50_20231218093103754.jpg | AJ82: 황해 | AK82: (광양)압연설비1부 후판정비섹션 | AL82: yellowsea@posco.co.kr | AM82: 정재승 | AN82: (광양)압연설비1부 후판정비섹션 | AO82: shk5912@posco.co.kr | AP82: 2023-12-18 11:12:10 | AQ82: 2023 | AR82: 차후 재점검 | AT82: N
A83: Q4687826 | B83: 0 | C83: 포스코 | D83: Pneumatic Cylinder | E83: Pneumatic Cylinder | F83: 전아람 | G83: 특정사양품(단수) | H83: ACTIVE | I83: L | J83: KRW | K83: CSB,32Dx12Dx50ST,10kgf/cm2,[CDG1BA32-50Z1/SMC],OR EQUIVALENT | L83: EA | M83: STANDARD | N83: CDG1BA32-50Z1 | O83: SMC | Q83: UNKNOWN | R83: NONE | T83: UNKNOWN | U83: NONE | AE83: https://www.smckorea.co.kr/homepage/ver3.5/srch/search.asp | AH83: 재질시험실 100KJ DWTT 실린더 (스토퍼)_20251203155205532.png | AJ83: 장요한 | AK83: (포항)EIC기술부 자동화설비정비섹션 | AL83: dreamjyh1@posco.co.kr | AM83: 조경탁 | AN83: (포항)EIC기술부 자동화설비정비섹션 | AO83: kyoungtak01@posco.co.kr | AP83: 2025-12-04 13:12:06 | AQ83: 2025 | AR83: 차후 재점검 | AS83: 기 설치된 물품의 호환성을 위해 특정 사양으로 등록건 확인, _x000D_ 유사 item 검색하였으나, 유사/동일품 없음 확인후 승인합니다._x000D_ (특정 사양품감축 관련) 차후 입고시 스케치, 현물 확인을 통한 도면화, 일반 사양화, 복수화 전환 검토 요청 부탁드립니다. 감사합니다._x000D_ | AT83: N
A84: Q4570987 | B84: 0 | C84: 포스코 | D84: Pneumatic Cylinder | E84: Pneumatic Cylinder | F84: 전아람 | G84: 특정사양품(단수) | H84: ACTIVE | I84: L | J84: KRW | K84: CWC(DA),LB,50Dx30Dx165ST,3.0kgf/cm2,[CDA2T50-KRT09TO-165Z-A54Z/SMC],FOR 4M/C AIR CYLINDER,OR EQUIVALENT | L84: SET | M84: STANDARD | N84: CDA2T50-KRT09TO-165Z-A54Z | O84: SMC | R84: NONE | X84: FOR 4M/C AIR CYLINDER | AE84: https://www.smckorea.co.kr/ppis/data/catalog/CA2-Z.pdf | AH84: C(D)A2_Z_20220819134831908.jpg | AJ84: 김재석 | AK84: (포항)제강설비부 연주정비섹션 | AM84: 김창현 | AN84: (포항)제강설비부 연주정비섹션 | AO84: kch0306@posco.co.kr | AP84: 2022-08-25 08:08:19 | AQ84: 2022 | AR84: 불가피 품목 | AT84: N
A85: Q4664750 | B85: 0 | C85: 포스코 | D85: Pneumatic Cylinder | E85: Pneumatic Cylinder | F85: 전아람 | G85: 특정사양품(단수) | H85: ACTIVE | I85: L | J85: KRW | K85: CWC(DA),TC,80Dx25Dx150ST,10kgf/cm2,[CA2T80-KRT09KO-150Z-XC5/SMC],OR EQUIVALENT | L85: EA | M85: STANDARD | N85: CA2T80-KRT09KO-150Z-XC5 | O85: SMC | R85: NONE | AE85: https://www.smckorea.co.kr/ppis/data/catalog/CA2-Z.pdf | AH85: CA2_20250211141456015.jpg | AJ85: 이태호 | AK85: (포항)압연설비1부 선재정비섹션 | AL85: xogh2518@posco.co.kr | AM85: 김경형 | AN85: (포항)압연설비1부 선재정비섹션 | AO85: freezeblood@posco.co.kr | AP85: 2025-02-17 16:02:12 | AQ85: 2025 | AR85: 차후 재점검 | AS85: MRO e-Caltalog시스템 경유건으로 대체 Maker 미 발굴건, 기 설치된 Cylinder의 호환성을 위해 특정 사양으로 등록건 확인,_x000D_ Q4107450등 유사item 검색하였으나, 유사/동일품 없음 확인후 승인합니다._x000D_ (특정 사양품감축 관련) 차후 입고시 스케치, 현물 확인을 통한 도면화,일반 사양화, 복수화 전환 검토 요청 필히 부탁드립니다. 감사합니다._x000D_ | AT85: N
A86: Q4532144 | B86: 0 | C86: 포스코 | D86: Pneumatic Cylinder | E86: Hydraulic & Pneumatics | F86: 전아람 | G86: 특정사양품(단수) | H86: ACTIVE | I86: L | J86: KRW | K86: CWC(DA),CC,63Dx20Dx110ST,10kgf/cm2,[CDA2C63-110Z-A93L/SMC],FOR 2ZRM WR CHANGE CAR NEW ROLL STORAGE STOPPER,OR EQUIVALENT | L86: SET | M86: STANDARD | N86: CDA2C63-110Z-A93L | O86: SMC | R86: NONE | X86: FOR 2ZRM WR CHANGE CAR NEW ROLL STORAGE STOPPER | AE86: https://www.smckorea.co.kr/ppis/data/catalog/CA2-Z.pdf | AH86: CA2_CDA2_Z_20210810112047681.jpg | AJ86: 박용봉 | AK86: (포항)압연설비부 전기강판정비섹션 | AM86: 최육기 | AN86: (포항)압연설비부 전기강판정비섹션 | AO86: ykchoi@posco.co.kr | AP86: 2021-08-12 11:08:24 | AQ86: 2021 | AR86: 차후 재점검 | AT86: N
A87: Q4642442 | B87: 0 | C87: 포스코 | D87: Pneumatic Cylinder | E87: Pneumatic Cylinder | F87: 전아람 | G87: 특정사양품(단수) | H87: ACTIVE | I87: L | J87: KRW | K87: CWC(DA),TC,63Dx20Dx125ST,7kgf/cm2,[CA2WT63-125KKZ-NW-XC5/SMC],FOR 2SMP SUB LANCE LOCKING DEVICE,OR EQUIVALENT | L87: EA | M87: STANDARD | N87: CA2WT63-125KKZ-NW-XC5 | O87: SMC | R87: NONE | X87: FOR 2SMP SUB LANCE LOCKING DEVICE | AE87: https://www.smckorea.co.kr/ppis/data/catalog/CA2-Z.pdf?ver=9343.67818688394 | AH87: 실린더 사진(복동, 양로드)_20240416114404866.png | AJ87: 하성원 | AK87: (포항)제강설비부 제강정비섹션 | AL87: hagry2@posco.co.kr | AM87: 하성원 | AN87: (포항)제강설비부 제강정비섹션 | AO87: hagry2@posco.co.kr | AP87: 2024-06-28 10:06:43 | AQ87: 2024 | AR87: 차후 재점검 | AS87: Q4107450 등 유사itme 검색하였으나, 없음 확인후 승인합니다. | AT87: N
A88: Q4533799 | B88: 0 | C88: 포스코 | D88: Pneumatic Cylinder | E88: Hydraulic & Pneumatics | F88: 전아람 | G88: 특정사양품(단수) | H88: ACTIVE | I88: L | J88: KRW | K88: CWC(DA),40Dx200ST,[CDG1TA40-200Z-H7BWL3/SMC],OR EQUIVALENT | L88: SET | M88: STANDARD | N88: CDG1TA40-200Z-H7BWL3 | O88: SMC | R88: NONE | AE88: https://www.smckorea.co.kr/ppis/data/catalog/CG1-Z.pdf | AH88: cyl123123_20210927161905877.jpg | AJ88: 김재석 | AK88: (포항)제강설비부 연주정비섹션 | AM88: 김현우 | AN88: (포항)제강설비부 연주정비섹션 | AO88: bearer601n@posco.co.kr | AP88: 2021-10-05 15:10:40 | AQ88: 2021 | AR88: 차후 재점검 | AT88: N
A89: Q4550787 | B89: 0 | C89: 포스코 | D89: Pneumatic Cylinder | E89: Pneumatic Cylinder | F89: 전아람 | G89: 특정사양품(단수) | H89: ACTIVE | I89: L | J89: KRW | K89: CWC(DA),LB,50Dx20Dx30ST,[SDG1LN50-S8630-30/SMC],OR EQUIVALENT | L89: SET | M89: STANDARD | N89: SDG1LN50-S8630-30 | O89: SMC | R89: NONE | AE89: https://www.smckorea.co.kr/ppis/data/catalog/CG1-Z.pdf | AH89: CDG1LN50_20220110085649032.jpg | AJ89: 이규연 | AK89: (포항)압연설비부 전기강판정비섹션 | AL89: lkydh@posco.co.kr | AM89: 김태원 | AN89: (포항)압연설비부 전기강판정비섹션 | AP89: 2022-02-09 08:02:32 | AQ89: 2022 | AR89: 불가피 품목 | AT89: N
A90: Q4662525 | B90: 0 | C90: 포스코 | D90: Pneumatic Cylinder | E90: Pneumatic Cylinder | F90: 전아람 | G90: 특정사양품(단수) | H90: ACTIVE | I90: L | J90: KRW | K90: CWC(DA),FL,40Dx250ST,10kgf/cm2,[CDM2L40-250Z-M9BL/SMC],FOR 1RCL EXIT SLEEVE MACHINE,OR EQUIVALENT | L90: SET | M90: STANDARD | N90: CDM2L40-250Z-M9BL | O90: SMC | R90: NONE | X90: FOR 1RCL EXIT SLEEVE MACHINE | AE90: https://www.smckorea.co.kr/ppis/data/catalog/CM2-Z.pdf | AH90: Pneumatic Cylinder_20250114075055004.png | AJ90: 이규연 | AK90: (포항)압연설비2부 전기강판정비섹션 | AL90: lkydh@posco.co.kr | AM90: 장재훈 | AN90: (포항)압연설비2부 전기강판정비섹션 | AO90: banana4356@posco.co.kr | AP90: 2025-01-21 13:01:25 | AQ90: 2025 | AR90: 차후 재점검 | AS90: MRO e-Caltalog시스템 경유건으로 대체 Maker 미 발굴건, 기 설치된 Cylinder의 호환성을 위해 특정 사양으로 등록건 확인,_x000D_ Q4241983등 유사item 검색하였으나, 유사/동일품 없음 확인후 승인합니다._x000D_ (특정 사양품감축 관련) 차후 입고시 스케치, 현물 확인을 통한 도면화,일반 사양화, 복수화 전환 검토 요청 필히 부탁드립니다. 감사합니다._x000D_ | AT90: N
A91: Q4586797 | B91: 0 | C91: 포스코 | D91: Pneumatic Cylinder | E91: Pneumatic Cylinder | F91: 전아람 | G91: 특정사양품(단수) | H91: ACTIVE | I91: L | J91: KRW | K91: CWC(DA),LB,50Dx20Dx550ST,[CDNA2L50-550-D-A93L3/SMC],FOR P1H LABEL MACHINE FEEDER LOCK PNEUMATIC CYLINDER,OR EQUIVALENT | L91: SET | M91: STANDARD | N91: CDNA2L50-550-D-A93L3 | O91: SMC | R91: NONE | X91: FOR P1H LABEL MACHINE FEEDER LOCK PNEUMATIC CYLINDER | AE91: https://www.smckorea.co.kr/ppis/data/catalog/CNA2.pdf | AH91: 엔드락실린더_20230109143658929.jpg | AJ91: 조규호 | AK91: (포항)압연설비1부 열연정비섹션 | AL91: kyuho85@posco.co.kr | AM91: 이일하 | AN91: (포항)압연설비1부 열연정비섹션 | AP91: 2023-01-16 16:01:35 | AQ91: 2023 | AR91: 불가피 품목 | AS91: MRO e-Caltalog시스템 엔투비경유건으로 대체 Maker 미 발굴건,Label Feeder Lock 핵심 부품으로 기 설치된 Pneumatic Cylinder의 호환성을 위해 특정 사양으로 등록건 확인 후 승인,(특정 사양품감축 관련)특정 사양 감축 활동의 일환으로 차후 특정 사양품을 도면화,일반 사양화,복수화 전환 검토 필히 부탁드립니다. 감사합니다. | AT91: N
A92: Q4603925 | B92: 0 | C92: 포스코 | D92: Pneumatic Cylinder | E92: Pneumatic Cylinder | F92: 전아람 | G92: 특정사양품(단수) | H92: ACTIVE | I92: L | J92: KRW | K92: CWC(DA),FA,50Dx20Dx450ST,10kgf/cm2,[CDNA2F50-KRT22KO-450-D-B54L/SMC],FOR 2PL GAS CUTTING MACHINE MC2000,OR EQUIVALENT | L92: EA | M92: STANDARD | N92: CDNA2F50-KRT22KO-450-D-B54L | O92: SMC | R92: NONE | X92: FOR 2PL GAS CUTTING MACHINE MC2000 | AE92: https://www.smckorea.co.kr/ppis/data/catalog/CNA2.pdf | AH92: CNA2_20230607161506729.jpg | AJ92: 장원령 | AK92: (포항)압연설비1부 후판정비섹션 | AL92: jwr0322@posco.co.kr | AM92: 김현중 | AN92: (포항)압연설비1부 후판정비섹션 | AO92: cypher0615@posco.co.kr | AP92: 2023-06-22 13:06:35 | AQ92: 2023 | AR92: 차후 재점검 | AS92: MRO e-Caltalog시스템 경유건으로 대체 Maker 미 발굴건, 2PL GAS CUTTING MACHINE MC2000의 핵심 부품으로 기 설치된 Pneumatic Cylinder의 호환성을 위해 특정 사양으로 등록건 확인 후 승인,(특정 사양품감축 관련) 차후 입고시 스케치, 현물 확인을 통한 도면화,일반 사양화,복수화 전환 검토 요청 필히 부탁드립니다. 감사합니다.( KRT22KO 벨로즈우 사양 확인후 smc확인건) | AT92: N
A93: Q4621318 | B93: 0 | C93: 포스코 | D93: Pneumatic Cylinder | E93: Pneumatic Cylinder | F93: 전아람 | G93: 특정사양품(단수) | H93: ACTIVE | I93: L | J93: KRW | K93: 80Dx71Dx500ST,10kgf/cm2,[CNA2D80-500-D/SMC],OR EQUIVALENT | L93: EA | M93: BLANKET | N93: CNA2D80-500-D | O93: SMC | R93: NONE | AE93: https://www.smckorea.co.kr/ppis/data/catalog/CNA2.pdf | AH93: 락실린더_20231129093247662.png | AI93: lock cyl_20231204133201193.jpg | AJ93: 김원길 | AK93: (포항)압연설비2부 STS압연정비섹션 | AL93: 855956@posco.co.kr | AM93: 이현수 | AN93: (포항)압연설비2부 STS압연정비섹션 | AO93: hslee940111@posco.co.kr | AP93: 2023-12-04 13:12:07 | AQ93: 2023 | AR93: 차후 재점검 | AS93: 유사품 검색 및 사양 검증용 자료 확인후 승인합니다._x000D_ | AT93: N
A94: Q4590564 | B94: 0 | C94: 포스코 | D94: Pneumatic Cylinder | E94: Pneumatic Cylinder | F94: 전아람 | G94: 특정사양품(단수) | H94: ACTIVE | I94: L | J94: KRW | K94: CWC(DA),40Dx30ST,[CQ2B40-30DZ/SMC],FOR 1CGL ZINC POT AIR KNIFE DOCKING UNIT,OR EQUIVALENT | L94: SET | M94: STANDARD | N94: CQ2B40-30DZ | O94: SMC | R94: NONE | X94: FOR 1CGL ZINC POT AIR KNIFE DOCKING UNIT | AE94: https://www.smckorea.co.kr/ppis/data/catalog/CQ2-Z.pdf | AH94: CD2B40-30DZ_20230214081259454.jpg | AJ94: 박광웅 | AK94: (광양)압연설비2부 도금정비1섹션 | AM94: 김준기 | AN94: (광양)압연설비2부 도금정비1섹션 | AP94: 2023-02-21 09:02:56 | AQ94: 2023 | AR94: 차후 재점검 | AS94: Q4295735 ,Q4476307의 복수화 사례를 참조하여 차후 필히 복수화 검토 부탁드립니다. MRO e-Caltalog시스템 경유건으로 대체 Maker 미 발굴건, 기 설치된 Pneumatic Cylinder의 호환성을 위해 특정 사양으로 등록건 확인 후 승인,(특정 사양품감축 관련) 차후 입고시 스케치, 현물 확인을 통한 도면화,일반 사양화,복수화 전환 검토 요청 필히 부탁드립니다. 감사합니다. | AT94: N
A95: Q4663082 | B95: 0 | C95: 포스코 | D95: Pneumatic Cylinder | E95: Pneumatic Cylinder | F95: 전아람 | G95: 특정사양품(단수) | H95: ACTIVE | I95: L | J95: KRW | K95: CWC(DA),80Dx22Dx75ST,10kgf/cm2,[CQ2A80-75DMZ/SMC],FOR STSTHENS 1CPL PAPER UNWINDER,OR EQUIVALENT | L95: EA | M95: STANDARD | N95: CQ2A80-75DMZ | O95: SMC | R95: NONE | X95: FOR STSTHENS 1CPL PAPER UNWINDER | AE95: https://www.smckorea.co.kr/ppis/data/catalog/CQ2-Z.pdf | AH95: 박형 실린더 외형_20250122124715278.jpg | AJ95: 김원길 | AK95: (포항)압연설비2부 STS압연정비섹션 | AL95: 855956@posco.co.kr | AM95: 박성도 | AN95: (포항)압연설비2부 STS압연정비섹션 | AO95: sdbark@posco.co.kr | AP95: 2025-02-03 07:02:02 | AQ95: 2025 | AR95: 차후 재점검 | AS95: MRO e-Caltalog시스템 경유건으로 대체 Maker 미 발굴건, 기 설치된 Cylinder의 호환성을 위해 특정 사양으로 등록건 확인,_x000D_ Q4420623등 유사item 검색하였으나, 유사/동일품 없음 확인후 승인합니다._x000D_ (특정 사양품감축 관련) 차후 입고시 스케치, 현물 확인을 통한 도면화,일반 사양화, 복수화 전환 검토 요청 필히 부탁드립니다. 감사합니다._x000D_ | AT95: N
A96: Q4664034 | B96: 0 | C96: 포스코 | D96: Pneumatic Cylinder | E96: Pneumatic Cylinder | F96: 전아람 | G96: 특정사양품(단수) | H96: ACTIVE | I96: L | J96: KRW | K96: CSA,180Dx45Dx850ST,10kgf/cm2,[CS1TN180-KRD036-8-850-XC15/SMC],OR EQUIVALENT | L96: EA | M96: STANDARD | N96: CS1TN180-KRD036-8-850-XC15 | O96: SMC | R96: NONE | AE96: https://www.smckorea.co.kr/ppis/data/catalog/CS1.pdf | AH96: BANDING MACHINE HEAD CARRIAGE CYLINDER_20250205075724806.jpg | AJ96: 김원길 | AK96: (포항)압연설비2부 STS압연정비섹션 | AL96: 855956@posco.co.kr | AM96: 김희재 | AN96: (포항)압연설비2부 STS압연정비섹션 | AO96: gmlwo7225@posco.co.kr | AP96: 2025-02-10 09:02:20 | AQ96: 2025 | AR96: 차후 재점검 | AS96: MRO e-Caltalog시스템 경유건으로 대체 Maker 미 발굴건, 기 설치된 Cylinder의 호환성을 위해 특정 사양으로 등록건 확인,_x000D_ Q4350825 등 유사item 검색하였으나, 유사/동일품 없음 확인후 승인합니다._x000D_ (특정 사양품감축 관련) 차후 입고시 스케치, 현물 확인을 통한 도면화,일반 사양화, 복수화 전환 검토 요청 필히 부탁드립니다. 감사합니다._x000D_ | AT96: N
A97: Q4696036 | B97: 0 | C97: 포스코 | D97: Pneumatic Cylinder | E97: Pneumatic Cylinder | F97: 전아람 | G97: 특정사양품(단수) | H97: ACTIVE | I97: L | J97: KRW | K97: CWC(DA),CB,200Dx50Dx1800ST,10kgf/cm2,[CDS1DN200-KRD0368-1800-X1034/SMC],FOR 1EGL BANDING MACHINE HEAD,OR EQUIVALENT | L97: EA | M97: STANDARD | N97: CDS1DN200-KRD0368-1800-X1034 | O97: SMC | Q97: UNKNOWN | R97: NONE | T97: UNKNOWN | U97: NONE | X97: FOR 1EGL BANDING MACHINE HEAD | AE97: https://www.smckorea.co.kr/ppis/data/catalog/CS1.pdf | AH97: CDS1 CYLINDER_20251215074400923.jpg | AJ97: 박무균 | AK97: (포항)압연설비2부 냉연정비2섹션 | AL97: any0406@posco.co.kr | AM97: 백종수 | AN97: (포항)압연설비2부 냉연정비2섹션 | AO97: jongsu97@posco.co.kr | AP97: 2025-12-18 13:12:03 | AQ97: 2025 | AS97: 기 설치된 물품의 호환성을 위해 특정 사양으로 등록건 확인, Q4391441등 유사 item 검색하였으나 동일 메이커의 다른 형번임을 확인하였고, 유사/동일품 없음 확인후 승인합니다. (특정 사양품감축 관련) 차후 입고시 스케치, 현물 확인을 통한 도면화, 일반 사양화, 복수화 전환 검토 요청 부탁드립니다. 감사합니다. | AT97: N
A98: Q4658997 | B98: 0 | C98: 포스코 | D98: Pneumatic Cylinder | E98: Pneumatic Cylinder | F98: 전아람 | G98: 특정사양품(단수) | H98: ACTIVE | I98: L | J98: KRW | K98: CWC(DA),CC,140Dx300ST,9.9kgf/cm2,[CS1DN140-KRT04K0-300-XC5/SMC],7GGL AL INGOT FEEDER,OR EQUIVALENT | L98: SET | M98: BLANKET | N98: CS1DN140-KRT04K0-300-XC5 | O98: SMC | R98: NONE | X98: 7GGL AL INGOT FEEDER | AE98: https://www.smckorea.co.kr/ppis/data/catalog/CS1.pdf?ver=5456.764074372962 | AH98: CYLINDER-INGOT_20241216075846425.jpg | AJ98: 김형종 | AK98: (광양)압연설비2부 도금정비2섹션 | AL98: naju68@posco.co.kr | AM98: 장호선 | AN98: (광양)압연설비2부 도금정비2섹션 | AO98: hs6011@posco.co.kr | AP98: 2024-12-17 16:12:14 | AQ98: 2024 | AR98: 차후 재점검 | AS98: Q4448869등 유사item 검색하였으나, 동일 메이커의 다른 형번임 확인후 승인합니다. _x000D_ | AT98: N
A99: Q4618340 | B99: 0 | C99: 포스코 | D99: Pneumatic Cylinder | E99: Pneumatic Cylinder | F99: 전아람 | G99: 특정사양품(단수) | H99: ACTIVE | I99: L | J99: KRW | K99: 32Dx0Dx500ST,10kgf/cm2,[CY1L32H-500/SMC],FOR 2APL BAND CUTTER,OR EQUIVALENT | L99: SET | M99: STANDARD | N99: CY1L32H-500 | O99: SMC | R99: NONE | X99: FOR 2APL BAND CUTTER | AE99: https://www.smckorea.co.kr/ppis/data/catalog/CY1.pdf | AH99: CY1L32H-500-SMC_20231103131749121.jpg | AJ99: 이규연 | AK99: (포항)압연설비2부 전기강판정비섹션 | AL99: lkydh@posco.co.kr | AM99: 김충기 | AN99: (포항)압연설비2부 전기강판정비섹션 | AP99: 2023-11-03 14:11:09 | AQ99: 2023 | AR99: 차후 재점검 | AS99: NPR승인 화면에 측정 사양품 단수 등록건이나 카달로그 번호 없어 등록신청이력 조회 > 카달로그 번호 (LC0471-0000796) 확인건,MRO e-Caltalog시스템 경유건으로 대체 Maker 미 발굴건, 2전강 2APL Band Cutter의 핵심 부품으로 기 설치된 Pneumatic Cylinder의 호환성을 위해 특정 사양으로 등록건 확인 후 승인,_x000D_ (특정 사양품감축 관련) 차후 입고시 스케치, 현물 확인을 통한 도면화,일반 사양화,복수화 전환 검토 요청 필히 부탁드립니다. (첨부 PDF 6~7 Page 확인)감사합니다. | AT99: N
A100: Q4532140 | B100: 0 | C100: 포스코 | D100: Pneumatic Cylinder | E100: Hydraulic & Pneumatics | F100: 전아람 | G100: 특정사양품(단수) | H100: ACTIVE | I100: L | J100: KRW | K100: CWC(DA),LC,50Dx20Dx50ST,10kgf/cm2,[MDBL50-50Z-A93/SMC],FOR 2ZRM W/ROLL CHANGE CAR W/ROLL PULLING CYLINDER,OR EQUIVALENT | L100: SET | M100: STANDARD | N100: MDBL50-50Z-A93 | O100: SMC | R100: NONE | X100: FOR 2ZRM W/ROLL CHANGE CAR W/ROLL PULLING CYLINDER | AE100: https://www.smckorea.co.kr/ppis/data/catalog/MB-Z.pdf | AH100: MB_MDB_Z_20210810103950238.jpg | AJ100: 박용봉 | AK100: (포항)압연설비부 전기강판정비섹션 | AM100: 최육기 | AN100: (포항)압연설비부 전기강판정비섹션 | AO100: ykchoi@posco.co.kr | AP100: 2021-08-12 11:08:54 | AQ100: 2021 | AR100: 차후 재점검 | AT100: N
...

Sheet 실린더 상세사양값. 80
A1: ITEM코드 | B1: 처리상태 | C1: 자재특성구분 | D1: 해당여부 | E1: 물품(Leaf Class)명 | F1: 그룹사명 | G1: 사양/규격 | H1: 개정차수 | I1: 단위 | J1: 조달구분 | K1: 신청자 | L1: 도면번호 | M1: 행번호 | N1: 첨부URL1 | O1: 첨부URL2 | P1: 첨부URL3 | Q1: SPEC_TITLE_1 | R1: SPEC_VALUE_1 | S1: SPEC_TITLE_2 | T1: SPEC_VALUE_2 | U1: SPEC_TITLE_3 | V1: SPEC_VALUE_3 | W1: SPEC_TITLE_4 | X1: SPEC_VALUE_4 | Y1: SPEC_TITLE_5 | Z1: SPEC_VALUE_5 | AA1: SPEC_TITLE_6 | AB1: SPEC_VALUE_6 | AC1: SPEC_TITLE_7 | AD1: SPEC_VALUE_7 | AE1: SPEC_TITLE_8 | AF1: SPEC_VALUE_8 | AG1: SPEC_TITLE_9 | AH1: SPEC_VALUE_9 | AI1: SPEC_TITLE_10 | AJ1: SPEC_VALUE_10 | AK1: SPEC_TITLE_11 | AL1: SPEC_VALUE_11 | AM1: SPEC_TITLE_12 | AN1: SPEC_VALUE_12 | AO1: SPEC_TITLE_13 | AP1: SPEC_VALUE_13 | AQ1: SPEC_TITLE_14 | AR1: SPEC_VALUE_14 | AS1: SPEC_TITLE_15 | AT1: SPEC_VALUE_15 | AU1: SPEC_TITLE_16 | AV1: SPEC_VALUE_16 | AW1: SPEC_TITLE_17 | AX1: SPEC_VALUE_17 | AY1: SPEC_TITLE_18 | AZ1: SPEC_VALUE_18 | BA1: SPEC_TITLE_19 | BB1: SPEC_VALUE_19 | BC1: SPEC_TITLE_20 | BD1: SPEC_VALUE_20 | BE1: SPEC_TITLE_21 | BF1: SPEC_VALUE_21 | BG1: SPEC_TITLE_22 | BH1: SPEC_VALUE_22 | BI1: SPEC_TITLE_23 | BJ1: SPEC_VALUE_23 | BK1: SPEC_TITLE_24 | BL1: SPEC_VALUE_24 | BM1: SPEC_TITLE_25 | BN1: SPEC_VALUE_25 | BO1: SPEC_TITLE_26 | BP1: SPEC_VALUE_26 | BQ1: SPEC_TITLE_27 | BR1: SPEC_VALUE_27 | BS1: SPEC_TITLE_28 | BT1: SPEC_VALUE_28 | BU1: SPEC_TITLE_29 | BV1: SPEC_VALUE_29 | BW1: SPEC_TITLE_30 | BX1: SPEC_VALUE_30 | BY1: SPEC_TITLE_31 | BZ1: SPEC_VALUE_31 | CA1: SPEC_TITLE_32 | CB1: SPEC_VALUE_32 | CC1: SPEC_TITLE_33 | CD1: SPEC_VALUE_33 | CE1: SPEC_TITLE_34 | CF1: SPEC_VALUE_34 | CG1: SPEC_VALUE_34
A2: Q4269320 | B2: ACTIVE | C2: 특정사양품(단수) | D2: Q4269320 | E2: Pneumatic Cylinder | F2: 포스코 | G2: CWC(DA),CA,160Dx40Dx900ST,10kgf/cm2,[CS1CN160-900-CJQD1890/SMC],FOR 2SMP KR IMPELLER SLAG CUTING CYLINDER,OR EQUIVALENT | H2: 1 | I2: SET | J2: L | K2: 하성원 | N2: http://www.smckorea.co.kr/posco/Q1890D_AP.tif | Q2: Used Goods | S2: Green Purchase | T2: NONE | U2: Safety Management | V2: NONE | W2: Posco Patent | Y2: Or Equivalent | Z2: OR EQUIVALENT | AA2: Cylinder Type | AB2: CWC(DA) | AC2: Mounting Type | AD2: CA | AE2: Bore Size | AF2: 160 | AG2: Rod Diameter | AH2: 40 | AI2: Stroke Length | AJ2: 900 | AK2: Pressure Rating | AL2: 10 | AM2: Model-1 | AN2: CS1CN160-900-CJQD1890 | AO2: Maker Name-1 | AP2: SMC | AQ2: Option-1 | AS2: Model-2 | AU2: Maker Name-2 | AV2: NONE | AW2: Option-2 | AY2: Model-3 | BA2: Maker Name-3 | BC2: Option-3 | BE2: Option & Others | BG2: Application | BH2: FOR 2SMP KR IMPELLER SLAG CUTING CYLINDER
A3: Q4507377 | B3: ACTIVE | C3: 특정사양품(단수) | D3: Q4507377 | E3: Pneumatic Cylinder | F3: 포스코 | G3: CWC(DA),FA,50Dx20Dx10ST,10kgf/cm2,[CDQMB50-10-A72/SMC],FOR 2ZRM ROLL CHANGE CAR LIFTER ROLL SHIFT CYLINDER,OR EQUIVALENT | H3: 1 | I3: EA | J3: L | K3: 박용봉 | N3: http://www.smckorea.co.kr/ppis/data/catalog/CQM.pdf | Q3: Used Goods | S3: Green Purchase | T3: NONE | U3: Safety Management | V3: NONE | W3: Posco Patent | Y3: Or Equivalent | Z3: OR EQUIVALENT | AA3: Cylinder Type | AB3: CWC(DA) | AC3: Mounting Type | AD3: FA | AE3: Bore Size | AF3: 50 | AG3: Rod Diameter | AH3: 20 | AI3: Stroke Length | AJ3: 10 | AK3: Pressure Rating | AL3: 10 | AM3: Model-1 | AN3: CDQMB50-10-A72 | AO3: Maker Name-1 | AP3: SMC | AQ3: Option-1 | AS3: Model-2 | AU3: Maker Name-2 | AV3: NONE | AW3: Option-2 | AY3: Model-3 | BA3: Maker Name-3 | BC3: Option-3 | BE3: Option & Others | BG3: Application | BH3: FOR 2ZRM ROLL CHANGE CAR LIFTER ROLL SHIFT CYLINDER
A4: Q4508586 | B4: ACTIVE | C4: 특정사양품(단수) | D4: Q4508586 | E4: Pneumatic Cylinder | F4: 포스코 | G4: CWC(DA),[CDM2E32-200Z-NW-A93L/SMC],4CC MARKING | H4: 1 | I4: SET | J4: L | K4: 김재석 | N4: http://www.smckorea.co.kr/ppis/data/catalog/CM2-Z.pdf | Q4: Used Goods | S4: Green Purchase | T4: NONE | U4: Safety Management | V4: NONE | W4: Posco Patent | Y4: Or Equivalent | AA4: Cylinder Type | AB4: CWC(DA) | AC4: Mounting Type | AD4: OTHERS | AE4: Bore Size | AF4: 9999 | AG4: Rod Diameter | AH4: 9999 | AI4: Stroke Length | AJ4: 9999 | AK4: Pressure Rating | AM4: Model-1 | AN4: CDM2E32-200Z-NW-A93L | AO4: Maker Name-1 | AP4: SMC | AQ4: Option-1 | AS4: Model-2 | AU4: Maker Name-2 | AV4: NONE | AW4: Option-2 | AY4: Model-3 | BA4: Maker Name-3 | BC4: Option-3 | BE4: Option & Others | BG4: Application | BH4: 4CC MARKING
A5: Q4510521 | B5: ACTIVE | C5: 특정사양품(단수) | D5: Q4510521 | E5: Pneumatic Cylinder | F5: 포스코퓨처엠 | G5: CWC(DA),CA,80Dx25Dx100ST,10kgf/cm2,[CDQ2B80-100DMZ-XA18/SMC] | H5: 1 | I5: SET | J5: L | K5: 김 지환 | N5: http://www.smckorea.co.kr/ppis/data/catalog/CQ-Z.pdf | Q5: Used Goods | S5: Green Purchase | T5: NONE | U5: Safety Management | V5: NONE | W5: Posco Patent | Y5: Or Equivalent | AA5: Cylinder Type | AB5: CWC(DA) | AC5: Mounting Type | AD5: CA | AE5: Bore Size | AF5: 80 | AG5: Rod Diameter | AH5: 25 | AI5: Stroke Length | AJ5: 100 | AK5: Pressure Rating | AL5: 10 | AM5: Model-1 | AN5: CDQ2B80-100DMZ-XA18 | AO5: Maker Name-1 | AP5: SMC | AQ5: Option-1 | AS5: Model-2 | AU5: Maker Name-2 | AV5: NONE | AW5: Option-2 | AY5: Model-3 | BA5: Maker Name-3 | BC5: Option-3 | BE5: Option & Others | BG5: Application
A6: Q4361361 | B6: ACTIVE | C6: 특정사양품(단수) | D6: Q4361361 | E6: Pneumatic Cylinder | F6: 포스코 | G6: CWC(DA),TC,180Dx45Dx800ST,10kgf/cm2,[CS1T180-800-XC86B/SMC],FOR SOFT COKE HOPPER GATE CYLINDER,OR EQUIVALENT | H6: 2 | I6: EA | K6: 이오근 | N6: http://www.smckorea.co.kr/ppis/data/catalog/CS1.pdf | Q6: Used Goods | S6: Green Purchase | T6: NONE | U6: Safety Management | V6: NONE | W6: Posco Patent | Y6: Or Equivalent | Z6: OR EQUIVALENT | AA6: Cylinder Type | AB6: CWC(DA) | AC6: Mounting Type | AD6: TC | AE6: Bore Size | AF6: 180 | AG6: Rod Diameter | AH6: 45 | AI6: Stroke Length | AJ6: 800 | AK6: Pressure Rating | AL6: 10 | AM6: Model-1 | AN6: CS1T180-800-XC86B | AO6: Maker Name-1 | AP6: SMC | AQ6: Option-1 | AS6: Model-2 | AU6: Maker Name-2 | AV6: NONE | AW6: Option-2 | AY6: Model-3 | BA6: Maker Name-3 | BC6: Option-3 | BE6: Option & Others | BG6: Application | BH6: FOR SOFT COKE HOPPER GATE CYLINDER
A7: Q4511190 | B7: ACTIVE | C7: 특정사양품(단수) | D7: Q4511190 | E7: Pneumatic Cylinder | F7: 포스코 | G7: CWC(DA),TC,100Dx30Dx125ST,[CDA2T100-KRT09KO-125Z-W-A96L/SMC],FOR 2PL MAIN MARKING LINK CYLINDER,OR EQUIVALENT | H7: 1 | I7: EA | J7: L | K7: 김형진 | N7: http://www.smckorea.co.kr/ppis/data/catalog/CA2-Z.pdf | Q7: Used Goods | S7: Green Purchase | T7: NONE | U7: Safety Management | V7: NONE | W7: Posco Patent | Y7: Or Equivalent | Z7: OR EQUIVALENT | AA7: Cylinder Type | AB7: CWC(DA) | AC7: Mounting Type | AD7: TC | AE7: Bore Size | AF7: 100 | AG7: Rod Diameter | AH7: 30 | AI7: Stroke Length | AJ7: 125 | AK7: Pressure Rating | AM7: Model-1 | AN7: CDA2T100-KRT09KO-125Z-W-A96L | AO7: Maker Name-1 | AP7: SMC | AQ7: Option-1 | AS7: Model-2 | AU7: Maker Name-2 | AV7: NONE | AW7: Option-2 | AY7: Model-3 | BA7: Maker Name-3 | BC7: Option-3 | BE7: Option & Others | BG7: Application | BH7: FOR 2PL MAIN MARKING LINK CYLINDER
A8: Q4520278 | B8: ACTIVE | C8: 특정사양품(단수) | D8: Q4520278 | E8: Pneumatic Cylinder | F8: 포스코 | G8: CWC(DA),CA,40Dx14Dx160ST,10kgf/cm2,[CDM2E40TF-160Z-XC6/SMC],FOR 2PL UST MEASURING WHEEL CYLINDER,OR EQUIVALENT | H8: 1 | I8: EA | J8: L | K8: 김형진 | N8: http://www.smckorea.co.kr/ppis/data/catalog/CM2-Z.pdf | Q8: Used Goods | S8: Green Purchase | T8: NONE | U8: Safety Management | V8: NONE | W8: Posco Patent | Y8: Or Equivalent | Z8: OR EQUIVALENT | AA8: Cylinder Type | AB8: CWC(DA) | AC8: Mounting Type | AD8: CA | AE8: Bore Size | AF8: 40 | AG8: Rod Diameter | AH8: 14 | AI8: Stroke Length | AJ8: 160 | AK8: Pressure Rating | AL8: 10 | AM8: Model-1 | AN8: CDM2E40TF-160Z-XC6 | AO8: Maker Name-1 | AP8: SMC | AQ8: Option-1 | AS8: Model-2 | AU8: Maker Name-2 | AV8: NONE | AW8: Option-2 | AY8: Model-3 | BA8: Maker Name-3 | BC8: Option-3 | BE8: Option & Others | BG8: Application | BH8: FOR 2PL UST MEASURING WHEEL CYLINDER
A9: Q4521203 | B9: ACTIVE | C9: 특정사양품(단수) | D9: Q4521203 | E9: Pneumatic Cylinder | F9: 포스코 | G9: CWC(DA),CB,100Dx25Dx320ST,10kgf/cm2,[C96SD100-320C/SMC],OR EQUIVALENT | H9: 1 | I9: SET | J9: L | K9: 최춘식 | N9: http://www.smckorea.co.kr/ppis/data/catalog/C96.pdf | Q9: Used Goods | S9: Green Purchase | T9: NONE | U9: Safety Management | V9: NONE | W9: Posco Patent | Y9: Or Equivalent | Z9: OR EQUIVALENT | AA9: Cylinder Type | AB9: CWC(DA) | AC9: Mounting Type | AD9: CB | AE9: Bore Size | AF9: 100 | AG9: Rod Diameter | AH9: 25 | AI9: Stroke Length | AJ9: 320 | AK9: Pressure Rating | AL9: 10 | AM9: Model-1 | AN9: C96SD100-320C | AO9: Maker Name-1 | AP9: SMC | AQ9: Option-1 | AS9: Model-2 | AU9: Maker Name-2 | AV9: NONE | AW9: Option-2 | AY9: Model-3 | BA9: Maker Name-3 | BC9: Option-3 | BE9: Option & Others | BG9: Application
A10: Q4524100 | B10: ACTIVE | C10: 특정사양품(단수) | D10: Q4524100 | E10: Pneumatic Cylinder | F10: 포스코 | G10: 20Dx50ST,[JCMMZ20TR-50/SMC],FOR 1WRM BTJ A-LINE G/M #1,2,3 WHEEL MEASURING CYL',OR EQUIVALENT | H10: 1 | I10: EA | J10: L | K10: 김성엽 | N10: http://ca01.smcworld.com/catalog/New-products/mpv/s20-237-jcm/index.html#target/page_no=4 | Q10: Used Goods | S10: Green Purchase | T10: NONE | U10: Safety Management | W10: Posco Patent | Y10: Or Equivalent | Z10: OR EQUIVALENT | AA10: Cylinder Type | AB10: OTHERS | AC10: Mounting Type | AD10: OTHERS | AE10: Bore Size | AF10: 20 | AG10: Rod Diameter | AH10: 9999 | AI10: Stroke Length | AJ10: 50 | AK10: Pressure Rating | AM10: Model-1 | AN10: JCMMZ20TR-50 | AO10: Maker Name-1 | AP10: SMC | AQ10: Option-1 | AS10: Model-2 | AU10: Maker Name-2 | AV10: NONE | AW10: Option-2 | AY10: Model-3 | BA10: Maker Name-3 | BC10: Option-3 | BE10: Option & Others | BG10: Application | BH10: FOR 1WRM BTJ A-LINE G/M #1,2,3 WHEEL MEASURING CYL'
A11: Q4532140 | B11: ACTIVE | C11: 특정사양품(단수) | D11: Q4532140 | E11: Pneumatic Cylinder | F11: 포스코 | G11: CWC(DA),LC,50Dx20Dx50ST,10kgf/cm2,[MDBL50-50Z-A93/SMC],FOR 2ZRM W/ROLL CHANGE CAR W/ROLL PULLING CYLINDER,OR EQUIVALENT | H11: 1 | I11: SET | J11: L | K11: 박용봉 | N11: https://www.smckorea.co.kr/ppis/data/catalog/MB-Z.pdf | Q11: Used Goods | S11: Green Purchase | T11: NONE | U11: Safety Management | W11: Posco Patent | Y11: Or Equivalent | Z11: OR EQUIVALENT | AA11: Cylinder Type | AB11: CWC(DA) | AC11: Mounting Type | AD11: LC | AE11: Bore Size | AF11: 50 | AG11: Rod Diameter | AH11: 20 | AI11: Stroke Length | AJ11: 50 | AK11: Pressure Rating | AL11: 10 | AM11: Model-1 | AN11: MDBL50-50Z-A93 | AO11: Maker Name-1 | AP11: SMC | AQ11: Option-1 | AS11: Model-2 | AU11: Maker Name-2 | AV11: NONE | AW11: Option-2 | AY11: Model-3 | BA11: Maker Name-3 | BC11: Option-3 | BE11: Option & Others | BG11: Application | BH11: FOR 2ZRM W/ROLL CHANGE CAR W/ROLL PULLING CYLINDER
A12: Q4532141 | B12: ACTIVE | C12: 특정사양품(단수) | D12: Q4532141 | E12: Pneumatic Cylinder | F12: 포스코 | G12: CWC(DA),SD,40Dx20Dx700ST,10kgf/cm2,[MGZ40-700-A93/SMC],FOR 2ZRM WR CHANGE CAR WR PUSHER,OR EQUIVALENT | H12: 1 | I12: SET | J12: L | K12: 박용봉 | N12: https://www.smckorea.co.kr/ppis/data/catalog/MGZ_MGZR.pdf | Q12: Used Goods | S12: Green Purchase | T12: NONE | U12: Safety Management | W12: Posco Patent | Y12: Or Equivalent | Z12: OR EQUIVALENT | AA12: Cylinder Type | AB12: CWC(DA) | AC12: Mounting Type | AD12: SD | AE12: Bore Size | AF12: 40 | AG12: Rod Diameter | AH12: 20 | AI12: Stroke Length | AJ12: 700 | AK12: Pressure Rating | AL12: 10 | AM12: Model-1 | AN12: MGZ40-700-A93 | AO12: Maker Name-1 | AP12: SMC | AQ12: Option-1 | AS12: Model-2 | AU12: Maker Name-2 | AV12: NONE | AW12: Option-2 | AY12: Model-3 | BA12: Maker Name-3 | BC12: Option-3 | BE12: Option & Others | BG12: Application | BH12: FOR 2ZRM WR CHANGE CAR WR PUSHER
A13: Q4532142 | B13: ACTIVE | C13: 특정사양품(단수) | D13: Q4532142 | E13: Pneumatic Cylinder | F13: 포스코 | G13: CWC(DA),SD,40Dx20Dx100ST,10kgf/cm2,[MGZL40-100-A93/SMC],FOR 2ZRM WR CHANGE CAR WR SHIFT AND ESCAPER STOPPER AIR CYLINDER,OR EQUIVALENT | H13: 1 | I13: SET | J13: L | K13: 박용봉 | N13: https://www.smckorea.co.kr/ppis/data/catalog/MGZ_MGZR.pdf | Q13: Used Goods | S13: Green Purchase | T13: NONE | U13: Safety Management | W13: Posco Patent | Y13: Or Equivalent | Z13: OR EQUIVALENT | AA13: Cylinder Type | AB13: CWC(DA) | AC13: Mounting Type | AD13: SD | AE13: Bore Size | AF13: 40 | AG13: Rod Diameter | AH13: 20 | AI13: Stroke Length | AJ13: 100 | AK13: Pressure Rating | AL13: 10 | AM13: Model-1 | AN13: MGZL40-100-A93 | AO13: Maker Name-1 | AP13: SMC | AQ13: Option-1 | AS13: Model-2 | AU13: Maker Name-2 | AV13: NONE | AW13: Option-2 | AY13: Model-3 | BA13: Maker Name-3 | BC13: Option-3 | BE13: Option & Others | BG13: Application | BH13: FOR 2ZRM WR CHANGE CAR WR SHIFT AND ESCAPER STOPPER AIR CYLINDER
A14: Q4532144 | B14: ACTIVE | C14: 특정사양품(단수) | D14: Q4532144 | E14: Pneumatic Cylinder | F14: 포스코 | G14: CWC(DA),CC,63Dx20Dx110ST,10kgf/cm2,[CDA2C63-110Z-A93L/SMC],FOR 2ZRM WR CHANGE CAR NEW ROLL STORAGE STOPPER,OR EQUIVALENT | H14: 1 | I14: SET | J14: L | K14: 박용봉 | N14: https://www.smckorea.co.kr/ppis/data/catalog/CA2-Z.pdf | Q14: Used Goods | S14: Green Purchase | T14: NONE | U14: Safety Management | W14: Posco Patent | Y14: Or Equivalent | Z14: OR EQUIVALENT | AA14: Cylinder Type | AB14: CWC(DA) | AC14: Mounting Type | AD14: CC | AE14: Bore Size | AF14: 63 | AG14: Rod Diameter | AH14: 20 | AI14: Stroke Length | AJ14: 110 | AK14: Pressure Rating | AL14: 10 | AM14: Model-1 | AN14: CDA2C63-110Z-A93L | AO14: Maker Name-1 | AP14: SMC | AQ14: Option-1 | AS14: Model-2 | AU14: Maker Name-2 | AV14: NONE | AW14: Option-2 | AY14: Model-3 | BA14: Maker Name-3 | BC14: Option-3 | BE14: Option & Others | BG14: Application | BH14: FOR 2ZRM WR CHANGE CAR NEW ROLL STORAGE STOPPER
A15: Q4532777 | B15: ACTIVE | C15: 특정사양품(단수) | D15: Q4532777 | E15: Pneumatic Cylinder | F15: 포스코 | G15: CWC(DA),40Dx350ST,[CDA2G40-350Z-W-A93L/SMC],1CC BILLET MARKING MACHINE,OR EQUIVALENT | H15: 1 | I15: SET | J15: L | K15: 김재석 | N15: https://kr.c.misumi-ec.com/book/SMC1_37/digitalcatalog.html?page_num=A-470 | Q15: Used Goods | S15: Green Purchase | T15: NONE | U15: Safety Management | W15: Posco Patent | Y15: Or Equivalent | Z15: OR EQUIVALENT | AA15: Cylinder Type | AB15: CWC(DA) | AC15: Mounting Type | AD15: OTHERS | AE15: Bore Size | AF15: 40 | AG15: Rod Diameter | AH15: 9999 | AI15: Stroke Length | AJ15: 350 | AK15: Pressure Rating | AM15: Model-1 | AN15: CDA2G40-350Z-W-A93L | AO15: Maker Name-1 | AP15: SMC | AQ15: Option-1 | AS15: Model-2 | AU15: Maker Name-2 | AV15: NONE | AW15: Option-2 | AY15: Model-3 | BA15: Maker Name-3 | BC15: Option-3 | BE15: Option & Others | BG15: Application | BH15: 1CC BILLET MARKING MACHINE
A16: Q4533799 | B16: ACTIVE | C16: 특정사양품(단수) | D16: Q4533799 | E16: Pneumatic Cylinder | F16: 포스코 | G16: CWC(DA),40Dx200ST,[CDG1TA40-200Z-H7BWL3/SMC],OR EQUIVALENT | H16: 2 | I16: SET | K16: 김재석 | N16: https://www.smckorea.co.kr/ppis/data/catalog/CG1-Z.pdf | Q16: Used Goods | S16: Green Purchase | T16: NONE | U16: Safety Management | W16: Posco Patent | Y16: Or Equivalent | Z16: OR EQUIVALENT | AA16: Cylinder Type | AB16: CWC(DA) | AC16: Mounting Type | AD16: OTHERS | AE16: Bore Size | AF16: 40 | AG16: Rod Diameter | AH16: 9999 | AI16: Stroke Length | AJ16: 200 | AK16: Pressure Rating | AM16: Model-1 | AN16: CDG1TA40-200Z-H7BWL3 | AO16: Maker Name-1 | AP16: SMC | AQ16: Option-1 | AS16: Model-2 | AU16: Maker Name-2 | AV16: NONE | AW16: Option-2 | AY16: Model-3 | BA16: Maker Name-3 | BC16: Option-3 | BE16: Option & Others | BG16: Application
A17: Q4542398 | B17: ACTIVE | C17: 특정사양품(단수) | D17: Q4542398 | E17: Pneumatic Cylinder | F17: 포스코 | G17: CWC(DA),FA,160Dx40Dx550ST,10kgf/cm2,[CS1FN160-550-CJZD0231/SMC],FOR 3SMP RH ALLOYING,OR EQUIVALENT | H17: 1 | I17: SET | J17: L | K17: 김종훈 | N17: https://www.smckorea.co.kr/ppis/data/domyun/CJZD0231-AP.pdf | Q17: Used Goods | S17: Green Purchase | T17: NONE | U17: Safety Management | W17: Posco Patent | Y17: Or Equivalent | Z17: OR EQUIVALENT | AA17: Cylinder Type | AB17: CWC(DA) | AC17: Mounting Type | AD17: FA | AE17: Bore Size | AF17: 160 | AG17: Rod Diameter | AH17: 40 | AI17: Stroke Length | AJ17: 550 | AK17: Pressure Rating | AL17: 10 | AM17: Model-1 | AN17: CS1FN160-550-CJZD0231 | AO17: Maker Name-1 | AP17: SMC | AQ17: Option-1 | AS17: Model-2 | AU17: Maker Name-2 | AV17: NONE | AW17: Option-2 | AY17: Model-3 | BA17: Maker Name-3 | BC17: Option-3 | BE17: Option & Others | BG17: Application | BH17: FOR 3SMP RH ALLOYING
A18: Q4459460 | B18: ACTIVE | C18: 특정사양품(단수) | D18: Q4459460 | E18: Pneumatic Cylinder | F18: 포스코 | G18: CWC(DA),FA,200Dx50Dx125ST,[CS1FN200-KRT04JO-125-XC6/SMC],FOR K1CGL WATER QUENCH,OR EQUIVALENT | H18: 2 | I18: EA | K18: 박광웅 | N18: http://www.smckorea.co.kr/ppis/data/catalog/CS1.pdf | Q18: Used Goods | S18: Green Purchase | T18: NONE | U18: Safety Management | V18: NONE | W18: Posco Patent | Y18: Or Equivalent | Z18: OR EQUIVALENT | AA18: Cylinder Type | AB18: CWC(DA) | AC18: Mounting Type | AD18: FA | AE18: Bore Size | AF18: 200 | AG18: Rod Diameter | AH18: 50 | AI18: Stroke Length | AJ18: 125 | AK18: Pressure Rating | AM18: Model-1 | AN18: CS1FN200-KRT04JO-125-XC6 | AO18: Maker Name-1 | AP18: SMC | AQ18: Option-1 | AS18: Model-2 | AU18: Maker Name-2 | AV18: NONE | AW18: Option-2 | AY18: Model-3 | BA18: Maker Name-3 | BC18: Option-3 | BE18: Option & Others | BG18: Application | BH18: FOR K1CGL WATER QUENCH
A19: Q4501288 | B19: ACTIVE | C19: 특정사양품(단수) | D19: Q4501288 | E19: Pneumatic Cylinder | F19: 포스코 | G19: CWC(DA),160Dx100ST,[CS1CN160-100-CJAD0046/SMC],FOR 1CGL #5,#6,#7 TENSION BRIDLE SNUBBER ROLL,OR EQUIVALENT | H19: 2 | I19: EA | K19: 박광웅 | N19: http://www.smcpneumatics.com/pdfs/smc/70ACS1.pdf | Q19: Used Goods | S19: Green Purchase | T19: NONE | U19: Safety Management | V19: NONE | W19: Posco Patent | Y19: Or Equivalent | Z19: OR EQUIVALENT | AA19: Cylinder Type | AB19: CWC(DA) | AC19: Mounting Type | AD19: OTHERS | AE19: Bore Size | AF19: 160 | AG19: Rod Diameter | AH19: 9999 | AI19: Stroke Length | AJ19: 100 | AK19: Pressure Rating | AM19: Model-1 | AN19: CS1CN160-100-CJAD0046 | AO19: Maker Name-1 | AP19: SMC | AQ19: Option-1 | AS19: Model-2 | AU19: Maker Name-2 | AV19: NONE | AW19: Option-2 | AY19: Model-3 | BA19: Maker Name-3 | BC19: Option-3 | BE19: Option & Others | BG19: Application | BH19: FOR 1CGL #5,#6,#7 TENSION BRIDLE SNUBBER ROLL
A20: Q4549165 | B20: ACTIVE | C20: 특정사양품(단수) | D20: Q4549165 | E20: Pneumatic Cylinder | F20: 포스코 | G20: CWC(DA),TC,80Dx25Dx125ST,10kgf/cm2,[ACM-N-TC80-S125-J/KCC],FOR CGL SHOT BLAST DUST COLLECTOR DOUBLE DAMPER PNEUMATIC CYLINDER,OR EQUIVALENT | H20: 1 | I20: EA | J20: L | K20: 권인순 | N20: https://www.kccpr.com/bbs/search.php?url=https%3A%2F%2Fwww.kccpr.com%2Fbbs%2Fsearch.php&stx=ACM | Q20: Used Goods | S20: Green Purchase | T20: NONE | U20: Safety Management | W20: Posco Patent | Y20: Or Equivalent | Z20: OR EQUIVALENT | AA20: Cylinder Type | AB20: CWC(DA) | AC20: Mounting Type | AD20: TC | AE20: Bore Size | AF20: 80 | AG20: Rod Diameter | AH20: 25 | AI20: Stroke Length | AJ20: 125 | AK20: Pressure Rating | AL20: 10 | AM20: Model-1 | AN20: ACM-N-TC80-S125-J | AO20: Maker Name-1 | AP20: KCC | AQ20: Option-1 | AS20: Model-2 | AU20: Maker Name-2 | AV20: NONE | AW20: Option-2 | AY20: Model-3 | BA20: Maker Name-3 | BC20: Option-3 | BE20: Option & Others | BG20: Application | BH20: FOR CGL SHOT BLAST DUST COLLECTOR DOUBLE DAMPER PNEUMATIC CYLINDER
A21: Q4550786 | B21: ACTIVE | C21: 특정사양품(단수) | D21: Q4550786 | E21: Pneumatic Cylinder | F21: 포스코 | G21: FA,50Dx20Dx425ST,10kgf/cm2,[ACM-N-FA50-S425/KCC],OR EQUIVALENT | H21: 1 | I21: SET | J21: L | K21: 이규연 | N21: https://www.kccpr.com/bbs/search.php?url=https%3A%2F%2Fwww.kccpr.com%2Fbbs%2Fsearch.php&stx=ACM | Q21: Used Goods | S21: Green Purchase | T21: NONE | U21: Safety Management | W21: Posco Patent | Y21: Or Equivalent | Z21: OR EQUIVALENT | AA21: Cylinder Type | AB21: OTHERS | AC21: Mounting Type | AD21: FA | AE21: Bore Size | AF21: 50 | AG21: Rod Diameter | AH21: 20 | AI21: Stroke Length | AJ21: 425 | AK21: Pressure Rating | AL21: 10 | AM21: Model-1 | AN21: ACM-N-FA50-S425 | AO21: Maker Name-1 | AP21: KCC | AQ21: Option-1 | AS21: Model-2 | AU21: Maker Name-2 | AV21: NONE | AW21: Option-2 | AY21: Model-3 | BA21: Maker Name-3 | BC21: Option-3 | BE21: Option & Others | BG21: Application
A22: Q4550787 | B22: ACTIVE | C22: 특정사양품(단수) | D22: Q4550787 | E22: Pneumatic Cylinder | F22: 포스코 | G22: CWC(DA),LB,50Dx20Dx30ST,[SDG1LN50-S8630-30/SMC],OR EQUIVALENT | H22: 1 | I22: SET | J22: L | K22: 이규연 | N22: https://www.smckorea.co.kr/ppis/data/catalog/CG1-Z.pdf | Q22: Used Goods | S22: Green Purchase | T22: NONE | U22: Safety Management | W22: Posco Patent | Y22: Or Equivalent | Z22: OR EQUIVALENT | AA22: Cylinder Type | AB22: CWC(DA) | AC22: Mounting Type | AD22: LB | AE22: Bore Size | AF22: 50 | AG22: Rod Diameter | AH22: 20 | AI22: Stroke Length | AJ22: 30 | AK22: Pressure Rating | AM22: Model-1 | AN22: SDG1LN50-S8630-30 | AO22: Maker Name-1 | AP22: SMC | AQ22: Option-1 | AS22: Model-2 | AU22: Maker Name-2 | AV22: NONE | AW22: Option-2 | AY22: Model-3 | BA22: Maker Name-3 | BC22: Option-3 | BE22: Option & Others | BG22: Application
A23: Q4550788 | B23: ACTIVE | C23: 특정사양품(단수) | D23: Q4550788 | E23: Pneumatic Cylinder | F23: 포스코 | G23: CWC(DA),TC,40Dx16Dx575ST,[CDA2T40-575Z/SMC],OR EQUIVALENT | H23: 1 | I23: SET | J23: L | K23: 이규연 | N23: https://www.smckorea.co.kr/esales/data/sangpum/catalog/CA2.pdf | Q23: Used Goods | S23: Green Purchase | T23: NONE | U23: Safety Management | W23: Posco Patent | Y23: Or Equivalent | Z23: OR EQUIVALENT | AA23: Cylinder Type | AB23: CWC(DA) | AC23: Mounting Type | AD23: TC | AE23: Bore Size | AF23: 40 | AG23: Rod Diameter | AH23: 16 | AI23: Stroke Length | AJ23: 575 | AK23: Pressure Rating | AM23: Model-1 | AN23: CDA2T40-575Z | AO23: Maker Name-1 | AP23: SMC | AQ23: Option-1 | AS23: Model-2 | AU23: Maker Name-2 | AV23: NONE | AW23: Option-2 | AY23: Model-3 | BA23: Maker Name-3 | BC23: Option-3 | BE23: Option & Others | BG23: Application
A24: Q4284408 | B24: ACTIVE | C24: 특정사양품(단수) | D24: Q4284408 | E24: Pneumatic Cylinder | F24: 포스코 | G24: CWC(DA),TE,32Dx12Dx30ST,10kgf/cm2,[DWG NO:CDM2HU32-30Z-A93L/SMC],AUTO S/W D-A93L,FOR 2CAL WELDER UPPER & LOWER DRESS SWING | H24: 3 | I24: SET | K24: 이현식 | N24: http://www.smckorea.co.kr/posco/CDM2HU32-30-A93LS.tif | Q24: Used Goods | S24: Green Purchase | T24: NONE | U24: Safety Management | V24: NONE | W24: Posco Patent | Y24: Or Equivalent | AA24: Cylinder Type | AB24: CWC(DA) | AC24: Mounting Type | AD24: TE | AE24: Bore Size | AF24: 32 | AG24: Rod Diameter | AH24: 12 | AI24: Stroke Length | AJ24: 30 | AK24: Pressure Rating | AL24: 10 | AM24: Model-1 | AN24: DWG NO:CDM2HU32-30Z-A93L | AO24: Maker Name-1 | AP24: SMC | AQ24: Option-1 | AS24: Model-2 | AU24: Maker Name-2 | AV24: NONE | AW24: Option-2 | AY24: Model-3 | BA24: Maker Name-3 | BC24: Option-3 | BE24: Option & Others | BF24: AUTO S/W D-A93L | BG24: Application | BH24: FOR 2CAL WELDER UPPER & LOWER DRESS SWING
A25: Q4570987 | B25: ACTIVE | C25: 특정사양품(단수) | D25: Q4570987 | E25: Pneumatic Cylinder | F25: 포스코 | G25: CWC(DA),LB,50Dx30Dx165ST,3.0kgf/cm2,[CDA2T50-KRT09TO-165Z-A54Z/SMC],FOR 4M/C AIR CYLINDER,OR EQUIVALENT | H25: 1 | I25: SET | J25: L | K25: 김재석 | N25: https://www.smckorea.co.kr/ppis/data/catalog/CA2-Z.pdf | Q25: Used Goods | S25: Green Purchase | T25: NONE | U25: Safety Management | W25: Posco Patent | Y25: Or Equivalent | Z25: OR EQUIVALENT | AA25: Cylinder Type | AB25: CWC(DA) | AC25: Mounting Type | AD25: LB | AE25: Bore Size | AF25: 50 | AG25: Rod Diameter | AH25: 30 | AI25: Stroke Length | AJ25: 165 | AK25: Pressure Rating | AL25: 3.0 | AM25: Model-1 | AN25: CDA2T50-KRT09TO-165Z-A54Z | AO25: Maker Name-1 | AP25: SMC | AQ25: Option-1 | AS25: Model-2 | AU25: Maker Name-2 | AV25: NONE | AW25: Option-2 | AY25: Model-3 | BA25: Maker Name-3 | BC25: Option-3 | BE25: Option & Others | BG25: Application | BH25: FOR 4M/C AIR CYLINDER
A26: Q4580829 | B26: ACTIVE | C26: 특정사양품(단수) | D26: Q4580829 | E26: Pneumatic Cylinder | F26: 포스코 | G26: 40Dx16Dx450ST,[CDA2F40-450Z-Z73/SMC],FOR P1H HSL LABEL MACHINE FEEDER PNEUMATIC CYLINDER,OR EQUIVALENT | H26: 1 | I26: EA | J26: L | K26: 조규호 | N26: https://www.smckorea.co.kr/ppis/data/catalog/CA2-Z.pdf | Q26: Used Goods | S26: Green Purchase | T26: NONE | U26: Safety Management | W26: Posco Patent | Y26: Or Equivalent | Z26: OR EQUIVALENT | AA26: Cylinder Type | AB26: OTHERS | AC26: Mounting Type | AD26: OTHERS | AE26: Bore Size | AF26: 40 | AG26: Rod Diameter | AH26: 16 | AI26: Stroke Length | AJ26: 450 | AK26: Pressure Rating | AM26: Model-1 | AN26: CDA2F40-450Z-Z73 | AO26: Maker Name-1 | AP26: SMC | AQ26: Option-1 | AS26: Model-2 | AU26: Maker Name-2 | AV26: NONE | AW26: Option-2 | AY26: Model-3 | BA26: Maker Name-3 | BC26: Option-3 | BE26: Option & Others | BG26: Application | BH26: FOR P1H HSL LABEL MACHINE FEEDER PNEUMATIC CYLINDER
A27: Q4586797 | B27: ACTIVE | C27: 특정사양품(단수) | D27: Q4586797 | E27: Pneumatic Cylinder | F27: 포스코 | G27: CWC(DA),LB,50Dx20Dx550ST,[CDNA2L50-550-D-A93L3/SMC],FOR P1H LABEL MACHINE FEEDER LOCK PNEUMATIC CYLINDER,OR EQUIVALENT | H27: 1 | I27: SET | J27: L | K27: 조규호 | N27: https://www.smckorea.co.kr/ppis/data/catalog/CNA2.pdf | Q27: Used Goods | S27: Green Purchase | T27: NONE | U27: Safety Management | W27: Posco Patent | Y27: Or Equivalent | Z27: OR EQUIVALENT | AA27: Cylinder Type | AB27: CWC(DA) | AC27: Mounting Type | AD27: LB | AE27: Bore Size | AF27: 50 | AG27: Rod Diameter | AH27: 20 | AI27: Stroke Length | AJ27: 550 | AK27: Pressure Rating | AM27: Model-1 | AN27: CDNA2L50-550-D-A93L3 | AO27: Maker Name-1 | AP27: SMC | AQ27: Option-1 | AS27: Model-2 | AU27: Maker Name-2 | AV27: NONE | AW27: Option-2 | AY27: Model-3 | BA27: Maker Name-3 | BC27: Option-3 | BE27: Option & Others | BG27: Application | BH27: FOR P1H LABEL MACHINE FEEDER LOCK PNEUMATIC CYLINDER
A28: Q4590564 | B28: ACTIVE | C28: 특정사양품(단수) | D28: Q4590564 | E28: Pneumatic Cylinder | F28: 포스코 | G28: CWC(DA),40Dx30ST,[CQ2B40-30DZ/SMC],FOR 1CGL ZINC POT AIR KNIFE DOCKING UNIT,OR EQUIVALENT | H28: 1 | I28: SET | J28: L | K28: 박광웅 | N28: https://www.smckorea.co.kr/ppis/data/catalog/CQ2-Z.pdf | Q28: Used Goods | S28: Green Purchase | T28: NONE | U28: Safety Management | W28: Posco Patent | Y28: Or Equivalent | Z28: OR EQUIVALENT | AA28: Cylinder Type | AB28: CWC(DA) | AC28: Mounting Type | AD28: OTHERS | AE28: Bore Size | AF28: 40 | AG28: Rod Diameter | AH28: 9999 | AI28: Stroke Length | AJ28: 30 | AK28: Pressure Rating | AM28: Model-1 | AN28: CQ2B40-30DZ | AO28: Maker Name-1 | AP28: SMC | AQ28: Option-1 | AS28: Model-2 | AU28: Maker Name-2 | AV28: NONE | AW28: Option-2 | AY28: Model-3 | BA28: Maker Name-3 | BC28: Option-3 | BE28: Option & Others | BG28: Application | BH28: FOR 1CGL ZINC POT AIR KNIFE DOCKING UNIT
A29: Q4592305 | B29: ACTIVE | C29: 특정사양품(단수) | D29: Q4592305 | E29: Pneumatic Cylinder | F29: 포스코 | G29: CWC(DA),CA,160Dx40Dx320ST,[CS1CN160-320-CJBD0239/SMC],FOR 2CC MULTI BEBURRER,OR EQUIVALENT | H29: 1 | I29: SET | J29: L | K29: 서대봉 | N29: https://www.smckorea.co.kr/ppis/data/domyun/CJBD0239-AP.pdf | Q29: Used Goods | S29: Green Purchase | T29: NONE | U29: Safety Management | W29: Posco Patent | Y29: Or Equivalent | Z29: OR EQUIVALENT | AA29: Cylinder Type | AB29: CWC(DA) | AC29: Mounting Type | AD29: CA | AE29: Bore Size | AF29: 160 | AG29: Rod Diameter | AH29: 40 | AI29: Stroke Length | AJ29: 320 | AK29: Pressure Rating | AM29: Model-1 | AN29: CS1CN160-320-CJBD0239 | AO29: Maker Name-1 | AP29: SMC | AQ29: Option-1 | AS29: Model-2 | AU29: Maker Name-2 | AV29: NONE | AW29: Option-2 | AY29: Model-3 | BA29: Maker Name-3 | BC29: Option-3 | BE29: Option & Others | BG29: Application | BH29: FOR 2CC MULTI BEBURRER
A30: Q4592849 | B30: ACTIVE | C30: 특정사양품(단수) | D30: Q4592849 | E30: Pneumatic Cylinder | F30: 포스코 | G30: CWC(DA),TC,63Dx20Dx1100ST,[CA2T63-1100Z-XC14/SMC],FOR 1CGL BANDING MACHINE LOWER CHUTE CYLINDER,OR EQUIVALENT | H30: 1 | I30: EA | J30: L | K30: 김응백 | N30: https://www.smckorea.co.kr | Q30: Used Goods | S30: Green Purchase | T30: NONE | U30: Safety Management | W30: Posco Patent | Y30: Or Equivalent | Z30: OR EQUIVALENT | AA30: Cylinder Type | AB30: CWC(DA) | AC30: Mounting Type | AD30: TC | AE30: Bore Size | AF30: 63 | AG30: Rod Diameter | AH30: 20 | AI30: Stroke Length | AJ30: 1100 | AK30: Pressure Rating | AM30: Model-1 | AN30: CA2T63-1100Z-XC14 | AO30: Maker Name-1 | AP30: SMC | AQ30: Option-1 | AS30: Model-2 | AU30: Maker Name-2 | AV30: NONE | AW30: Option-2 | AY30: Model-3 | BA30: Maker Name-3 | BC30: Option-3 | BE30: Option & Others | BG30: Application | BH30: FOR 1CGL BANDING MACHINE LOWER CHUTE CYLINDER
A31: Q4596799 | B31: ACTIVE | C31: 특정사양품(단수) | D31: Q4596799 | E31: Pneumatic Cylinder | F31: 포스코 | G31: 32Dx200ST,[MY1B32-200Z-M9N/SMC],OR EQUIVALENT | H31: 1 | I31: SET | J31: L | K31: 박제혁 | N31: https://www.smckorea.co.kr/ppis/data/catalog/MY1.pdf | Q31: Used Goods | S31: Green Purchase | T31: NONE | U31: Safety Management | W31: Posco Patent | Y31: Or Equivalent | Z31: OR EQUIVALENT | AA31: Cylinder Type | AB31: OTHERS | AC31: Mounting Type | AD31: OTHERS | AE31: Bore Size | AF31: 32 | AG31: Rod Diameter | AH31: 9999 | AI31: Stroke Length | AJ31: 200 | AK31: Pressure Rating | AM31: Model-1 | AN31: MY1B32-200Z-M9N | AO31: Maker Name-1 | AP31: SMC | AQ31: Option-1 | AS31: Model-2 | AU31: Maker Name-2 | AV31: NONE | AW31: Option-2 | AY31: Model-3 | BA31: Maker Name-3 | BC31: Option-3 | BE31: Option & Others | BG31: Application
A32: Q4602359 | B32: ACTIVE | C32: 특정사양품(단수) | D32: Q4602359 | E32: Pneumatic Cylinder | F32: 포스코 | G32: CWC(DA),CA,63Dx20Dx300ST,[CDA2C63-KRT09JO-300Z-W-A54/SMC],FOR CGL OVEN FUME EXHAUST FAN DAMPER CYLINDER,OR EQUIVALENT | H32: 1 | I32: EA | J32: L | K32: 김응백 | N32: https://www.smckorea.co.kr/ | Q32: Used Goods | S32: Green Purchase | T32: NONE | U32: Safety Management | W32: Posco Patent | Y32: Or Equivalent | Z32: OR EQUIVALENT | AA32: Cylinder Type | AB32: CWC(DA) | AC32: Mounting Type | AD32: CA | AE32: Bore Size | AF32: 63 | AG32: Rod Diameter | AH32: 20 | AI32: Stroke Length | AJ32: 300 | AK32: Pressure Rating | AM32: Model-1 | AN32: CDA2C63-KRT09JO-300Z-W-A54 | AO32: Maker Name-1 | AP32: SMC | AQ32: Option-1 | AS32: Model-2 | AU32: Maker Name-2 | AV32: NONE | AW32: Option-2 | AY32: Model-3 | BA32: Maker Name-3 | BC32: Option-3 | BE32: Option & Others | BG32: Application | BH32: FOR CGL OVEN FUME EXHAUST FAN DAMPER CYLINDER
A33: Q4603925 | B33: ACTIVE | C33: 특정사양품(단수) | D33: Q4603925 | E33: Pneumatic Cylinder | F33: 포스코 | G33: CWC(DA),FA,50Dx20Dx450ST,10kgf/cm2,[CDNA2F50-KRT22KO-450-D-B54L/SMC],FOR 2PL GAS CUTTING MACHINE MC2000,OR EQUIVALENT | H33: 1 | I33: EA | J33: L | K33: 장원령 | N33: https://www.smckorea.co.kr/ppis/data/catalog/CNA2.pdf | Q33: Used Goods | S33: Green Purchase | T33: NONE | U33: Safety Management | W33: Posco Patent | Y33: Or Equivalent | Z33: OR EQUIVALENT | AA33: Cylinder Type | AB33: CWC(DA) | AC33: Mounting Type | AD33: FA | AE33: Bore Size | AF33: 50 | AG33: Rod Diameter | AH33: 20 | AI33: Stroke Length | AJ33: 450 | AK33: Pressure Rating | AL33: 10 | AM33: Model-1 | AN33: CDNA2F50-KRT22KO-450-D-B54L | AO33: Maker Name-1 | AP33: SMC | AQ33: Option-1 | AS33: Model-2 | AU33: Maker Name-2 | AV33: NONE | AW33: Option-2 | AY33: Model-3 | BA33: Maker Name-3 | BC33: Option-3 | BE33: Option & Others | BG33: Application | BH33: FOR 2PL GAS CUTTING MACHINE MC2000
A34: Q2095909 | B34: ACTIVE | C34: 특정사양품(단수) | D34: Q2095909 | E34: Pneumatic Cylinder | F34: 포스코 | G34: CTC,SD,32Dx16Dx70ST,7kgf/cm2,[MHL2-32D/SMC],DOUBLE PISTON(14,16),FOR 4RH SAMPLING DEVICE | H34: 2 | I34: SET | K34: 박경득 | N34: https://www.smckorea.co.kr/homepage/ver3.5/product/catalogue_sub_detail.asp?no=1051# | Q34: Used Goods | S34: Green Purchase | T34: NONE | U34: Safety Management | W34: Posco Patent | Y34: Or Equivalent | AA34: Cylinder Type | AB34: CTC | AC34: Mounting Type | AD34: SD | AE34: Bore Size | AF34: 32 | AG34: Rod Diameter | AH34: 16 | AI34: Stroke Length | AJ34: 70 | AK34: Pressure Rating | AL34: 7 | AM34: Model-1 | AN34: MHL2-32D | AO34: Maker Name-1 | AP34: SMC | AQ34: Option-1 | AS34: Model-2 | AU34: Maker Name-2 | AV34: NONE | AW34: Option-2 | AY34: Model-3 | BA34: Maker Name-3 | BC34: Option-3 | BE34: Option & Others | BF34: DOUBLE PISTON(14,16) | BG34: Application | BH34: FOR 4RH SAMPLING DEVICE
A35: Q4607652 | B35: ACTIVE | C35: 특정사양품(단수) | D35: Q4607652 | E35: Pneumatic Cylinder | F35: 포스코 | G35: CWC(DA),FA,200Dx50Dx2350ST,[ACL N H FA200 S2350 -Y D-J59K/KCC],1-1RCL BANDING MACHINE LIFTER | H35: 1 | I35: SET | J35: L | K35: 곽진섭 | N35: https://www.kccpr.com/bbs/search.php?url=https%3A%2F%2Fwww.kccpr.com%2Fbbs%2Fsearch.php&stx=ACL+N+H+FA200+ | Q35: Used Goods | S35: Green Purchase | T35: NONE | U35: Safety Management | W35: Posco Patent | Y35: Or Equivalent | AA35: Cylinder Type | AB35: CWC(DA) | AC35: Mounting Type | AD35: FA | AE35: Bore Size | AF35: 200 | AG35: Rod Diameter | AH35: 50 | AI35: Stroke Length | AJ35: 2350 | AK35: Pressure Rating | AM35: Model-1 | AN35: ACL N H FA200 S2350 -Y D-J59K | AO35: Maker Name-1 | AP35: KCC | AQ35: Option-1 | AS35: Model-2 | AU35: Maker Name-2 | AV35: NONE | AW35: Option-2 | AY35: Model-3 | BA35: Maker Name-3 | BC35: Option-3 | BE35: Option & Others | BG35: Application | BH35: 1-1RCL BANDING MACHINE LIFTER
A36: Q4609635 | B36: ACTIVE | C36: 특정사양품(단수) | D36: Q4609635 | E36: Pneumatic Cylinder | F36: 포스코 | G36: CWC(DA),CF,40Dx14Dx40ST,10kgf/cm2,[CM2B40-40Z/SMC],FOR K1APL EXIT SEAL ROLL UPPER/LOWER SEAL PACKING OPEN/CLOSE,OR EQUIVALENT | H36: 1 | I36: SET | J36: L | K36: 정정현 | N36: https://www.smckorea.co.kr/ppis/data/catalog/CM2-Z.pdf | Q36: Used Goods | S36: Green Purchase | T36: NONE | U36: Safety Management | W36: Posco Patent | Y36: Or Equivalent | Z36: OR EQUIVALENT | AA36: Cylinder Type | AB36: CWC(DA) | AC36: Mounting Type | AD36: CF | AE36: Bore Size | AF36: 40 | AG36: Rod Diameter | AH36: 14 | AI36: Stroke Length | AJ36: 40 | AK36: Pressure Rating | AL36: 10 | AM36: Model-1 | AN36: CM2B40-40Z | AO36: Maker Name-1 | AP36: SMC | AQ36: Option-1 | AS36: Model-2 | AU36: Maker Name-2 | AV36: NONE | AW36: Option-2 | AY36: Model-3 | BA36: Maker Name-3 | BC36: Option-3 | BE36: Option & Others | BG36: Application | BH36: FOR K1APL EXIT SEAL ROLL UPPER/LOWER SEAL PACKING OPEN/CLOSE
A37: Q4609636 | B37: ACTIVE | C37: 특정사양품(단수) | D37: Q4609636 | E37: Pneumatic Cylinder | F37: 포스코 | G37: CWC(DA),FA,100Dx30Dx115ST,10kgf/cm2,[CA2F100-KRT10KO-115Z-W-XC5/SMC],FOR K1APL FURNACE ENTRY SEAL ROLL UP & DOWN PNEUMATIC CYLINDER,OR EQUIVALENT | H37: 1 | I37: SET | J37: L | K37: 정정현 | N37: https://www.smckorea.co.kr/ | Q37: Used Goods | S37: Green Purchase | T37: NONE | U37: Safety Management | W37: Posco Patent | Y37: Or Equivalent | Z37: OR EQUIVALENT | AA37: Cylinder Type | AB37: CWC(DA) | AC37: Mounting Type | AD37: FA | AE37: Bore Size | AF37: 100 | AG37: Rod Diameter | AH37: 30 | AI37: Stroke Length | AJ37: 115 | AK37: Pressure Rating | AL37: 10 | AM37: Model-1 | AN37: CA2F100-KRT10KO-115Z-W-XC5 | AO37: Maker Name-1 | AP37: SMC | AQ37: Option-1 | AS37: Model-2 | AU37: Maker Name-2 | AV37: NONE | AW37: Option-2 | AY37: Model-3 | BA37: Maker Name-3 | BC37: Option-3 | BE37: Option & Others | BG37: Application | BH37: FOR K1APL FURNACE ENTRY SEAL ROLL UP & DOWN PNEUMATIC CYLINDER
A38: Q4610700 | B38: ACTIVE | C38: 특정사양품(단수) | D38: Q4610700 | E38: Pneumatic Cylinder | F38: 포스코 | G38: CWC(DA),TC,63Dx20Dx50ST,10kgf/cm2,[C96ST63-50-CJBG0810/SMC],OR EQUIVALENT | H38: 1 | I38: SET | J38: L | K38: 이규연 | Q38: Used Goods | S38: Green Purchase | T38: NONE | U38: Safety Management | W38: Posco Patent | Y38: Or Equivalent | Z38: OR EQUIVALENT | AA38: Cylinder Type | AB38: CWC(DA) | AC38: Mounting Type | AD38: TC | AE38: Bore Size | AF38: 63 | AG38: Rod Diameter | AH38: 20 | AI38: Stroke Length | AJ38: 50 | AK38: Pressure Rating | AL38: 10 | AM38: Model-1 | AN38: C96ST63-50-CJBG0810 | AO38: Maker Name-1 | AP38: SMC | AQ38: Option-1 | AS38: Model-2 | AU38: Maker Name-2 | AV38: NONE | AW38: Option-2 | AY38: Model-3 | BA38: Maker Name-3 | BC38: Option-3 | BE38: Option & Others | BG38: Application
A39: Q4611126 | B39: ACTIVE | C39: 특정사양품(단수) | D39: Q4611126 | E39: Pneumatic Cylinder | F39: 포스코 | G39: CWD,TC,100Dx30Dx420ST,[CDA2T100-420Z-A93L-XC14/SMC],OR EQUIVALENT | H39: 1 | I39: SET | J39: L | K39: 김영민 | N39: https://www.smckorea.co.kr/esales/data/sangpum/kisul_qa/2023KS008009/CDA2T100-420Z-A93L-XC14.pdf | Q39: Used Goods | S39: Green Purchase | T39: NONE | U39: Safety Management | W39: Posco Patent | Y39: Or Equivalent | Z39: OR EQUIVALENT | AA39: Cylinder Type | AB39: CWD | AC39: Mounting Type | AD39: TC | AE39: Bore Size | AF39: 100 | AG39: Rod Diameter | AH39: 30 | AI39: Stroke Length | AJ39: 420 | AK39: Pressure Rating | AM39: Model-1 | AN39: CDA2T100-420Z-A93L-XC14 | AO39: Maker Name-1 | AP39: SMC | AQ39: Option-1 | AS39: Model-2 | AU39: Maker Name-2 | AV39: NONE | AW39: Option-2 | AY39: Model-3 | BA39: Maker Name-3 | BC39: Option-3 | BE39: Option & Others | BG39: Application
A40: Q4618340 | B40: ACTIVE | C40: 특정사양품(단수) | D40: Q4618340 | E40: Pneumatic Cylinder | F40: 포스코 | G40: 32Dx0Dx500ST,10kgf/cm2,[CY1L32H-500/SMC],FOR 2APL BAND CUTTER,OR EQUIVALENT | H40: 1 | I40: SET | J40: L | K40: 이규연 | N40: https://www.smckorea.co.kr/ppis/data/catalog/CY1.pdf | Q40: Used Goods | S40: Green Purchase | T40: NONE | U40: Safety Management | W40: Posco Patent | Y40: Or Equivalent | Z40: OR EQUIVALENT | AA40: Cylinder Type | AB40: OTHERS | AC40: Mounting Type | AD40: OTHERS | AE40: Bore Size | AF40: 32 | AG40: Rod Diameter | AH40: 0 | AI40: Stroke Length | AJ40: 500 | AK40: Pressure Rating | AL40: 10 | AM40: Model-1 | AN40: CY1L32H-500 | AO40: Maker Name-1 | AP40: SMC | AQ40: Option-1 | AS40: Model-2 | AU40: Maker Name-2 | AV40: NONE | AW40: Option-2 | AY40: Model-3 | BA40: Maker Name-3 | BC40: Option-3 | BE40: Option & Others | BG40: Application | BH40: FOR 2APL BAND CUTTER
A41: Q4621318 | B41: ACTIVE | C41: 특정사양품(단수) | D41: Q4621318 | E41: Pneumatic Cylinder | F41: 포스코 | G41: 80Dx71Dx500ST,10kgf/cm2,[CNA2D80-500-D/SMC],OR EQUIVALENT | H41: 1 | I41: EA | J41: L | K41: 김원길 | N41: https://www.smckorea.co.kr/ppis/data/catalog/CNA2.pdf | Q41: Used Goods | S41: Green Purchase | T41: NONE | U41: Safety Management | W41: Posco Patent | Y41: Or Equivalent | Z41: OR EQUIVALENT | AA41: Cylinder Type | AB41: OTHERS | AC41: Mounting Type | AD41: OTHERS | AE41: Bore Size | AF41: 80 | AG41: Rod Diameter | AH41: 71 | AI41: Stroke Length | AJ41: 500 | AK41: Pressure Rating | AL41: 10 | AM41: Model-1 | AN41: CNA2D80-500-D | AO41: Maker Name-1 | AP41: SMC | AQ41: Option-1 | AS41: Model-2 | AU41: Maker Name-2 | AV41: NONE | AW41: Option-2 | AY41: Model-3 | BA41: Maker Name-3 | BC41: Option-3 | BE41: Option & Others | BG41: Application
A42: Q4371330 | B42: ACTIVE | C42: 특정사양품(단수) | D42: Q4371330 | E42: Pneumatic Cylinder | F42: 포스코 | G42: 50D,10kgf/cm2,[CDQ2B50-55Z-DCN446GN/SMC],AIR CYLINDER FOR BANDING MACHINE | H42: 2 | I42: SET | K42: 곽진섭 | N42: http://www.smckorea.co.kr/esales/data/sangpum/catalog/CQ2-Z.pdf | Q42: Used Goods | S42: Green Purchase | T42: NONE | U42: Safety Management | V42: NONE | W42: Posco Patent | Y42: Or Equivalent | AA42: Cylinder Type | AB42: OTHERS | AC42: Mounting Type | AD42: OTHERS | AE42: Bore Size | AF42: 50 | AG42: Rod Diameter | AH42: 9999 | AI42: Stroke Length | AJ42: 9999 | AK42: Pressure Rating | AL42: 10 | AM42: Model-1 | AN42: CDQ2B50-55Z-DCN446GN | AO42: Maker Name-1 | AP42: SMC | AQ42: Option-1 | AS42: Model-2 | AU42: Maker Name-2 | AV42: NONE | AW42: Option-2 | AY42: Model-3 | BA42: Maker Name-3 | BC42: Option-3 | BE42: Option & Others | BG42: Application | BH42: AIR CYLINDER FOR BANDING MACHINE
A43: Q4623087 | B43: ACTIVE | C43: 특정사양품(단수) | D43: Q4623087 | E43: Pneumatic Cylinder | F43: 포스코 | G43: CWC(DA),FH,50Dx20Dx200ST,10.2kgf/cm2,[MLGPM50-200Z-F-A96L/SMC],OR EQUIVALENT | H43: 1 | I43: SET | J43: L | K43: 황해 | N43: https://www.smckorea.co.kr/homepage/ver3.5/srch/search.asp | Q43: Used Goods | S43: Green Purchase | T43: NONE | U43: Safety Management | W43: Posco Patent | Y43: Or Equivalent | Z43: OR EQUIVALENT | AA43: Cylinder Type | AB43: CWC(DA) | AC43: Mounting Type | AD43: FH | AE43: Bore Size | AF43: 50 | AG43: Rod Diameter | AH43: 20 | AI43: Stroke Length | AJ43: 200 | AK43: Pressure Rating | AL43: 10.2 | AM43: Model-1 | AN43: MLGPM50-200Z-F-A96L | AO43: Maker Name-1 | AP43: SMC | AQ43: Option-1 | AS43: Model-2 | AU43: Maker Name-2 | AV43: NONE | AW43: Option-2 | AY43: Model-3 | BA43: Maker Name-3 | BC43: Option-3 | BE43: Option & Others | BG43: Application
A44: Q4627207 | B44: ACTIVE | C44: 특정사양품(단수) | D44: Q4627207 | E44: Pneumatic Cylinder | F44: 포스코 | G44: CWC(DA),CA,200Dx200Dx220ST,16kgf/cm2,[CDS2T200-200-CJCD0039/SMC],OR EQUIVALENT | H44: 1 | I44: EA | J44: L | K44: 홍성현 | Q44: Used Goods | S44: Green Purchase | T44: NONE | U44: Safety Management | W44: Posco Patent | Y44: Or Equivalent | Z44: OR EQUIVALENT | AA44: Cylinder Type | AB44: CWC(DA) | AC44: Mounting Type | AD44: CA | AE44: Bore Size | AF44: 200 | AG44: Rod Diameter | AH44: 200 | AI44: Stroke Length | AJ44: 220 | AK44: Pressure Rating | AL44: 16 | AM44: Model-1 | AN44: CDS2T200-200-CJCD0039 | AO44: Maker Name-1 | AP44: SMC | AQ44: Option-1 | AS44: Model-2 | AU44: Maker Name-2 | AV44: NONE | AW44: Option-2 | AY44: Model-3 | BA44: Maker Name-3 | BC44: Option-3 | BE44: Option & Others | BG44: Application
A45: Q4627759 | B45: ACTIVE | C45: 특정사양품(단수) | D45: Q4627759 | E45: Pneumatic Cylinder | F45: 포스코 | G45: CWC(DA),TC,80Dx80Dx150ST,[CA2YT80-150Z-W/SMC],FOR K4H DC0~2 PINCH ROLL POLISHER AIR CYLINDER,OR EQUIVALENT | H45: 1 | I45: EA | J45: L | K45: 김성겸 | Q45: Used Goods | S45: Green Purchase | T45: NONE | U45: Safety Management | W45: Posco Patent | Y45: Or Equivalent | Z45: OR EQUIVALENT | AA45: Cylinder Type | AB45: CWC(DA) | AC45: Mounting Type | AD45: TC | AE45: Bore Size | AF45: 80 | AG45: Rod Diameter | AH45: 80 | AI45: Stroke Length | AJ45: 150 | AK45: Pressure Rating | AM45: Model-1 | AN45: CA2YT80-150Z-W | AO45: Maker Name-1 | AP45: SMC | AQ45: Option-1 | AS45: Model-2 | AU45: Maker Name-2 | AV45: NONE | AW45: Option-2 | AY45: Model-3 | BA45: Maker Name-3 | BC45: Option-3 | BE45: Option & Others | BG45: Application | BH45: FOR K4H DC0~2 PINCH ROLL POLISHER AIR CYLINDER
A46: Q4627795 | B46: ACTIVE | C46: 특정사양품(단수) | D46: Q4627795 | E46: Pneumatic Cylinder | F46: 포스코 | G46: CSA,LB,40Dx16Dx750ST,10.1kgf/cm2,[MDBB40-750Z-M9N/SMC],WITH SENSOR,MATERIAL TEST SHOP DTTM,OR EQUIVALENT | H46: 1 | I46: SET | J46: L | K46: 장요한 | N46: https://www.smckorea.co.kr/homepage/ver3.5/product/catalogue_sub_detail.asp?cata_no=911# | Q46: Used Goods | S46: Green Purchase | T46: NONE | U46: Safety Management | W46: Posco Patent | Y46: Or Equivalent | Z46: OR EQUIVALENT | AA46: Cylinder Type | AB46: CSA | AC46: Mounting Type | AD46: LB | AE46: Bore Size | AF46: 40 | AG46: Rod Diameter | AH46: 16 | AI46: Stroke Length | AJ46: 750 | AK46: Pressure Rating | AL46: 10.1 | AM46: Model-1 | AN46: MDBB40-750Z-M9N | AO46: Maker Name-1 | AP46: SMC | AQ46: Option-1 | AS46: Model-2 | AU46: Maker Name-2 | AV46: NONE | AW46: Option-2 | AY46: Model-3 | BA46: Maker Name-3 | BC46: Option-3 | BE46: Option & Others | BF46: WITH SENSOR | BG46: Application | BH46: MATERIAL TEST SHOP DTTM
A47: Q4627796 | B47: ACTIVE | C47: 특정사양품(단수) | D47: Q4627796 | E47: Pneumatic Cylinder | F47: 포스코 | G47: CSA,LB,40Dx16Dx690ST,10kgf/cm2,[MDBL40-690Z-W-M9N/SMC],WITH SENSOR,MATERIAL TEST SHOP DTTM,OR EQUIVALENT | H47: 1 | I47: SET | J47: L | K47: 장요한 | N47: https://www.smckorea.co.kr/homepage/ver3.5/product/catalogue_sub_detail.asp?cata_no=911# | Q47: Used Goods | S47: Green Purchase | T47: NONE | U47: Safety Management | W47: Posco Patent | Y47: Or Equivalent | Z47: OR EQUIVALENT | AA47: Cylinder Type | AB47: CSA | AC47: Mounting Type | AD47: LB | AE47: Bore Size | AF47: 40 | AG47: Rod Diameter | AH47: 16 | AI47: Stroke Length | AJ47: 690 | AK47: Pressure Rating | AL47: 10 | AM47: Model-1 | AN47: MDBL40-690Z-W-M9N | AO47: Maker Name-1 | AP47: SMC | AQ47: Option-1 | AS47: Model-2 | AU47: Maker Name-2 | AV47: NONE | AW47: Option-2 | AY47: Model-3 | BA47: Maker Name-3 | BC47: Option-3 | BE47: Option & Others | BF47: WITH SENSOR | BG47: Application | BH47: MATERIAL TEST SHOP DTTM
A48: Q4629827 | B48: ACTIVE | C48: 특정사양품(단수) | D48: Q4629827 | E48: Pneumatic Cylinder | F48: 포스코 | G48: 125Dx727Dx500ST,9.7kgf/cm2,[CDS1TN125-KRD0368-500-Z73L/SMC],MAKER DWG NO:CDS1TN125-KRD0368-500-Z73L,OR EQUIVALENT | H48: 1 | I48: SET | J48: L | K48: 민병찬 | Q48: Used Goods | S48: Green Purchase | T48: NONE | U48: Safety Management | W48: Posco Patent | Y48: Or Equivalent | Z48: OR EQUIVALENT | AA48: Cylinder Type | AB48: OTHERS | AC48: Mounting Type | AD48: OTHERS | AE48: Bore Size | AF48: 125 | AG48: Rod Diameter | AH48: 727 | AI48: Stroke Length | AJ48: 500 | AK48: Pressure Rating | AL48: 9.7 | AM48: Model-1 | AN48: CDS1TN125-KRD0368-500-Z73L | AO48: Maker Name-1 | AP48: SMC | AQ48: Option-1 | AS48: Model-2 | AU48: Maker Name-2 | AV48: NONE | AW48: Option-2 | AY48: Model-3 | BA48: Maker Name-3 | BC48: Option-3 | BE48: Option & Others | BF48: MAKER DWG NO:CDS1TN125-KRD0368-500-Z73L | BG48: Application
A49: Q4520279 | B49: ACTIVE | C49: 특정사양품(단수) | D49: Q4520279 | E49: Pneumatic Cylinder | F49: 포스코 | G49: CWC(DA),TA,50Dx20Dx170ST,10kgf/cm2,[CDG1UN50TF-170-CJZH0846/SMC],FOR 2PL UST PROBE HEADER CYLINDER,OR EQUIVALENT | H49: 2 | I49: EA | K49: 장원령 | N49: http://www.smckorea.co.kr/ppis/data/catalog/CG1-Z.pdf | Q49: Used Goods | S49: Green Purchase | T49: NONE | U49: Safety Management | V49: NONE | W49: Posco Patent | Y49: Or Equivalent | Z49: OR EQUIVALENT | AA49: Cylinder Type | AB49: CWC(DA) | AC49: Mounting Type | AD49: TA | AE49: Bore Size | AF49: 50 | AG49: Rod Diameter | AH49: 20 | AI49: Stroke Length | AJ49: 170 | AK49: Pressure Rating | AL49: 10 | AM49: Model-1 | AN49: CDG1UN50TF-170-CJZH0846 | AO49: Maker Name-1 | AP49: SMC | AQ49: Option-1 | AS49: Model-2 | AU49: Maker Name-2 | AV49: NONE | AW49: Option-2 | AY49: Model-3 | BA49: Maker Name-3 | BC49: Option-3 | BE49: Option & Others | BG49: Application | BH49: FOR 2PL UST PROBE HEADER CYLINDER
A50: Q4642442 | B50: ACTIVE | C50: 특정사양품(단수) | D50: Q4642442 | E50: Pneumatic Cylinder | F50: 포스코 | G50: CWC(DA),TC,63Dx20Dx125ST,7kgf/cm2,[CA2WT63-125KKZ-NW-XC5/SMC],FOR 2SMP SUB LANCE LOCKING DEVICE,OR EQUIVALENT | H50: 1 | I50: EA | J50: L | K50: 하성원 | N50: https://www.smckorea.co.kr/ppis/data/catalog/CA2-Z.pdf?ver=9343.67818688394 | Q50: Used Goods | S50: Green Purchase | T50: NONE | U50: Safety Management | W50: Posco Patent | Y50: Or Equivalent | Z50: OR EQUIVALENT | AA50: Cylinder Type | AB50: CWC(DA) | AC50: Mounting Type | AD50: TC | AE50: Bore Size | AF50: 63 | AG50: Rod Diameter | AH50: 20 | AI50: Stroke Length | AJ50: 125 | AK50: Pressure Rating | AL50: 7 | AM50: Model-1 | AN50: CA2WT63-125KKZ-NW-XC5 | AO50: Maker Name-1 | AP50: SMC | AQ50: Option-1 | AS50: Model-2 | AU50: Maker Name-2 | AV50: NONE | AW50: Option-2 | AY50: Model-3 | BA50: Maker Name-3 | BC50: Option-3 | BE50: Option & Others | BG50: Application | BH50: FOR 2SMP SUB LANCE LOCKING DEVICE
A51: Q4636670 | B51: ACTIVE | C51: 특정사양품(단수) | D51: Q4636670 | E51: Pneumatic Cylinder | F51: 포스코 | G51: CWC(DA),CA,320Dx320Dx250ST,[CDS2T320-250-CJCD0239/SMC],MAKER DWG NO:CDS2T320-250-CJCD0239,OR EQUIVALENT | H51: 1 | I51: EA | J51: L | K51: 홍성현 | Q51: Used Goods | S51: Green Purchase | T51: NONE | U51: Safety Management | W51: Posco Patent | Y51: Or Equivalent | Z51: OR EQUIVALENT | AA51: Cylinder Type | AB51: CWC(DA) | AC51: Mounting Type | AD51: CA | AE51: Bore Size | AF51: 320 | AG51: Rod Diameter | AH51: 320 | AI51: Stroke Length | AJ51: 250 | AK51: Pressure Rating | AM51: Model-1 | AN51: CDS2T320-250-CJCD0239 | AO51: Maker Name-1 | AP51: SMC | AQ51: Option-1 | AS51: Model-2 | AU51: Maker Name-2 | AV51: NONE | AW51: Option-2 | AY51: Model-3 | BA51: Maker Name-3 | BC51: Option-3 | BE51: Option & Others | BF51: MAKER DWG NO:CDS2T320-250-CJCD0239 | BG51: Application
A52: Q4648582 | B52: ACTIVE | C52: 특정사양품(단수) | D52: Q4648582 | E52: Pneumatic Cylinder | F52: 포스코 | G52: CWC(DA),TC,80Dx25Dx800ST,10kgf/cm2,[CA2T80-800KZ-NW-XB6/SMC],FOR 2SMP DE-P SUB LANCE SLIDE GATE,OR EQUIVALENT | H52: 1 | I52: SET | J52: L | K52: 하성원 | N52: https://www.smckorea.co.kr/homepage/ver3.5/product/catalogue_sub_detail.asp?cata_no=913 | Q52: Used Goods | S52: Green Purchase | T52: NONE | U52: Safety Management | W52: Posco Patent | Y52: Or Equivalent | Z52: OR EQUIVALENT | AA52: Cylinder Type | AB52: CWC(DA) | AC52: Mounting Type | AD52: TC | AE52: Bore Size | AF52: 80 | AG52: Rod Diameter | AH52: 25 | AI52: Stroke Length | AJ52: 800 | AK52: Pressure Rating | AL52: 10 | AM52: Model-1 | AN52: CA2T80-800KZ-NW-XB6 | AO52: Maker Name-1 | AP52: SMC | AQ52: Option-1 | AS52: Model-2 | AU52: Maker Name-2 | AV52: NONE | AW52: Option-2 | AY52: Model-3 | BA52: Maker Name-3 | BC52: Option-3 | BE52: Option & Others | BG52: Application | BH52: FOR 2SMP DE-P SUB LANCE SLIDE GATE
A53: Q4649046 | B53: ACTIVE | C53: 특정사양품(단수) | D53: Q4649046 | E53: Pneumatic Cylinder | F53: 포스코 | G53: CWC(DA),CC,40Dx14Dx350ST,10kgf/cm2,[CDBM2B40-350-HN-A93/SMC],FOR 3CAL SAMPLE MACHINE "Y" HEAD,OR EQUIVALENT | H53: 1 | I53: EA | J53: L | K53: 김응백 | N53: https://www.smckorea.co.kr/ppis/data/catalog/CM2-Z.pdf | Q53: Used Goods | S53: Green Purchase | T53: NONE | U53: Safety Management | W53: Posco Patent | Y53: Or Equivalent | Z53: OR EQUIVALENT | AA53: Cylinder Type | AB53: CWC(DA) | AC53: Mounting Type | AD53: CC | AE53: Bore Size | AF53: 40 | AG53: Rod Diameter | AH53: 14 | AI53: Stroke Length | AJ53: 350 | AK53: Pressure Rating | AL53: 10 | AM53: Model-1 | AN53: CDBM2B40-350-HN-A93 | AO53: Maker Name-1 | AP53: SMC | AQ53: Option-1 | AS53: Model-2 | AU53: Maker Name-2 | AV53: NONE | AW53: Option-2 | AY53: Model-3 | BA53: Maker Name-3 | BC53: Option-3 | BE53: Option & Others | BG53: Application | BH53: FOR 3CAL SAMPLE MACHINE "Y" HEAD
A54: Q4504927 | B54: ACTIVE | C54: 특정사양품(단수) | D54: Q4504927 | E54: Pneumatic Cylinder | F54: 포스코 | G54: CWC(DA),TC,40Dx16Dx125ST,10kgf/cm2,[CDA2T40-125Z-NW-M9BW/SMC] | H54: 2 | I54: SET | K54: 김경수 | N54: https://www.smckorea.co.kr/ | Q54: Used Goods | S54: Green Purchase | T54: NONE | U54: Safety Management | V54: NONE | W54: Posco Patent | Y54: Or Equivalent | AA54: Cylinder Type | AB54: CWC(DA) | AC54: Mounting Type | AD54: TC | AE54: Bore Size | AF54: 40 | AG54: Rod Diameter | AH54: 16 | AI54: Stroke Length | AJ54: 125 | AK54: Pressure Rating | AL54: 10 | AM54: Model-1 | AN54: CDA2T40-125Z-NW-M9BW | AO54: Maker Name-1 | AP54: SMC | AQ54: Option-1 | AS54: Model-2 | AU54: Maker Name-2 | AV54: NONE | AW54: Option-2 | AY54: Model-3 | BA54: Maker Name-3 | BC54: Option-3 | BE54: Option & Others | BG54: Application
A55: Q4655802 | B55: ACTIVE | C55: 특정사양품(단수) | D55: Q4655802 | E55: Pneumatic Cylinder | F55: 포스코 | G55: CWC(DA),TA,80Dx50Dx200ST,10kgf/cm2,[CDA2T80-KRT09KO-200Z-A54L3/SMC],FOR K1SMP 1RH SAMPLING PROBE LOADING CLAMP ROTATE,OR EQUIVALENT | H55: 1 | I55: EA | J55: L | K55: 남태현 | N55: https://www.smckorea.co.kr/ppis/data/catalog/CA2-Z.pdf | Q55: Used Goods | S55: Green Purchase | T55: NONE | U55: Safety Management | W55: Posco Patent | Y55: Or Equivalent | Z55: OR EQUIVALENT | AA55: Cylinder Type | AB55: CWC(DA) | AC55: Mounting Type | AD55: TA | AE55: Bore Size | AF55: 80 | AG55: Rod Diameter | AH55: 50 | AI55: Stroke Length | AJ55: 200 | AK55: Pressure Rating | AL55: 10 | AM55: Model-1 | AN55: CDA2T80-KRT09KO-200Z-A54L3 | AO55: Maker Name-1 | AP55: SMC | AQ55: Option-1 | AS55: Model-2 | AU55: Maker Name-2 | AV55: NONE | AW55: Option-2 | AY55: Model-3 | BA55: Maker Name-3 | BC55: Option-3 | BE55: Option & Others | BG55: Application | BH55: FOR K1SMP 1RH SAMPLING PROBE LOADING CLAMP ROTATE
A56: Q4658997 | B56: ACTIVE | C56: 특정사양품(단수) | D56: Q4658997 | E56: Pneumatic Cylinder | F56: 포스코 | G56: CWC(DA),CC,140Dx300ST,9.9kgf/cm2,[CS1DN140-KRT04K0-300-XC5/SMC],7GGL AL INGOT FEEDER,OR EQUIVALENT | H56: 1 | I56: SET | J56: L | K56: 김형종 | N56: https://www.smckorea.co.kr/ppis/data/catalog/CS1.pdf?ver=5456.764074372962 | Q56: Used Goods | S56: Green Purchase | T56: NONE | U56: Safety Management | W56: Posco Patent | Y56: Or Equivalent | Z56: OR EQUIVALENT | AA56: Cylinder Type | AB56: CWC(DA) | AC56: Mounting Type | AD56: CC | AE56: Bore Size | AF56: 140 | AG56: Rod Diameter | AH56: 9999 | AI56: Stroke Length | AJ56: 300 | AK56: Pressure Rating | AL56: 9.9 | AM56: Model-1 | AN56: CS1DN140-KRT04K0-300-XC5 | AO56: Maker Name-1 | AP56: SMC | AQ56: Option-1 | AS56: Model-2 | AU56: Maker Name-2 | AV56: NONE | AW56: Option-2 | AY56: Model-3 | BA56: Maker Name-3 | BC56: Option-3 | BE56: Option & Others | BG56: Application | BH56: 7GGL AL INGOT FEEDER
A57: Q4661659 | B57: ACTIVE | C57: 특정사양품(단수) | D57: Q4661659 | E57: Pneumatic Cylinder | F57: 포스코 | G57: CWC(DA),FA,30Dx100Dx220ST,[ACM-N FA 100-S220/KCC],FOR K1APL EXIT SIDE GUIDE OPEN CLOSE,OR EQUIVALENT | H57: 1 | I57: SET | J57: L | K57: 박원준 | N57: https://www.kccpr.com/bbs/board.php?bo_table=Pneumatic_cylinder&wr_id=2&sca=%ED%91%9C%EC%A4%80+%EC%8B%A4%EB%A6%B0%EB%8D%94 | Q57: Used Goods | S57: Green Purchase | T57: NONE | U57: Safety Management | W57: Posco Patent | Y57: Or Equivalent | Z57: OR EQUIVALENT | AA57: Cylinder Type | AB57: CWC(DA) | AC57: Mounting Type | AD57: FA | AE57: Bore Size | AF57: 30 | AG57: Rod Diameter | AH57: 100 | AI57: Stroke Length | AJ57: 220 | AK57: Pressure Rating | AL57: 9999 | AM57: Model-1 | AN57: ACM-N FA 100-S220 | AO57: Maker Name-1 | AP57: KCC | AQ57: Option-1 | AS57: Model-2 | AU57: Maker Name-2 | AV57: NONE | AW57: Option-2 | AY57: Model-3 | BA57: Maker Name-3 | BC57: Option-3 | BE57: Option & Others | BG57: Application | BH57: FOR K1APL EXIT SIDE GUIDE OPEN CLOSE
A58: Q4661796 | B58: ACTIVE | C58: 특정사양품(단수) | D58: Q4661796 | E58: Pneumatic Cylinder | F58: 포스코 | G58: CWC(DA),CA,250Dx150ST,[CS1CN250-KRD0368-150/SMC],FOR K1APL NO.6 TBR SNUBBER ROLL UP/DOWN,OR EQUIVALENT | H58: 1 | I58: SET | J58: L | K58: 박원준 | N58: https://www.smckorea.co.kr/ | Q58: Used Goods | S58: Green Purchase | T58: NONE | U58: Safety Management | W58: Posco Patent | Y58: Or Equivalent | Z58: OR EQUIVALENT | AA58: Cylinder Type | AB58: CWC(DA) | AC58: Mounting Type | AD58: CA | AE58: Bore Size | AF58: 250 | AG58: Rod Diameter | AH58: 9999 | AI58: Stroke Length | AJ58: 150 | AK58: Pressure Rating | AL58: 9999 | AM58: Model-1 | AN58: CS1CN250-KRD0368-150 | AO58: Maker Name-1 | AP58: SMC | AQ58: Option-1 | AS58: Model-2 | AU58: Maker Name-2 | AV58: NONE | AW58: Option-2 | AY58: Model-3 | BA58: Maker Name-3 | BC58: Option-3 | BE58: Option & Others | BG58: Application | BH58: FOR K1APL NO.6 TBR SNUBBER ROLL UP/DOWN
A59: Q4662525 | B59: ACTIVE | C59: 특정사양품(단수) | D59: Q4662525 | E59: Pneumatic Cylinder | F59: 포스코 | G59: CWC(DA),FL,40Dx250ST,10kgf/cm2,[CDM2L40-250Z-M9BL/SMC],FOR 1RCL EXIT SLEEVE MACHINE,OR EQUIVALENT | H59: 1 | I59: SET | J59: L | K59: 이규연 | N59: https://www.smckorea.co.kr/ppis/data/catalog/CM2-Z.pdf | Q59: Used Goods | S59: Green Purchase | T59: NONE | U59: Safety Management | W59: Posco Patent | Y59: Or Equivalent | Z59: OR EQUIVALENT | AA59: Cylinder Type | AB59: CWC(DA) | AC59: Mounting Type | AD59: FL | AE59: Bore Size | AF59: 40 | AG59: Rod Diameter | AH59: 9999 | AI59: Stroke Length | AJ59: 250 | AK59: Pressure Rating | AL59: 10 | AM59: Model-1 | AN59: CDM2L40-250Z-M9BL | AO59: Maker Name-1 | AP59: SMC | AQ59: Option-1 | AS59: Model-2 | AU59: Maker Name-2 | AV59: NONE | AW59: Option-2 | AY59: Model-3 | BA59: Maker Name-3 | BC59: Option-3 | BE59: Option & Others | BG59: Application | BH59: FOR 1RCL EXIT SLEEVE MACHINE
A60: Q4663082 | B60: ACTIVE | C60: 특정사양품(단수) | D60: Q4663082 | E60: Pneumatic Cylinder | F60: 포스코 | G60: CWC(DA),80Dx22Dx75ST,10kgf/cm2,[CQ2A80-75DMZ/SMC],FOR STSTHENS 1CPL PAPER UNWINDER,OR EQUIVALENT | H60: 1 | I60: EA | J60: L | K60: 김원길 | N60: https://www.smckorea.co.kr/ppis/data/catalog/CQ2-Z.pdf | Q60: Used Goods | S60: Green Purchase | T60: NONE | U60: Safety Management | W60: Posco Patent | Y60: Or Equivalent | Z60: OR EQUIVALENT | AA60: Cylinder Type | AB60: CWC(DA) | AC60: Mounting Type | AD60: OTHERS | AE60: Bore Size | AF60: 80 | AG60: Rod Diameter | AH60: 22 | AI60: Stroke Length | AJ60: 75 | AK60: Pressure Rating | AL60: 10 | AM60: Model-1 | AN60: CQ2A80-75DMZ | AO60: Maker Name-1 | AP60: SMC | AQ60: Option-1 | AS60: Model-2 | AU60: Maker Name-2 | AV60: NONE | AW60: Option-2 | AY60: Model-3 | BA60: Maker Name-3 | BC60: Option-3 | BE60: Option & Others | BG60: Application | BH60: FOR STSTHENS 1CPL PAPER UNWINDER
A61: Q4664034 | B61: ACTIVE | C61: 특정사양품(단수) | D61: Q4664034 | E61: Pneumatic Cylinder | F61: 포스코 | G61: CSA,180Dx45Dx850ST,10kgf/cm2,[CS1TN180-KRD036-8-850-XC15/SMC],OR EQUIVALENT | H61: 1 | I61: EA | J61: L | K61: 김원길 | N61: https://www.smckorea.co.kr/ppis/data/catalog/CS1.pdf | Q61: Used Goods | S61: Green Purchase | T61: NONE | U61: Safety Management | W61: Posco Patent | Y61: Or Equivalent | Z61: OR EQUIVALENT | AA61: Cylinder Type | AB61: CSA | AC61: Mounting Type | AD61: OTHERS | AE61: Bore Size | AF61: 180 | AG61: Rod Diameter | AH61: 45 | AI61: Stroke Length | AJ61: 850 | AK61: Pressure Rating | AL61: 10 | AM61: Model-1 | AN61: CS1TN180-KRD036-8-850-XC15 | AO61: Maker Name-1 | AP61: SMC | AQ61: Option-1 | AS61: Model-2 | AU61: Maker Name-2 | AV61: NONE | AW61: Option-2 | AY61: Model-3 | BA61: Maker Name-3 | BC61: Option-3 | BE61: Option & Others | BG61: Application
A62: Q4664750 | B62: ACTIVE | C62: 특정사양품(단수) | D62: Q4664750 | E62: Pneumatic Cylinder | F62: 포스코 | G62: CWC(DA),TC,80Dx25Dx150ST,10kgf/cm2,[CA2T80-KRT09KO-150Z-XC5/SMC],OR EQUIVALENT | H62: 1 | I62: EA | J62: L | K62: 이태호 | N62: https://www.smckorea.co.kr/ppis/data/catalog/CA2-Z.pdf | Q62: Used Goods | S62: Green Purchase | T62: NONE | U62: Safety Management | W62: Posco Patent | Y62: Or Equivalent | Z62: OR EQUIVALENT | AA62: Cylinder Type | AB62: CWC(DA) | AC62: Mounting Type | AD62: TC | AE62: Bore Size | AF62: 80 | AG62: Rod Diameter | AH62: 25 | AI62: Stroke Length | AJ62: 150 | AK62: Pressure Rating | AL62: 10 | AM62: Model-1 | AN62: CA2T80-KRT09KO-150Z-XC5 | AO62: Maker Name-1 | AP62: SMC | AQ62: Option-1 | AS62: Model-2 | AU62: Maker Name-2 | AV62: NONE | AW62: Option-2 | AY62: Model-3 | BA62: Maker Name-3 | BC62: Option-3 | BE62: Option & Others | BG62: Application
A63: Q4668346 | B63: ACTIVE | C63: 특정사양품(단수) | D63: Q4668346 | E63: Pneumatic Cylinder | F63: 포스코 | G63: 40Dx16Dx150ST,10.197162kgf/cm2,[MGPM40-150-HL-M9BZ/SMC],OR EQUIVALENT | H63: 1 | I63: SET | J63: L | K63: 이규연 | N63: https://www.smckorea.co.kr/homepage/ver3.5/product/catalogue_sub_detail.asp?no=954 | Q63: Used Goods | S63: Green Purchase | T63: NONE | U63: Safety Management | W63: Posco Patent | Y63: Or Equivalent | Z63: OR EQUIVALENT | AA63: Cylinder Type | AB63: OTHERS | AC63: Mounting Type | AD63: OTHERS | AE63: Bore Size | AF63: 40 | AG63: Rod Diameter | AH63: 16 | AI63: Stroke Length | AJ63: 150 | AK63: Pressure Rating | AL63: 10.197162 | AM63: Model-1 | AN63: MGPM40-150-HL-M9BZ | AO63: Maker Name-1 | AP63: SMC | AQ63: Option-1 | AS63: Model-2 | AU63: Maker Name-2 | AV63: NONE | AW63: Option-2 | AY63: Model-3 | BA63: Maker Name-3 | BC63: Option-3 | BE63: Option & Others | BG63: Application
A64: Q4667371 | B64: ACTIVE | C64: 특정사양품(단수) | D64: Q4667371 | E64: Pneumatic Cylinder | F64: 포스코 | G64: 25Dx25Dx370ST,8kgf/cm2,[MY1B25-370-A93/SMC],BANDING MACHINE PAD EJECT,OR EQUIVALENT | H64: 2 | I64: EA | K64: 전봉걸 | N64: https://www.smckorea.co.kr/ppis/data/catalog/MY1.pdf?ver=104.67060961103725 | Q64: Used Goods | S64: Green Purchase | T64: NONE | U64: Safety Management | W64: Posco Patent | Y64: Or Equivalent | Z64: OR EQUIVALENT | AA64: Cylinder Type | AB64: OTHERS | AC64: Mounting Type | AD64: OTHERS | AE64: Bore Size | AF64: 25 | AG64: Rod Diameter | AH64: 25 | AI64: Stroke Length | AJ64: 370 | AK64: Pressure Rating | AL64: 8 | AM64: Model-1 | AN64: MY1B25-370-A93 | AO64: Maker Name-1 | AP64: SMC | AQ64: Option-1 | AS64: Model-2 | AU64: Maker Name-2 | AV64: NONE | AW64: Option-2 | AY64: Model-3 | BA64: Maker Name-3 | BC64: Option-3 | BE64: Option & Others | BF64: BANDING MACHINE PAD EJECT | BG64: Application
A65: Q4510146 | B65: ACTIVE | C65: 특정사양품(단수) | D65: Q4510146 | E65: Pneumatic Cylinder | F65: 포스코 | G65: 16Dx10Dx100ST,[MGPL16-100Z/SMC],MGP COMPACT GUIDE CYLINDER,FOR CTL-640 MACHINE STACKER UNIT | H65: 2 | I65: EA | K65: 전봉걸 | N65: https://www.smcpneumatics.com/MGPL16-100.html | Q65: Used Goods | S65: Green Purchase | T65: NONE | U65: Safety Management | V65: NONE | W65: Posco Patent | Y65: Or Equivalent | AA65: Cylinder Type | AB65: OTHERS | AC65: Mounting Type | AD65: OTHERS | AE65: Bore Size | AF65: 16 | AG65: Rod Diameter | AH65: 10 | AI65: Stroke Length | AJ65: 100 | AK65: Pressure Rating | AL65: 9999 | AM65: Model-1 | AN65: MGPL16-100Z | AO65: Maker Name-1 | AP65: SMC | AQ65: Option-1 | AS65: Model-2 | AU65: Maker Name-2 | AV65: NONE | AW65: Option-2 | AY65: Model-3 | BA65: Maker Name-3 | BC65: Option-3 | BE65: Option & Others | BF65: MGP COMPACT GUIDE CYLINDER | BG65: Application | BH65: FOR CTL-640 MACHINE STACKER UNIT
A66: Q4669390 | B66: ACTIVE | C66: 특정사양품(단수) | D66: Q4669390 | E66: Pneumatic Cylinder | F66: 포스코 | G66: CWC(DA),CA,125Dx90Dx350ST,15kgf/cm2,[CDS1CN125-KRD0368-350-A54L/SMC],MAKER DWG NO:CDS1CN125-KRD0368-350-A54L,OR EQUIVALENT | H66: 1 | I66: EA | J66: L | K66: 김형종 | N66: https://www.smckorea.co.kr/ppis/data/catalog/CS1.pdf | Q66: Used Goods | S66: Green Purchase | T66: NONE | U66: Safety Management | W66: Posco Patent | Y66: Or Equivalent | Z66: OR EQUIVALENT | AA66: Cylinder Type | AB66: CWC(DA) | AC66: Mounting Type | AD66: CA | AE66: Bore Size | AF66: 125 | AG66: Rod Diameter | AH66: 90 | AI66: Stroke Length | AJ66: 350 | AK66: Pressure Rating | AL66: 15 | AM66: Model-1 | AN66: CDS1CN125-KRD0368-350-A54L | AO66: Maker Name-1 | AP66: SMC | AQ66: Option-1 | AS66: Model-2 | AU66: Maker Name-2 | AV66: NONE | AW66: Option-2 | AY66: Model-3 | BA66: Maker Name-3 | BC66: Option-3 | BE66: Option & Others | BF66: MAKER DWG NO:CDS1CN125-KRD0368-350-A54L | BG66: Application
A67: Q4037566 | B67: ACTIVE | C67: 특정사양품(단수) | D67: Q4037566 | E67: Pneumatic Cylinder | F67: 포스코 | G67: CWC(DA),TD,140Dx35Dx710ST,10kgf/cm2,[CDS1TN140-KRT04KO-710-XC14 +D-A54Z(2EA)+BT-12(2EA)/SMC],FOR 3CC SAMPLING DEVICE TILTING AIR CYLINDER,OR EQUIVALENT | H67: 3 | I67: SET | K67: 김영학 | N67: http://www.smckorea.co.kr/homepage/ver3.5/product/catalogue_sub_detail.asp?no=914# | Q67: Used Goods | S67: Green Purchase | T67: NONE | U67: Safety Management | V67: NONE | W67: Posco Patent | Y67: Or Equivalent | Z67: OR EQUIVALENT | AA67: Cylinder Type | AB67: CWC(DA) | AC67: Mounting Type | AD67: TD | AE67: Bore Size | AF67: 140 | AG67: Rod Diameter | AH67: 35 | AI67: Stroke Length | AJ67: 710 | AK67: Pressure Rating | AL67: 10 | AM67: Model-1 | AN67: CDS1TN140-KRT04KO-710-XC14 +D-A54Z(2EA)+BT-12(2EA) | AO67: Maker Name-1 | AP67: SMC | AQ67: Option-1 | AS67: Model-2 | AU67: Maker Name-2 | AV67: NONE | AW67: Option-2 | AY67: Model-3 | BA67: Maker Name-3 | BC67: Option-3 | BE67: Option & Others | BG67: Application | BH67: FOR 3CC SAMPLING DEVICE TILTING AIR CYLINDER
A68: Q4674415 | B68: ACTIVE | C68: 특정사양품(단수) | D68: Q4674415 | E68: Pneumatic Cylinder | F68: 포스코 | G68: 50Dx40Dx550ST,15kgf/cm2,[CDA2L50-550Z/SMC],FOR 2PL MOVING CAR,OR EQUIVALENT | H68: 1 | I68: EA | J68: L | K68: 장원령 | N68: https://www.smcpneumatics.com/CDA2L50-550Z-P3DWASC.html | Q68: Used Goods | S68: Green Purchase | T68: NONE | U68: Safety Management | W68: Posco Patent | Y68: Or Equivalent | Z68: OR EQUIVALENT | AA68: Cylinder Type | AB68: OTHERS | AC68: Mounting Type | AD68: OTHERS | AE68: Bore Size | AF68: 50 | AG68: Rod Diameter | AH68: 40 | AI68: Stroke Length | AJ68: 550 | AK68: Pressure Rating | AL68: 15 | AM68: Model-1 | AN68: CDA2L50-550Z | AO68: Maker Name-1 | AP68: SMC | AQ68: Option-1 | AS68: Model-2 | AU68: Maker Name-2 | AV68: NONE | AW68: Option-2 | AY68: Model-3 | BA68: Maker Name-3 | BC68: Option-3 | BE68: Option & Others | BG68: Application | BH68: FOR 2PL MOVING CAR
A69: Q4675089 | B69: ACTIVE | C69: 특정사양품(단수) | D69: Q4675089 | E69: Pneumatic Cylinder | F69: 포스코 | G69: CWC(DA),25Dx25Dx25ST,10kgf/cm2,[CDM2B25-25Z-A93L/SMC],FOR CHARPY IMPACT TESTER(STOPPER),OR EQUIVALENT | H69: 1 | I69: EA | J69: L | K69: 권우석 | N69: https://www.smckorea.co.kr/ | Q69: Used Goods | S69: Green Purchase | T69: NONE | U69: Safety Management | W69: Posco Patent | Y69: Or Equivalent | Z69: OR EQUIVALENT | AA69: Cylinder Type | AB69: CWC(DA) | AC69: Mounting Type | AD69: OTHERS | AE69: Bore Size | AF69: 25 | AG69: Rod Diameter | AH69: 25 | AI69: Stroke Length | AJ69: 25 | AK69: Pressure Rating | AL69: 10 | AM69: Model-1 | AN69: CDM2B25-25Z-A93L | AO69: Maker Name-1 | AP69: SMC | AQ69: Option-1 | AS69: Model-2 | AU69: Maker Name-2 | AV69: NONE | AW69: Option-2 | AY69: Model-3 | BA69: Maker Name-3 | BC69: Option-3 | BE69: Option & Others | BG69: Application | BH69: FOR CHARPY IMPACT TESTER(STOPPER)
A70: Q4675156 | B70: ACTIVE | C70: 특정사양품(단수) | D70: Q4675156 | E70: Pneumatic Cylinder | F70: 포스코 | G70: CWC(DA),16Dx16Dx25ST,7kgf/cm2,[CDJ2F16-25Z-A93L-B/SMC],FOR CHARPY IMPACT TESTER(SETTER),OR EQUIVALENT | H70: 1 | I70: EA | J70: L | K70: 권우석 | N70: https://www.smckorea.co.kr/ | Q70: Used Goods | S70: Green Purchase | T70: NONE | U70: Safety Management | W70: Posco Patent | Y70: Or Equivalent | Z70: OR EQUIVALENT | AA70: Cylinder Type | AB70: CWC(DA) | AC70: Mounting Type | AD70: OTHERS | AE70: Bore Size | AF70: 16 | AG70: Rod Diameter | AH70: 16 | AI70: Stroke Length | AJ70: 25 | AK70: Pressure Rating | AL70: 7 | AM70: Model-1 | AN70: CDJ2F16-25Z-A93L-B | AO70: Maker Name-1 | AP70: SMC | AQ70: Option-1 | AS70: Model-2 | AU70: Maker Name-2 | AV70: NONE | AW70: Option-2 | AY70: Model-3 | BA70: Maker Name-3 | BC70: Option-3 | BE70: Option & Others | BG70: Application | BH70: FOR CHARPY IMPACT TESTER(SETTER)
A71: Q4675326 | B71: ACTIVE | C71: 특정사양품(단수) | D71: Q4675326 | E71: Pneumatic Cylinder | F71: 포스코 | G71: CWC(DA),16Dx16Dx25ST,10kgf/cm2,[CDQSD16-25DM-A93L/SMC],FOR CHARPY IMPACT TESTER(HOLDER),OR EQUIVALENT | H71: 1 | I71: EA | J71: L | K71: 권우석 | N71: https://www.smckorea.co.kr/ | Q71: Used Goods | S71: Green Purchase | T71: NONE | U71: Safety Management | W71: Posco Patent | Y71: Or Equivalent | Z71: OR EQUIVALENT | AA71: Cylinder Type | AB71: CWC(DA) | AC71: Mounting Type | AD71: OTHERS | AE71: Bore Size | AF71: 16 | AG71: Rod Diameter | AH71: 16 | AI71: Stroke Length | AJ71: 25 | AK71: Pressure Rating | AL71: 10 | AM71: Model-1 | AN71: CDQSD16-25DM-A93L | AO71: Maker Name-1 | AP71: SMC | AQ71: Option-1 | AS71: Model-2 | AU71: Maker Name-2 | AV71: NONE | AW71: Option-2 | AY71: Model-3 | BA71: Maker Name-3 | BC71: Option-3 | BE71: Option & Others | BG71: Application | BH71: FOR CHARPY IMPACT TESTER(HOLDER)
A72: Q4675164 | B72: ACTIVE | C72: 특정사양품(단수) | D72: Q4675164 | E72: Pneumatic Cylinder | F72: 포스코 | G72: CWC(DA),25Dx25Dx30ST,7kgf/cm2,[CDUK25-30D-A93L/SMC],FOR CHARPY IMPACT TESTER(BURR REMOVER),OR EQUIVALENT | H72: 1 | I72: EA | J72: L | K72: 권우석 | N72: https://www.smckorea.co.kr/ | Q72: Used Goods | S72: Green Purchase | T72: NONE | U72: Safety Management | W72: Posco Patent | Y72: Or Equivalent | Z72: OR EQUIVALENT | AA72: Cylinder Type | AB72: CWC(DA) | AC72: Mounting Type | AD72: OTHERS | AE72: Bore Size | AF72: 25 | AG72: Rod Diameter | AH72: 25 | AI72: Stroke Length | AJ72: 30 | AK72: Pressure Rating | AL72: 7 | AM72: Model-1 | AN72: CDUK25-30D-A93L | AO72: Maker Name-1 | AP72: SMC | AQ72: Option-1 | AS72: Model-2 | AU72: Maker Name-2 | AV72: NONE | AW72: Option-2 | AY72: Model-3 | BA72: Maker Name-3 | BC72: Option-3 | BE72: Option & Others | BG72: Application | BH72: FOR CHARPY IMPACT TESTER(BURR REMOVER)
A73: Q2054050 | B73: ACTIVE | C73: 특정사양품(단수) | D73: Q2054050 | E73: Pneumatic Cylinder | F73: 포스코 | G73: CWC(DA),SD,63Dx20Dx40ST,9.9kgf/cm2,[MGQL63-40-Z73/SMC],FOR K4C 2CAL SIDE TRIMMER,OR EQUIVALENT | H73: 2 | I73: EA | K73: 이현식 | N73: https://www.smckorea.co.kr/ppis/data/catalog/MGQ.pdf?ver=7283.1060531038265 | Q73: Used Goods | S73: Green Purchase | T73: NONE | U73: Safety Management | W73: Posco Patent | Y73: Or Equivalent | Z73: OR EQUIVALENT | AA73: Cylinder Type | AB73: CWC(DA) | AC73: Mounting Type | AD73: SD | AE73: Bore Size | AF73: 63 | AG73: Rod Diameter | AH73: 20 | AI73: Stroke Length | AJ73: 40 | AK73: Pressure Rating | AL73: 9.9 | AM73: Model-1 | AN73: MGQL63-40-Z73 | AO73: Maker Name-1 | AP73: SMC | AQ73: Option-1 | AS73: Model-2 | AU73: Maker Name-2 | AV73: NONE | AW73: Option-2 | AY73: Model-3 | BA73: Maker Name-3 | BC73: Option-3 | BE73: Option & Others | BG73: Application | BH73: FOR K4C 2CAL SIDE TRIMMER
A74: Q4680486 | B74: ACTIVE | C74: 특정사양품(단수) | D74: Q4680486 | E74: Pneumatic Cylinder | F74: 포스코 | G74: CWC(DA),CA,63Dx20Dx64ST,10kgf/cm2,[CG1DN63-64-CJD00567/SMC],MAKER DWG NO:CG1DN63-64-CJD00567,FOR K1C 3RCL OILER DRIP PAN SWING CYLINDER,OR EQUIVALENT | H74: 1 | I74: EA | J74: L | K74: 이현식 | N74: https://www.smckorea.co.kr/ppis/data/domyun/CJD00567-AP..pdf | Q74: Used Goods | S74: Green Purchase | T74: NONE | U74: Safety Management | W74: Posco Patent | Y74: Or Equivalent | Z74: OR EQUIVALENT | AA74: Cylinder Type | AB74: CWC(DA) | AC74: Mounting Type | AD74: CA | AE74: Bore Size | AF74: 63 | AG74: Rod Diameter | AH74: 20 | AI74: Stroke Length | AJ74: 64 | AK74: Pressure Rating | AL74: 10 | AM74: Model-1 | AN74: CG1DN63-64-CJD00567 | AO74: Maker Name-1 | AP74: SMC | AQ74: Option-1 | AS74: Model-2 | AU74: Maker Name-2 | AV74: NONE | AW74: Option-2 | AY74: Model-3 | BA74: Maker Name-3 | BC74: Option-3 | BE74: Option & Others | BF74: MAKER DWG NO:CG1DN63-64-CJD00567 | BG74: Application | BH74: FOR K1C 3RCL OILER DRIP PAN SWING CYLINDER
A75: Q4683457 | B75: ACTIVE | C75: 특정사양품(단수) | D75: Q4683457 | E75: Pneumatic Cylinder | F75: 포스코 | G75: CA,100Dx30Dx300ST,10kgf/cm2,[CA2B100-300Z/SMC],2FINEX RTO,OR EQUIVALENT | H75: 1 | I75: SET | J75: L | K75: 문승준 | N75: https://www.smcpneumatics.com/CA2B100-300Z.html | Q75: Used Goods | S75: Green Purchase | T75: NONE | U75: Safety Management | W75: Posco Patent | Y75: Or Equivalent | Z75: OR EQUIVALENT | AA75: Cylinder Type | AB75: OTHERS | AC75: Mounting Type | AD75: CA | AE75: Bore Size | AF75: 100 | AG75: Rod Diameter | AH75: 30 | AI75: Stroke Length | AJ75: 300 | AK75: Pressure Rating | AL75: 10 | AM75: Model-1 | AN75: CA2B100-300Z | AO75: Maker Name-1 | AP75: SMC | AQ75: Option-1 | AS75: Model-2 | AU75: Maker Name-2 | AV75: NONE | AW75: Option-2 | AY75: Model-3 | BA75: Maker Name-3 | BC75: Option-3 | BE75: Option & Others | BG75: Application | BH75: 2FINEX RTO
A76: Q4683941 | B76: ACTIVE | C76: 특정사양품(단수) | D76: Q4683941 | E76: Pneumatic Cylinder | F76: 포스코 | G76: CWC(DA),FA,63Dx20Dx600ST,10kgf/cm2,[MDBF63-600Z-W-M9BW/SMC],OR EQUIVALENT | H76: 1 | I76: EA | J76: L | K76: 김대환 | N76: https://www.smckorea.co.kr/ > 제품 검색 > MDBF63-600Z-W-M9BW | Q76: Used Goods | S76: Green Purchase | T76: NONE | U76: Safety Management | W76: Posco Patent | Y76: Or Equivalent | Z76: OR EQUIVALENT | AA76: Cylinder Type | AB76: CWC(DA) | AC76: Mounting Type | AD76: FA | AE76: Bore Size | AF76: 63 | AG76: Rod Diameter | AH76: 20 | AI76: Stroke Length | AJ76: 600 | AK76: Pressure Rating | AL76: 10 | AM76: Model-1 | AN76: MDBF63-600Z-W-M9BW | AO76: Maker Name-1 | AP76: SMC | AQ76: Option-1 | AS76: Model-2 | AU76: Maker Name-2 | AV76: NONE | AW76: Option-2 | AY76: Model-3 | BA76: Maker Name-3 | BC76: Option-3 | BE76: Option & Others | BG76: Application
A77: Q4688206 | B77: ACTIVE | C77: 특정사양품(단수) | D77: Q4688206 | E77: Pneumatic Cylinder | F77: 포스코 | G77: CWC(DA),SD,50Dx20Dx100ST,10.2kgf/cm2,[CDQ2A50-100DCZ-M9BWL/SMC],OR EQUIVALENT | H77: 1 | I77: EA | J77: L | K77: 정석운 | N77: https://www.smckorea.co.kr/ | Q77: Used Goods | S77: Green Purchase | T77: NONE | U77: Safety Management | W77: Posco Patent | Y77: Or Equivalent | Z77: OR EQUIVALENT | AA77: Cylinder Type | AB77: CWC(DA) | AC77: Mounting Type | AD77: SD | AE77: Bore Size | AF77: 50 | AG77: Rod Diameter | AH77: 20 | AI77: Stroke Length | AJ77: 100 | AK77: Pressure Rating | AL77: 10.2 | AM77: Model-1 | AN77: CDQ2A50-100DCZ-M9BWL | AO77: Maker Name-1 | AP77: SMC | AQ77: Option-1 | AS77: Model-2 | AU77: Maker Name-2 | AV77: NONE | AW77: Option-2 | AY77: Model-3 | BA77: Maker Name-3 | BC77: Option-3 | BE77: Option & Others | BG77: Application
A78: Q4280848 | B78: ACTIVE | C78: 특정사양품(단수) | D78: Q4280848 | E78: Pneumatic Cylinder | F78: 포스코 | G78: CWC(DA),FA,160Dx40Dx80ST,10kgf/cm2,[C95S F160-80/SMC],FOR 3APL RINSE WRRINGER ROLL,OR EQUIVALENT | H78: 2 | I78: SET | K78: 이규연 | N78: http://www.smckorea.co.kr/ppis/data/catalog/C95_large.pdf | Q78: Used Goods | S78: Green Purchase | T78: NONE | U78: Safety Management | V78: NONE | W78: Posco Patent | Y78: Or Equivalent | Z78: OR EQUIVALENT | AA78: Cylinder Type | AB78: CWC(DA) | AC78: Mounting Type | AD78: FA | AE78: Bore Size | AF78: 160 | AG78: Rod Diameter | AH78: 40 | AI78: Stroke Length | AJ78: 80 | AK78: Pressure Rating | AL78: 10 | AM78: Model-1 | AN78: C95S F160-80 | AO78: Maker Name-1 | AP78: SMC | AQ78: Option-1 | AS78: Model-2 | AU78: Maker Name-2 | AV78: NONE | AW78: Option-2 | AY78: Model-3 | BA78: Maker Name-3 | BC78: Option-3 | BE78: Option & Others | BG78: Application | BH78: FOR 3APL RINSE WRRINGER ROLL
A79: Q4687826 | B79: ACTIVE | C79: 특정사양품(단수) | D79: Q4687826 | E79: Pneumatic Cylinder | F79: 포스코 | G79: CSB,32Dx12Dx50ST,10kgf/cm2,[CDG1BA32-50Z1/SMC],OR EQUIVALENT | H79: 2 | I79: EA | J79: L | K79: 전봉걸 | N79: https://www.smckorea.co.kr/homepage/ver3.5/srch/search.asp | Q79: Used Goods | S79: Green Purchase | T79: NONE | U79: Safety Management | W79: Posco Patent | Y79: Or Equivalent | Z79: OR EQUIVALENT | AA79: Cylinder Type | AB79: CSB | AC79: Mounting Type | AD79: OTHERS | AE79: Bore Size | AF79: 32 | AG79: Rod Diameter | AH79: 12 | AI79: Stroke Length | AJ79: 50 | AK79: Pressure Rating | AL79: 10 | AM79: Model-1 | AN79: CDG1BA32-50Z1 | AO79: Maker Name-1 | AP79: SMC | AQ79: Option-1 | AS79: Model-2 | AT79: UNKNOWN | AU79: Maker Name-2 | AV79: NONE | AW79: Option-2 | AY79: Model-3 | AZ79: UNKNOWN | BA79: Maker Name-3 | BB79: NONE | BC79: Option-3 | BE79: Option & Others | BG79: Application
A80: Q4696036 | B80: ACTIVE | C80: 특정사양품(단수) | D80: Q4696036 | E80: Pneumatic Cylinder | F80: 포스코 | G80: CWC(DA),CB,200Dx50Dx1800ST,10kgf/cm2,[CDS1DN200-KRD0368-1800-X1034/SMC],FOR 1EGL BANDING MACHINE HEAD,OR EQUIVALENT | H80: 1 | I80: EA | J80: L | K80: 박무균 | N80: https://www.smckorea.co.kr/ppis/data/catalog/CS1.pdf | Q80: Used Goods | S80: Green Purchase | T80: NONE | U80: Safety Management | W80: Posco Patent | Y80: Or Equivalent | Z80: OR EQUIVALENT | AA80: Cylinder Type | AB80: CWC(DA) | AC80: Mounting Type | AD80: CB | AE80: Bore Size | AF80: 200 | AG80: Rod Diameter | AH80: 50 | AI80: Stroke Length | AJ80: 1800 | AK80: Pressure Rating | AL80: 10 | AM80: Model-1 | AN80: CDS1DN200-KRD0368-1800-X1034 | AO80: Maker Name-1 | AP80: SMC | AQ80: Option-1 | AS80: Model-2 | AT80: UNKNOWN | AU80: Maker Name-2 | AV80: NONE | AW80: Option-2 | AY80: Model-3 | AZ80: UNKNOWN | BA80: Maker Name-3 | BB80: NONE | BC80: Option-3 | BE80: Option & Others | BG80: Application | BH80: FOR 1EGL BANDING MACHINE HEAD
A81: Q4697437 | B81: ACTIVE | C81: 특정사양품(단수) | D81: Q4697437 | E81: Pneumatic Cylinder | F81: 포스코 | G81: CWC(DA),TC,200Dx246ST,[CDS1TN200-246K-A54/SMC],OR EQUIVALENT | H81: 1 | I81: SET | J81: L | K81: 구건웅 | Q81: Used Goods | S81: Green Purchase | T81: NONE | U81: Safety Management | W81: Posco Patent | Y81: Or Equivalent | Z81: OR EQUIVALENT | AA81: Cylinder Type | AB81: CWC(DA) | AC81: Mounting Type | AD81: TC | AE81: Bore Size | AF81: 200 | AG81: Rod Diameter | AH81: 9999 | AI81: Stroke Length | AJ81: 246 | AK81: Pressure Rating | AL81: 9999 | AM81: Model-1 | AN81: CDS1TN200-246K-A54 | AO81: Maker Name-1 | AP81: SMC | AQ81: Option-1 | AS81: Model-2 | AT81: UNKNOWN | AU81: Maker Name-2 | AV81: NONE | AW81: Option-2 | AY81: Model-3 | AZ81: UNKNOWN | BA81: Maker Name-3 | BB81: NONE | BC81: Option-3 | BE81: Option & Others | BG81: Application

Sheet 모터 9개
A1: Q-Code | B1: =COUNTA(B2:B1048576) -> 26 | C1: 그룹사명 | D1: 품명 | E1: Purchase Category | F1: 표준화섹션담당자 | G1: 자재특성구분 | H1: 처리상태 | I1: 조달 | J1: 통화 | K1: 사양 및 규격 | L1: 단위 | M1: 계약형태 | N1: Model-1 | O1: Maker-1 | P1: Option-1 | Q1: Model-2 | R1: Maker-2 | S1: Option-2 | T1: Model-3 | U1: Maker-3 | V1: Option-3 | W1: Option & Others | X1: Application | Y1: 도면번호1 | Z1: 첨부도면파일명 | AA1: 첨부자재규격서명 | AB1: Model-1 첨부파일명 | AC1: Model-2 첨부파일명 | AD1: Model-3 첨부파일명 | AE1: Model-1 첨부URL1 | AF1: Model-1 첨부URL2 | AG1: Model-2 첨부URL1 | AH1: 첨부Image파일명1 | AI1: 첨부Image파일명2 | AJ1: 신청자명 | AK1: 신청자 소속 | AL1: 신청자 E-mail | AM1: 요청자명 | AN1: 요청자 소속 | AO1: 요청자 E-mail | AP1: 최종검토일 | AQ1: 년도 | AR1: 단수승인사유 | AS1: 검토자 메모 | AT1: 월별Inactive대상
A2: Q4632857 | B2: 0 | C2: 포스코 | D2: AC Geared Motor | E2: AC Geared Motor (Ready) | F2: 전아람 | G2: 특정사양품(단수) | H2: ACTIVE | I2: L | J2: KRW | K2: 4P,5.5kW,440V,60Hz,1780rpm,I=1/43,F_class,200H,70D,380X275,CAGE,[DHHM8-9175-43/HANA MECHANICAL&ELECTRICAL],MAKER DWG NO:DHHM8-9175-43,OR EQUIVALENT | L2: SET | M2: STANDARD | N2: DHHM8-9175-43 | O2: HANA MECHANICAL&ELECTRICAL | R2: NONE | W2: MAKER DWG NO:DHHM8-9175-43 | AB2: [메이커도면] 원료시험실 Conveyor Motor_DHHM8-9175-43_20240319080822371.pdf | AH2: 이미지 원료시험실 기어드모터_20240319080822407.jpg | AJ2: 장요한 | AK2: (포항)EIC기술부 자동화설비정비섹션 | AL2: dreamjyh1@posco.co.kr | AM2: 이규문 | AN2: (포항)EIC기술부 자동화설비정비섹션 | AO2: kmlee0907@posco.co.kr | AP2: 2024-03-19 13:03:56 | AQ2: 2024 | AR2: 차후 재점검 | AS2: Q4553771등 유사item 검색하였으나, 유사품 없고 V등이 상이하여 확인후 승인. | AT2: N
A3: Q4685650 | B3: 0 | C3: 포스코 | D3: AC Geared Motor | E3: AC Geared Motor (Ready) | F3: 전아람 | G3: 특정사양품(단수) | H3: ACTIVE | I3: L | J3: KRW | K3: 4P,0.09kW,220V,60Hz,1600rpm,I=1/60,63H,18D,VVVF,[S9I90GTH-E/SPG]+WITH HEAD S9KD60B,OR EQUIVALENT | L3: SET | M3: STANDARD | N3: S9I90GTH-E | O3: SPG | P3: WITH HEAD S9KD60B | R3: NONE | AB3: [카탈로그]S9I90GTH-E_20250901090909524.pptx | AE3: http://www.spg.co.kr/sub/product.php?cate1=AC&gc_id=10 | AH3: S9I90GTH-E_20250901132618414.jpg | AJ3: 김원길 | AK3: (포항)압연설비2부 STS압연정비섹션 | AL3: 855956@posco.co.kr | AM3: 변현룡 | AN3: (포항)압연설비2부 STS압연정비섹션 | AO3: sbehsy@posco.co.kr | AP3: 2025-09-03 09:09:07 | AQ3: 2025 | AR3: 차후 재점검 | AS3: 기 설치된 물품의 호환성을 위해 특정 사양으로 등록건 확인,_x000D_ Q4454434 등 유사item 검색하였으나 감속비 등 옵션 일부 상이함 확인하였으며, 유사/동일품 없음 확인후 승인합니다._x000D_ (특정 사양품감축 관련) 차후 입고시 스케치, 현물 확인을 통한 도면화, 일반 사양화, 복수화 전환 검토 요청 부탁드립니다. 감사합니다._x000D_ _x000D_ | AT3: N
A4: Q4636710 | B4: 0 | C4: 포스코 | D4: AC Geared Motor | E4: AC Geared Motor (Ready) | F4: 전아람 | G4: 특정사양품(단수) | H4: ACTIVE | I4: L | J4: KRW | K4: 4P,2.2kW,254/440V,60Hz,1765/174rpm,I=1/10.15,155F_class,115H,30D,165X135,CAGE,IP54,[R47 DRN100L4/SEW],IE3,OR EQUIVALENT | L4: SET | M4: STANDARD | N4: R47 DRN100L4 | O4: SEW | R4: NONE | AB4: 003_20240404165529457.pdf | AE4: https://download.sew-eurodrive.com/download/pdf_u/22742654.pdf | AH4: d_20240404165456956.jpg | AJ4: 김기봉 | AK4: (광양)압연설비2부 냉연정비2섹션 | AM4: 정정훈 | AN4: (광양)압연설비2부 냉연정비2섹션 | AO4: jeonghoon717@posco.co.kr | AP4: 2024-04-25 10:04:20 | AQ4: 2024 | AR4: 차후 재점검 | AS4: Q4368598, Q4596341 등 유사item 검색하였으나, 감속비가 다르고 일부 사양이 다름 확인하고 승인합니다. _x000D_ _x000D_ _x000D_ _x000D_ | AT4: N
A5: Q4688576 | B5: 0 | C5: 포스코 | D5: AC Geared Motor | E5: AC Geared Motor (Ready) | F5: 전아람 | G5: 특정사양품(단수) | H5: ACTIVE | I5: L | J5: KRW | K5: 4P,0.75kW,440V,60Hz,1735/35rpm,I=1/50,F_class,120H,8D,145X190,CAGE,IP55,[RPH/HYOSUNG],IE3,OR EQUIVALENT | L5: EA | M5: STANDARD | N5: RPH | O5: HYOSUNG | R5: NONE | AB5: 13. RPH_0.75KW_4P_50_1 (효성중공업)_20250929103559629.pdf | AE5: https://www.hyosungheavyindustries.com/kr/data/geared-motors | AH5: 13. RPH10 50-4 (기어드 모터)_20250929103559811.jpg | AJ5: 정석운 | AK5: 설비자재구매실 자재구매그룹 광양자재지원섹션 | AL5: sambar@posco.co.kr | AM5: 김선재 | AN5: 설비자재구매실 자재구매그룹 광양자재지원섹션 | AO5: jae7668@posco.co.kr | AP5: 2025-09-29 16:09:47 | AQ5: 2025 | AR5: 차후 재점검 | AT5: N
A6: Q4688577 | B6: 0 | C6: 포스코 | D6: AC Geared Motor | E6: AC Geared Motor (Ready) | F6: 전아람 | G6: 특정사양품(단수) | H6: ACTIVE | I6: L | J6: KRW | K6: 4P,0.75kW,440V,60Hz,1735/35rpm,I=50,F_class,120H,8D,145X190,CAGE,IP55,[RPH/HYOSUNG]+BRAKE,IE3,OR EQUIVALENT | L6: EA | M6: STANDARD | N6: RPH | O6: HYOSUNG | P6: BRAKE | R6: NONE | AB6: 13.14.15. 기어드 모터_20250929103825992.pptx_20250929103825992.pptx | AE6: https://www.hyosungheavyindustries.com/kr/data/geared-motors | AH6: 14. RPH10 50-4(ACB) (기어드 모터)_20250929103826123.jpg | AJ6: 정석운 | AK6: 설비자재구매실 자재구매그룹 광양자재지원섹션 | AL6: sambar@posco.co.kr | AM6: 김선재 | AN6: 설비자재구매실 자재구매그룹 광양자재지원섹션 | AO6: jae7668@posco.co.kr | AP6: 2025-09-29 16:09:10 | AQ6: 2025 | AR6: 차후 재점검 | AT6: N
A7: Q4688760 | B7: 0 | C7: 포스코 | D7: AC Geared Motor | E7: AC Geared Motor (Ready) | F7: 전아람 | G7: 특정사양품(단수) | H7: ACTIVE | I7: L | J7: KRW | K7: 4P,1.5kW,440V,60Hz,1750/29.2rpm,I=60,F_class,135H,10D,190X235,CAGE,IP55,[RPH/HYOSUNG]+BRAKE,OR EQUIVALENT | L7: EA | M7: STANDARD | N7: RPH | O7: HYOSUNG | P7: BRAKE | R7: NONE | AB7: 15. RPH_1.5KW_4P_60_1 (효성중공업)_20250929103706073.pdf | AE7: https://www.hyosungheavyindustries.com/kr/data/geared-motors | AH7: 15. (기어드 모터)_20250929103706247.jpg | AJ7: 정석운 | AK7: 설비자재구매실 자재구매그룹 광양자재지원섹션 | AL7: sambar@posco.co.kr | AM7: 김선재 | AN7: 설비자재구매실 자재구매그룹 광양자재지원섹션 | AO7: jae7668@posco.co.kr | AP7: 2025-09-30 16:09:43 | AQ7: 2025 | AR7: 차후 재점검 | AS7: 기 설치된 물품의 호환성을 위해 특정 사양으로 등록건 확인,_x000D_ 유사 item 검색하였으나, 유사/동일품 없음 확인후 승인합니다._x000D_ (특정 사양품감축 관련) 차후 입고시 스케치, 현물 확인을 통한 도면화, 일반 사양화, 복수화 전환 검토 요청 부탁드립니다. 감사합니다._x000D_ | AT7: N
A8: Q4622968 | B8: 0 | C8: 포스코 | D8: AC Geared Motor | E8: AC Geared Motor (Ready) | F8: 전아람 | G8: 특정사양품(단수) | H8: ACTIVE | I8: L | J8: KRW | K8: 4P,1.5kW,440V,60Hz,1750rpm,I=1/15,F_class,153H,38D,150X215,TE,[HLA020101057587/HYOSUNG]+WITH AC 220V MAGNETIC DISC BRAKE(SHB 142 A, SAMHWAN),OR EQUIVALENT | L8: EA | M8: STANDARD | N8: HLA020101057587 | O8: HYOSUNG | P8: WITH AC 220V MAGNETIC DISC BRAKE(SHB 142 A, SAMHWAN) | R8: NONE | AB8: 220928_APL 1ERT, 1DSRT, 2DSRT -AGM 3set(1.5kW)_P-건설(브레이크)_20240110103813827.pdf | AH8: HLA020101057587_20240110103813748.png | AJ8: 이용우 | AK8: (광양)압연설비2부 전기강판정비섹션 | AL8: yongwoo@posco.co.kr | AM8: 강경묵 | AN8: (광양)압연설비2부 전기강판정비섹션 | AO8: muk@posco.co.kr | AP8: 2024-01-17 09:01:45 | AQ8: 2024 | AR8: 차후 재점검 | AT8: N
A9: Q4621316 | B9: 0 | C9: 포스코 | D9: AC Geared Motor | E9: AC Geared Motor (Ready) | F9: 전아람 | G9: 특정사양품(단수) | H9: ACTIVE | I9: L | J9: KRW | K9: 4P,3.7kW,440V,60Hz,1755rpm,I=1/120,F_class,270H,70D,350X360,TE,[HMA01080000560/HYOSUNG]+WITH AC 220V MAGNETIC DISC BRAKE(SHB 155 A, SAMHWAN),OR EQUIVALENT | L9: EA | M9: STANDARD | N9: HMA01080000560 | O9: HYOSUNG | P9: WITH AC 220V MAGNETIC DISC BRAKE(SHB 155 A, SAMHWAN) | R9: NONE | AB9: 220928_APL EDS, DDS-AGM-04,01 2set(3.7kW)_P-건설(브레이크)_20240109150839397.pdf | AH9: HMA0180000560_20240109150601499.png | AJ9: 이용우 | AK9: (광양)압연설비2부 전기강판정비섹션 | AL9: yongwoo@posco.co.kr | AM9: 강경묵 | AN9: (광양)압연설비2부 전기강판정비섹션 | AO9: muk@posco.co.kr | AP9: 2024-01-17 09:01:58 | AQ9: 2024 | AR9: 차후 재점검 | AS9: 유사품 검색 및 사양 검증용 자료 확인후 승인합니다._x000D_ | AT9: N
A10: Q4621046 | B10: 0 | C10: 포스코 | D10: AC Geared Motor | E10: AC Geared Motor (Ready) | F10: 전아람 | G10: 특정사양품(단수) | H10: ACTIVE | I10: L | J10: KRW | K10: 4P,5.5kW,440V,60Hz,1775rpm,I=1/100,F_class,270H,70D,350X360,TE,[HLA020101057590/HYOSUNG]+WITH AC 220V MAGNETIC DISC BRAKE(SHB 175 A, SAMHWAN),IP55,OR EQUIVALENT | L10: EA | M10: STANDARD | N10: HLA020101057590 | O10: HYOSUNG | P10: WITH AC 220V MAGNETIC DISC BRAKE(SHB 175 A, SAMHWAN) | R10: NONE | W10: IP55 | AB10: 220928_APL EDS-AGM-01 1set(5.5kW)_P-건설(브레이크)_20240110110841287.pdf | AH10: HLA020101057590_20240110110841222.png | AJ10: 이용우 | AK10: (광양)압연설비2부 전기강판정비섹션 | AL10: yongwoo@posco.co.kr | AM10: 강경묵 | AN10: (광양)압연설비2부 전기강판정비섹션 | AO10: muk@posco.co.kr | AP10: 2024-01-11 17:01:24 | AQ10: 2024 | AR10: 차후 재점검 | AS10: 유사품 검색 및 사양 검증용 자료 확인후 승인합니다._x000D_ (특정 사양품감축 관련) 차후 입고시 스케치, 현물 확인을 통한 도면화,일반 사양화,복수화 전환 검토 요청 부탁드립니다._x000D_ | AT10: N
A11: Q4620473 | B11: 0 | C11: 포스코 | D11: AC Geared Motor | E11: AC Geared Motor (Ready) | F11: 전아람 | G11: 특정사양품(단수) | H11: ACTIVE | I11: L | J11: KRW | K11: 4P,7.5kW,440V,60Hz,1770rpm,I=1/60,F_class,270H,70D,350X360,TE,[HLA020101057591/HYOSUNG]+WITH AC 220V MAGNETIC DISC BRAKE(SHB 185 A, SAMHWAN),OR EQUIVALENT | L11: EA | M11: STANDARD | N11: HLA020101057591 | O11: HYOSUNG | P11: WITH AC 220V MAGNETIC DISC BRAKE(SHB 185 A, SAMHWAN) | R11: NONE | AB11: 220928_APL EDS-AGM-02,03 2set(7.5kW)_P-건설(브레이크)_20240110111348538.pdf | AH11: HLA020101057587_20240110111348485.png | AJ11: 이용우 | AK11: (광양)압연설비2부 전기강판정비섹션 | AL11: yongwoo@posco.co.kr | AM11: 강경묵 | AN11: (광양)압연설비2부 전기강판정비섹션 | AO11: muk@posco.co.kr | AP11: 2024-01-17 09:01:33 | AQ11: 2024 | AR11: 차후 재점검 | AS11: 유사품 검색 및 사양 검증용 자료 확인후 승인합니다._x000D_ (특정 사양품감축 관련) 차후 입고시 스케치, 현물 확인을 통한 도면화,일반 사양화,복수화 전환 검토 요청 부탁드립니다._x000D_ | AT11: N
A12: Q4620571 | B12: 0 | C12: 포스코 | D12: AC Geared Motor | E12: AC Geared Motor (Ready) | F12: 전아람 | G12: 특정사양품(단수) | H12: ACTIVE | I12: L | J12: KRW | K12: 4P,2.2kW,440V,60Hz,1765rpm,I=1/30,F_class,172H,45D,172X232,TE,[HLA020101057588/HYOSUNG]+WITH AC 220V MAGNETIC DISC BRAKE(SHB 150 A, SAMHWAN),OR EQUIVALENT | L12: EA | M12: STANDARD | N12: HLA020101057588 | O12: HYOSUNG | P12: WITH AC 220V MAGNETIC DISC BRAKE(SHB 150 A, SAMHWAN) | R12: NONE | AB12: 220928_APL FLT-AGM-02,03 6set(2.2kW)_P-건설(브레이크)_20240110111127081.pdf | AH12: HLA020101057587_20240110111127027.png | AJ12: 이용우 | AK12: (광양)압연설비2부 전기강판정비섹션 | AL12: yongwoo@posco.co.kr | AM12: 강경묵 | AN12: (광양)압연설비2부 전기강판정비섹션 | AO12: muk@posco.co.kr | AP12: 2024-01-15 09:01:28 | AQ12: 2024 | AR12: 차후 재점검 | AT12: N
A13: Q4621315 | B13: 0 | C13: 포스코 | D13: AC Geared Motor | E13: AC Geared Motor (Ready) | F13: 전아람 | G13: 특정사양품(단수) | H13: ACTIVE | I13: L | J13: KRW | K13: 4P,3.7kW,440V,60Hz,1755rpm,I=1/90,F_class,270H,70D,350X360,IP55,[HMA01080000560/HYOSUNG]+WITH AC 220V MAGNETIC DISC BRAKE(SHB 155 A, SAMHWAN),IE3,OR EQUIVALENT | L13: EA | M13: STANDARD | N13: HMA01080000560 | O13: HYOSUNG | P13: WITH AC 220V MAGNETIC DISC BRAKE(SHB 155 A, SAMHWAN) | R13: NONE | AB13: 221011_APL ESR-AM-01,02 2set(3.7KW)_P-건설(브레이크)_20240110110451185.pdf | AH13: HMA01080000560_20240110110451122.png | AJ13: 이용우 | AK13: (광양)압연설비2부 전기강판정비섹션 | AL13: yongwoo@posco.co.kr | AM13: 강경묵 | AN13: (광양)압연설비2부 전기강판정비섹션 | AO13: muk@posco.co.kr | AP13: 2024-01-11 17:01:07 | AQ13: 2024 | AR13: 차후 재점검 | AS13: 유사품 검색 및 사양 검증용 자료 확인후 승인합니다._x000D_ | AT13: N
